Workbook

Sheet Landing Page
B2: 🚀 RELEASE DESK | D2: Enterprise Release Management Platform | F2: 👤 Welcome, Release Manager | 📅 28/06/2026
B4: 📊 Dashboard | C4: 📋 Releases | D4: 📅 Calendar | E4: ⚠️ Risks | F4: ⚙️ Admin
B6: ⚡ 3 releases scheduled this week | ⚠️ 2 active conflicts require attention | 🔔 5 pending approvals
G7: 📊 QUICK STATS
B8: Welcome to Release Desk
B9: Your central hub for managing releases, tracking risks, coordinating environments, and ensuring successful deployments across the enterprise.
G10: 📋 Total Releases
G11: =COUNTA(Releases!A:A)-1 -> 83
B12: 📱 Main Pages
G13: ⚠️ Active Conflicts
B14: 📊 | D14: 📋 | F14: 📅 | G14: =COUNTIF(Releases!O:O,"*CONFLICT*") -> 27
B15: DASHBOARD | D15: RELEASES | F15: CALENDAR
G16: 🚫 Blocked Releases
B17: Real-time KPIs, metrics, | D17: Manage all releases, | F17: CAB meetings, releases, | G17: =COUNTIF(Releases!N:N,"Blocked") -> 1
B18: and release health overview | D18: status, priorities & blockers | F18: and key milestones
G19: 🔴 P1 Critical
B20: 🖥️ | D20: ⚠️ | F20: 🔗 | G20: =COUNTIF(Releases!H:H,"P1*") -> 11
B21: ENV BOOKING | D21: RISK | F21: DEPENDENCIES
G22: 📝 Pending CAB
B23: Reserve & manage test | D23: Risk scores, factors, | F23: Track inter-release | G23: =COUNTIF(Releases!N:N,"Pending CAB") -> 1
B24: and UAT environments | D24: and mitigation tracking | F24: and system dependencies
G25: ✅ Approved
B26: ✅ | D26: 🏖️ | F26: 📉 | G26: =COUNTIF(Releases!N:N,"Approved") -> 4
B27: APPROVALS | D27: LEAVE CALENDAR | F27: DRIFT
B29: CAB approvals and | D29: Team availability and | F29: Schedule drift analysis
B30: sign-off workflows | D30: resource scheduling | F30: and timeline tracking | G30: ⚡ QUICK ACTIONS
B32: 🔔 Operational Monitoring
G33: ➕ Create New Release
B34: 🔔 | D34: 🚨 | F34: 🖥️
B35: MONITORING | D35: INCIDENTS | F35: APP STATUS | G35: 📅 Book Environment
B37: System alerts, health | D37: P1/P2 incident tracking | F37: Real-time application | G37: 📋 View All Risks
B38: checks & notifications | D38: and resolution status | F38: availability by env
G39: 🔔 Active Alerts
B40: 🔧 | D40: 📦 | F40: 🗺️
B41: MAINTENANCE | D41: VERSIONS | F41: SYSTEM MAPPING | G41: 📊 Open Dashboard
B43: Scheduled outages | D43: Version history and | F43: Environment and system | G43: Last refreshed:
B44: and maintenance windows | D44: deployment tracking | F44: architecture views | G44: =NOW() -> 46203.002
B46: 📚 Reference Data (Admin Only)
B48: 📱 Applications | D48: 👥 Users | F48: ⚙️ Admin Config
B49: Master app registry | D49: User directory | F49: Release Managers & Super Admins
B51: 🎨 Color Guide: | C51: 🟢 Dashboard | D51: 🟠 Core Release Pages | E51: 🔵 Monitoring & Ops | F51: 🟣 Resources | 🔴 Risk | 🔷 Reference Data
B54: Release Desk v1.0 | Enterprise Release Management Platform | © 2026 | F54: 📧 Support | 📖 Documentation | 🔒 Security

Sheet Dashboard
B1: RELEASE DESK DASHBOARD | J1: Last Refresh:
B2: 🔍 FILTERS | C2: Time Period: | D2: This Month | E2: Department: | F2: All | G2: Application: | H2: All | J2: =NOW() -> 46203.002
B4: 📦 RELEASE PIPELINE | E4: ⚠️ RELEASE CONFLICTS & RISKS | H4: 🖥️ ENVIRONMENT BOOKINGS
B5: Total Releases | C5: {=SUMPRODUCT( (Releases!A5:A84<>"")* (IF($D$2="All Time",1,IF($D$2="Today",Releases!J5:J84=TODAY(),IF($D$2="This Week",(Releases!J5:J84>=TODAY())*(Releases!J5:J84<=TODAY()+7),IF($D$2="This Month",(Releases!J5:J84>=TODAY())*(Releases!J5:J84<=TODAY()+30),(Releases!J5:J84>=DATE(YEAR(TODAY()),1,1))*(Releases!J5:J84<=DATE(YEAR(TODAY()),12,31)))))))* (IF($F$2="All",1,Releases!C5:C84=$F$2))* (IF($H$2="All",1,Releases!D5:D84=$H$2)) )} -> 9 | E5: Active Conflicts | F5: {=SUMPRODUCT( (ISNUMBER(SEARCH("CONFLICT",Releases!O5:O84)))* (IF($D$2="All Time",1,IF($D$2="Today",Releases!J5:J84=TODAY(),IF($D$2="This Week",(Releases!J5:J84>=TODAY())*(Releases!J5:J84<=TODAY()+7),IF($D$2="This Month",(Releases!J5:J84>=TODAY())*(Releases!J5:J84<=TODAY()+30),(Releases!J5:J84>=DATE(YEAR(TODAY()),1,1))*(Releases!J5:J84<=DATE(YEAR(TODAY()),12,31)))))))* (IF($F$2="All",1,Releases!C5:C84=$F$2))* (IF($H$2="All",1,Releases!D5:D84=$H$2)) )} -> 6 | H5: Env Conflicts | I5: {=SUMPRODUCT( (ISNUMBER(SEARCH("CONFLICT",'Env booking'!U5:U115)))* (IF($F$2="All",1,'Env booking'!D5:D115=$F$2)) )} -> 26
B6: Blocked | C6: {=SUMPRODUCT( (Releases!N5:N84="Blocked")* (IF($D$2="All Time",1,IF($D$2="Today",Releases!J5:J84=TODAY(),IF($D$2="This Week",(Releases!J5:J84>=TODAY())*(Releases!J5:J84<=TODAY()+7),IF($D$2="This Month",(Releases!J5:J84>=TODAY())*(Releases!J5:J84<=TODAY()+30),(Releases!J5:J84>=DATE(YEAR(TODAY()),1,1))*(Releases!J5:J84<=DATE(YEAR(TODAY()),12,31)))))))* (IF($F$2="All",1,Releases!C5:C84=$F$2))* (IF($H$2="All",1,Releases!D5:D84=$H$2)) )} -> 1 | E6: Critical Risk (Score 20+) | F6: {=SUMPRODUCT( (Risk!J5:J81>=20)* (IF($F$2="All",1,Risk!C5:C81=$F$2)) )} -> 2 | H6: Env Bookings Active | I6: {=SUMPRODUCT( ('Env booking'!A5:A115<>"")* (IF($F$2="All",1,'Env booking'!D5:D115=$F$2)) )} -> 101
B7: Approved | C7: {=SUMPRODUCT( (Releases!N5:N84="Approved")* (IF($D$2="All Time",1,IF($D$2="Today",Releases!J5:J84=TODAY(),IF($D$2="This Week",(Releases!J5:J84>=TODAY())*(Releases!J5:J84<=TODAY()+7),IF($D$2="This Month",(Releases!J5:J84>=TODAY())*(Releases!J5:J84<=TODAY()+30),(Releases!J5:J84>=DATE(YEAR(TODAY()),1,1))*(Releases!J5:J84<=DATE(YEAR(TODAY()),12,31)))))))* (IF($F$2="All",1,Releases!C5:C84=$F$2))* (IF($H$2="All",1,Releases!D5:D84=$H$2)) )} -> 4 | E7: High Risk (Score 15-19) | F7: {=SUMPRODUCT( (Risk!J5:J81>=15)*(Risk!J5:J81<20)* (IF($F$2="All",1,Risk!C5:C81=$F$2)) )} -> 3
B8: Testing | C8: {=SUMPRODUCT( (Releases!N5:N84="Testing")* (IF($D$2="All Time",1,IF($D$2="Today",Releases!J5:J84=TODAY(),IF($D$2="This Week",(Releases!J5:J84>=TODAY())*(Releases!J5:J84<=TODAY()+7),IF($D$2="This Month",(Releases!J5:J84>=TODAY())*(Releases!J5:J84<=TODAY()+30),(Releases!J5:J84>=DATE(YEAR(TODAY()),1,1))*(Releases!J5:J84<=DATE(YEAR(TODAY()),12,31)))))))* (IF($F$2="All",1,Releases!C5:C84=$F$2))* (IF($H$2="All",1,Releases!D5:D84=$H$2)) )} -> 3 | E8: Medium Risk (Score 10-14) | F8: {=SUMPRODUCT( (Risk!J5:J81>=10)*(Risk!J5:J81<15)* (IF($F$2="All",1,Risk!C5:C81=$F$2)) )} -> 12 | H8: 🔗 DEPENDENCIES
B9: Planning | C9: {=SUMPRODUCT( (Releases!N5:N84="Planning")* (IF($D$2="All Time",1,IF($D$2="Today",Releases!J5:J84=TODAY(),IF($D$2="This Week",(Releases!J5:J84>=TODAY())*(Releases!J5:J84<=TODAY()+7),IF($D$2="This Month",(Releases!J5:J84>=TODAY())*(Releases!J5:J84<=TODAY()+30),(Releases!J5:J84>=DATE(YEAR(TODAY()),1,1))*(Releases!J5:J84<=DATE(YEAR(TODAY()),12,31)))))))* (IF($F$2="All",1,Releases!C5:C84=$F$2))* (IF($H$2="All",1,Releases!D5:D84=$H$2)) )} -> 0 | E9: Low Risk (Score <10) | F9: {=SUMPRODUCT( (Risk!J5:J81>0)*(Risk!J5:J81<10)* (IF($F$2="All",1,Risk!C5:C81=$F$2)) )} -> 14 | H9: Blocked Dependencies | I9: {=SUMPRODUCT( (Dependencies!G4:G91="Blocked")* (IF($F$2="All",1,Dependencies!#REF!=$F$2)) )} -> 5
B10: Draft | C10: {=SUMPRODUCT( (Releases!N5:N84="Draft")* (IF($D$2="All Time",1,IF($D$2="Today",Releases!J5:J84=TODAY(),IF($D$2="This Week",(Releases!J5:J84>=TODAY())*(Releases!J5:J84<=TODAY()+7),IF($D$2="This Month",(Releases!J5:J84>=TODAY())*(Releases!J5:J84<=TODAY()+30),(Releases!J5:J84>=DATE(YEAR(TODAY()),1,1))*(Releases!J5:J84<=DATE(YEAR(TODAY()),12,31)))))))* (IF($F$2="All",1,Releases!C5:C84=$F$2))* (IF($H$2="All",1,Releases!D5:D84=$H$2)) )} -> 0 | H10: Total Dependencies | I10: {=SUMPRODUCT( (Dependencies!A4:A91<>"")* (IF($F$2="All",1,Dependencies!#REF!=$F$2)) )} -> 69
B11: Pending CAB | C11: {=SUMPRODUCT( (Releases!N5:N84="Pending CAB")* (IF($D$2="All Time",1,IF($D$2="Today",Releases!J5:J84=TODAY(),IF($D$2="This Week",(Releases!J5:J84>=TODAY())*(Releases!J5:J84<=TODAY()+7),IF($D$2="This Month",(Releases!J5:J84>=TODAY())*(Releases!J5:J84<=TODAY()+30),(Releases!J5:J84>=DATE(YEAR(TODAY()),1,1))*(Releases!J5:J84<=DATE(YEAR(TODAY()),12,31)))))))* (IF($F$2="All",1,Releases!C5:C84=$F$2))* (IF($H$2="All",1,Releases!D5:D84=$H$2)) )} -> 1 | E11: 📋 CAB & APPROVALS
B12: P1 - Critical | C12: {=SUMPRODUCT( (Releases!H5:H84="P1 - Critical")* (IF($D$2="All Time",1,IF($D$2="Today",Releases!J5:J84=TODAY(),IF($D$2="This Week",(Releases!J5:J84>=TODAY())*(Releases!J5:J84<=TODAY()+7),IF($D$2="This Month",(Releases!J5:J84>=TODAY())*(Releases!J5:J84<=TODAY()+30),(Releases!J5:J84>=DATE(YEAR(TODAY()),1,1))*(Releases!J5:J84<=DATE(YEAR(TODAY()),12,31)))))))* (IF($F$2="All",1,Releases!C5:C84=$F$2))* (IF($H$2="All",1,Releases!D5:D84=$H$2)) )} -> 2 | E12: CAB Meetings (Next 7 Days) | F12: {=SUMPRODUCT( (Calendar!E15:E180="CAB MEETING")* (IF($D$2="All Time",1,IF($D$2="Today",Calendar!C15:C180=TODAY(),IF($D$2="This Week",(Calendar!C15:C180>=TODAY())*(Calendar!C15:C180<=TODAY()+7),IF($D$2="This Month",(Calendar!C15:C180>=TODAY())*(Calendar!C15:C180<=TODAY()+30),(Calendar!C15:C180>=DATE(YEAR(TODAY()),1,1))*(Calendar!C15:C180<=DATE(YEAR(TODAY()),12,31))))))) )} -> 9 | H12: 👥 RESOURCE AVAILABILITY
B13: P2 - High | C13: {=SUMPRODUCT( (Releases!H5:H84="P2 - High")* (IF($D$2="All Time",1,IF($D$2="Today",Releases!J5:J84=TODAY(),IF($D$2="This Week",(Releases!J5:J84>=TODAY())*(Releases!J5:J84<=TODAY()+7),IF($D$2="This Month",(Releases!J5:J84>=TODAY())*(Releases!J5:J84<=TODAY()+30),(Releases!J5:J84>=DATE(YEAR(TODAY()),1,1))*(Releases!J5:J84<=DATE(YEAR(TODAY()),12,31)))))))* (IF($F$2="All",1,Releases!C5:C84=$F$2))* (IF($H$2="All",1,Releases!D5:D84=$H$2)) )} -> 4 | E13: Pending Approvals | F13: {=SUMPRODUCT( ((Releases!W5:W84="CAB Submitted")+(Releases!W5:W84="On Hold"))* (IF($D$2="All Time",1,IF($D$2="Today",Releases!J5:J84=TODAY(),IF($D$2="This Week",(Releases!J5:J84>=TODAY())*(Releases!J5:J84<=TODAY()+7),IF($D$2="This Month",(Releases!J5:J84>=TODAY())*(Releases!J5:J84<=TODAY()+30),(Releases!J5:J84>=DATE(YEAR(TODAY()),1,1))*(Releases!J5:J84<=DATE(YEAR(TODAY()),12,31)))))))* (IF($F$2="All",1,Releases!C5:C84=$F$2))* (IF($H$2="All",1,Releases!D5:D84=$H$2)) )} -> 2 | H13: Staff on Leave Today | I13: =COUNTIFS('Leave Calendar'!F4:F93,"<="&TODAY(),'Leave Calendar'!G4:G93,">="&TODAY()) -> 1
B14: P3 - Medium | C14: {=SUMPRODUCT( (Releases!H5:H84="P3 - Medium")* (IF($D$2="All Time",1,IF($D$2="Today",Releases!J5:J84=TODAY(),IF($D$2="This Week",(Releases!J5:J84>=TODAY())*(Releases!J5:J84<=TODAY()+7),IF($D$2="This Month",(Releases!J5:J84>=TODAY())*(Releases!J5:J84<=TODAY()+30),(Releases!J5:J84>=DATE(YEAR(TODAY()),1,1))*(Releases!J5:J84<=DATE(YEAR(TODAY()),12,31)))))))* (IF($F$2="All",1,Releases!C5:C84=$F$2))* (IF($H$2="All",1,Releases!D5:D84=$H$2)) )} -> 2 | H14: Staff on Leave (7 Days) | I14: {=SUMPRODUCT( ('Leave Calendar'!F4:F93<=TODAY()+IF($D$2="Today",0,IF($D$2="This Week",7,IF($D$2="This Month",30,365))))* ('Leave Calendar'!G4:G93>=TODAY()) )} -> 4
B15: P4 - Low | C15: {=SUMPRODUCT( (Releases!H5:H84="P4 - Low")* (IF($D$2="All Time",1,IF($D$2="Today",Releases!J5:J84=TODAY(),IF($D$2="This Week",(Releases!J5:J84>=TODAY())*(Releases!J5:J84<=TODAY()+7),IF($D$2="This Month",(Releases!J5:J84>=TODAY())*(Releases!J5:J84<=TODAY()+30),(Releases!J5:J84>=DATE(YEAR(TODAY()),1,1))*(Releases!J5:J84<=DATE(YEAR(TODAY()),12,31)))))))* (IF($F$2="All",1,Releases!C5:C84=$F$2))* (IF($H$2="All",1,Releases!D5:D84=$H$2)) )} -> 1
B17: 🚨 MONITORING ALERTS | E17: 🔥 INCIDENTS | H17: 📊 APPLICATION AVAILABILITY
B18: Critical Alerts (Active) | C18: {=SUMPRODUCT( ('Monitoring Alerts'!F:F="Critical")* ('Monitoring Alerts'!J:J="Active")* (IF($D$2="All Time",1,IF($D$2="Today",'Monitoring Alerts'!B:B>=TODAY(),IF($D$2="This Week",('Monitoring Alerts'!B:B>=TODAY()-7),IF($D$2="This Month",('Monitoring Alerts'!B:B>=TODAY()-30),('Monitoring Alerts'!B:B>=DATE(YEAR(TODAY()),1,1)))))))* (IF($F$2="All",1,'Monitoring Alerts'!D:D=$F$2))* (IF($H$2="All",1,'Monitoring Alerts'!C:C=$H$2)) )} -> 11 | E18: P1 Incidents (Active) | F18: {=SUMPRODUCT( (Incidents!E:E="P1")* (Incidents!G:G<>"Resolved")* (IF($D$2="All Time",1,IF($D$2="Today",Incidents!B:B>=TODAY(),IF($D$2="This Week",(Incidents!B:B>=TODAY()-7),IF($D$2="This Month",(Incidents!B:B>=TODAY()-30),(Incidents!B:B>=DATE(YEAR(TODAY()),1,1)))))))* (IF($F$2="All",1,Incidents!D:D=$F$2))* (IF($H$2="All",1,Incidents!C:C=$H$2)) )} -> 4 | H18: Apps Down - Production | I18: {=SUMPRODUCT( ('Application Status'!C:C="Prod")* ('Application Status'!D:D="Down")* (IF($F$2="All",1,'Application Status'!B:B=$F$2))* (IF($H$2="All",1,'Application Status'!A:A=$H$2)) )} -> 4
B19: Warning Alerts (Active) | C19: {=SUMPRODUCT( ('Monitoring Alerts'!F:F="Warning")* ('Monitoring Alerts'!J:J="Active")* (IF($D$2="All Time",1,IF($D$2="Today",'Monitoring Alerts'!B:B>=TODAY(),IF($D$2="This Week",('Monitoring Alerts'!B:B>=TODAY()-7),IF($D$2="This Month",('Monitoring Alerts'!B:B>=TODAY()-30),('Monitoring Alerts'!B:B>=DATE(YEAR(TODAY()),1,1)))))))* (IF($F$2="All",1,'Monitoring Alerts'!D:D=$F$2))* (IF($H$2="All",1,'Monitoring Alerts'!C:C=$H$2)) )} -> 16 | E19: P2 Incidents (Active) | F19: {=SUMPRODUCT( (Incidents!E:E="P2")* (Incidents!G:G<>"Resolved")* (IF($D$2="All Time",1,IF($D$2="Today",Incidents!B:B>=TODAY(),IF($D$2="This Week",(Incidents!B:B>=TODAY()-7),IF($D$2="This Month",(Incidents!B:B>=TODAY()-30),(Incidents!B:B>=DATE(YEAR(TODAY()),1,1)))))))* (IF($F$2="All",1,Incidents!D:D=$F$2))* (IF($H$2="All",1,Incidents!C:C=$H$2)) )} -> 6 | H19: Apps Degraded - Production | I19: {=SUMPRODUCT( ('Application Status'!C:C="Prod")* ('Application Status'!D:D="Degraded")* (IF($F$2="All",1,'Application Status'!B:B=$F$2))* (IF($H$2="All",1,'Application Status'!A:A=$H$2)) )} -> 5
B20: Info Alerts (Active) | C20: {=SUMPRODUCT( ('Monitoring Alerts'!F:F="Info")* ('Monitoring Alerts'!J:J="Active")* (IF($D$2="All Time",1,IF($D$2="Today",'Monitoring Alerts'!B:B>=TODAY(),IF($D$2="This Week",('Monitoring Alerts'!B:B>=TODAY()-7),IF($D$2="This Month",('Monitoring Alerts'!B:B>=TODAY()-30),('Monitoring Alerts'!B:B>=DATE(YEAR(TODAY()),1,1)))))))* (IF($F$2="All",1,'Monitoring Alerts'!D:D=$F$2))* (IF($H$2="All",1,'Monitoring Alerts'!C:C=$H$2)) )} -> 2 | E20: P3 Incidents (Active) | F20: {=SUMPRODUCT( (Incidents!E:E="P3")* (Incidents!G:G<>"Resolved")* (IF($D$2="All Time",1,IF($D$2="Today",Incidents!B:B>=TODAY(),IF($D$2="This Week",(Incidents!B:B>=TODAY()-7),IF($D$2="This Month",(Incidents!B:B>=TODAY()-30),(Incidents!B:B>=DATE(YEAR(TODAY()),1,1)))))))* (IF($F$2="All",1,Incidents!D:D=$F$2))* (IF($H$2="All",1,Incidents!C:C=$H$2)) )} -> 3 | H20: Apps Healthy - Production | I20: {=SUMPRODUCT( ('Application Status'!C:C="Prod")* ('Application Status'!D:D="Healthy")* (IF($F$2="All",1,'Application Status'!B:B=$F$2))* (IF($H$2="All",1,'Application Status'!A:A=$H$2)) )} -> 11
B21: Acknowledged | C21: {=SUMPRODUCT( ('Monitoring Alerts'!J:J="Acknowledged")* (IF($D$2="All Time",1,IF($D$2="Today",'Monitoring Alerts'!B:B>=TODAY(),IF($D$2="This Week",('Monitoring Alerts'!B:B>=TODAY()-7),IF($D$2="This Month",('Monitoring Alerts'!B:B>=TODAY()-30),('Monitoring Alerts'!B:B>=DATE(YEAR(TODAY()),1,1)))))))* (IF($F$2="All",1,'Monitoring Alerts'!D:D=$F$2))* (IF($H$2="All",1,'Monitoring Alerts'!C:C=$H$2)) )} -> 5 | E21: Investigating | F21: {=SUMPRODUCT( (Incidents!G:G="Investigating")* (IF($D$2="All Time",1,IF($D$2="Today",Incidents!B:B>=TODAY(),IF($D$2="This Week",(Incidents!B:B>=TODAY()-7),IF($D$2="This Month",(Incidents!B:B>=TODAY()-30),(Incidents!B:B>=DATE(YEAR(TODAY()),1,1)))))))* (IF($F$2="All",1,Incidents!D:D=$F$2))* (IF($H$2="All",1,Incidents!C:C=$H$2)) )} -> 4 | H21: Apps Down - Lower Env | I21: {=SUMPRODUCT( ('Application Status'!C:C<>"Prod")* ('Application Status'!D:D="Down")* ('Application Status'!A:A<>"")* (IF($F$2="All",1,'Application Status'!B:B=$F$2))* (IF($H$2="All",1,'Application Status'!A:A=$H$2)) )} -> 5
B22: Resolved (Last 24h) | C22: {=SUMPRODUCT( ('Monitoring Alerts'!J:J="Resolved")* ('Monitoring Alerts'!B:B>=TODAY()-1)* (IF($F$2="All",1,'Monitoring Alerts'!D:D=$F$2))* (IF($H$2="All",1,'Monitoring Alerts'!C:C=$H$2)) )} -> 0 | E22: Resolved (Last 24h) | F22: {=SUMPRODUCT( (Incidents!G:G="Resolved")* (Incidents!B:B>=TODAY()-1)* (IF($F$2="All",1,Incidents!D:D=$F$2))* (IF($H$2="All",1,Incidents!C:C=$H$2)) )} -> 0 | H22: Apps Degraded - Lower Env | I22: {=SUMPRODUCT( ('Application Status'!C:C<>"Prod")* ('Application Status'!D:D="Degraded")* ('Application Status'!A:A<>"")* (IF($F$2="All",1,'Application Status'!B:B=$F$2))* (IF($H$2="All",1,'Application Status'!A:A=$H$2)) )} -> 3
B23: Total Active Alerts | C23: {=SUMPRODUCT( (('Monitoring Alerts'!J:J="Active")+('Monitoring Alerts'!J:J="Acknowledged"))* (IF($D$2="All Time",1,IF($D$2="Today",'Monitoring Alerts'!B:B>=TODAY(),IF($D$2="This Week",('Monitoring Alerts'!B:B>=TODAY()-7),IF($D$2="This Month",('Monitoring Alerts'!B:B>=TODAY()-30),('Monitoring Alerts'!B:B>=DATE(YEAR(TODAY()),1,1)))))))* (IF($F$2="All",1,'Monitoring Alerts'!D:D=$F$2))* (IF($H$2="All",1,'Monitoring Alerts'!C:C=$H$2)) )} -> 34 | E23: Total Active Incidents | F23: {=SUMPRODUCT( ((Incidents!G:G="Active")+(Incidents!G:G="Investigating")+(Incidents!G:G="Acknowledged"))* (IF($D$2="All Time",1,IF($D$2="Today",Incidents!B:B>=TODAY(),IF($D$2="This Week",(Incidents!B:B>=TODAY()-7),IF($D$2="This Month",(Incidents!B:B>=TODAY()-30),(Incidents!B:B>=DATE(YEAR(TODAY()),1,1)))))))* (IF($F$2="All",1,Incidents!D:D=$F$2))* (IF($H$2="All",1,Incidents!C:C=$H$2)) )} -> 13 | H23: Total App-Env Records | I23: {=SUMPRODUCT( ('Application Status'!A:A<>"")* ('Application Status'!A:A<>"Application")* (IF($F$2="All",1,'Application Status'!B:B=$F$2))* (IF($H$2="All",1,'Application Status'!A:A=$H$2)) )} -> 85
B26: 🔧 PLANNED MAINTENANCE | E26: ❄️ CHANGE FREEZE | H26: 📈 QUICK STATS
B27: Scheduled Today | C27: {=SUMPRODUCT( ('Planned Maintenance'!B:B=TODAY())* (IF($F$2="All",1,'Planned Maintenance'!H:H=$F$2)) )} -> 2 | E27: Quarter-End Freeze | F27: {=SUMPRODUCT( (ISNUMBER(SEARCH("Quarter",Releases!T5:T84)))* (IF($D$2="All Time",1,IF($D$2="Today",Releases!J5:J84=TODAY(),IF($D$2="This Week",(Releases!J5:J84>=TODAY())*(Releases!J5:J84<=TODAY()+7),IF($D$2="This Month",(Releases!J5:J84>=TODAY())*(Releases!J5:J84<=TODAY()+30),(Releases!J5:J84>=DATE(YEAR(TODAY()),1,1))*(Releases!J5:J84<=DATE(YEAR(TODAY()),12,31)))))))* (IF($F$2="All",1,Releases!C5:C84=$F$2))* (IF($H$2="All",1,Releases!D5:D84=$H$2)) )} -> 1 | H27: Releases This Week | I27: {=SUMPRODUCT( (Releases!A5:A84<>"")* (Releases!J5:J84>=TODAY())* (Releases!J5:J84<=TODAY()+7)* (IF($F$2="All",1,Releases!C5:C84=$F$2))* (IF($H$2="All",1,Releases!D5:D84=$H$2)) )} -> 5
B28: ="DB Refreshes ("&IF($D$2="Today","Today",IF($D$2="This Week","7 Days",IF($D$2="This Month","30 Days",IF($D$2="This Year","Year","All"))))&")" -> DB Refreshes (30 Days) | C28: {=SUMPRODUCT( ('Planned Maintenance'!E:E="DB Refresh")* ('Planned Maintenance'!B:B>=TODAY())* ('Planned Maintenance'!B:B<=TODAY()+IF($D$2="Today",0,IF($D$2="This Week",7,IF($D$2="This Month",30,365))))* (IF($F$2="All",1,'Planned Maintenance'!H:H=$F$2)) )} -> 4 | E28: Year-End Freeze | F28: {=SUMPRODUCT( (ISNUMBER(SEARCH("Year",Releases!T5:T84)))* (IF($D$2="All Time",1,IF($D$2="Today",Releases!J5:J84=TODAY(),IF($D$2="This Week",(Releases!J5:J84>=TODAY())*(Releases!J5:J84<=TODAY()+7),IF($D$2="This Month",(Releases!J5:J84>=TODAY())*(Releases!J5:J84<=TODAY()+30),(Releases!J5:J84>=DATE(YEAR(TODAY()),1,1))*(Releases!J5:J84<=DATE(YEAR(TODAY()),12,31)))))))* (IF($F$2="All",1,Releases!C5:C84=$F$2))* (IF($H$2="All",1,Releases!D5:D84=$H$2)) )} -> 0 | H28: Releases This Month | I28: {=SUMPRODUCT( (Releases!A5:A84<>"")* (Releases!J5:J84>=TODAY())* (Releases!J5:J84<=TODAY()+30)* (IF($F$2="All",1,Releases!C5:C84=$F$2))* (IF($H$2="All",1,Releases!D5:D84=$H$2)) )} -> 9
B29: ="Vendor Windows ("&IF($D$2="Today","Today",IF($D$2="This Week","7 Days",IF($D$2="This Month","30 Days",IF($D$2="This Year","Year","All"))))&")" -> Vendor Windows (30 Days) | C29: {=SUMPRODUCT( ('Planned Maintenance'!E:E="Vendor Maintenance")* ('Planned Maintenance'!B:B>=TODAY())* ('Planned Maintenance'!B:B<=TODAY()+IF($D$2="Today",0,IF($D$2="This Week",7,IF($D$2="This Month",30,365))))* (IF($F$2="All",1,'Planned Maintenance'!H:H=$F$2)) )} -> 4 | E29: Audit Freeze | F29: {=SUMPRODUCT( (ISNUMBER(SEARCH("Audit",Releases!T5:T84)))* (IF($D$2="All Time",1,IF($D$2="Today",Releases!J5:J84=TODAY(),IF($D$2="This Week",(Releases!J5:J84>=TODAY())*(Releases!J5:J84<=TODAY()+7),IF($D$2="This Month",(Releases!J5:J84>=TODAY())*(Releases!J5:J84<=TODAY()+30),(Releases!J5:J84>=DATE(YEAR(TODAY()),1,1))*(Releases!J5:J84<=DATE(YEAR(TODAY()),12,31)))))))* (IF($F$2="All",1,Releases!C5:C84=$F$2))* (IF($H$2="All",1,Releases!D5:D84=$H$2)) )} -> 0 | H29: With Rollback Plan Ready | I29: {=SUMPRODUCT( (Releases!Y5:Y84="Ready")* (IF($D$2="All Time",1,IF($D$2="Today",Releases!J5:J84=TODAY(),IF($D$2="This Week",(Releases!J5:J84>=TODAY())*(Releases!J5:J84<=TODAY()+7),IF($D$2="This Month",(Releases!J5:J84>=TODAY())*(Releases!J5:J84<=TODAY()+30),(Releases!J5:J84>=DATE(YEAR(TODAY()),1,1))*(Releases!J5:J84<=DATE(YEAR(TODAY()),12,31)))))))* (IF($F$2="All",1,Releases!C5:C84=$F$2))* (IF($H$2="All",1,Releases!D5:D84=$H$2)) )} -> 4
B30: ="Full Outages ("&IF($D$2="Today","Today",IF($D$2="This Week","7 Days",IF($D$2="This Month","30 Days",IF($D$2="This Year","Year","All"))))&")" -> Full Outages (30 Days) | C30: {=SUMPRODUCT( ('Planned Maintenance'!I:I="Full Outage")* ('Planned Maintenance'!B:B>=TODAY())* ('Planned Maintenance'!B:B<=TODAY()+IF($D$2="Today",0,IF($D$2="This Week",7,IF($D$2="This Month",30,365))))* (IF($F$2="All",1,'Planned Maintenance'!H:H=$F$2)) )} -> 7 | E30: Holiday Freeze | F30: {=SUMPRODUCT( (ISNUMBER(SEARCH("Holiday",Releases!T5:T84)))* (IF($D$2="All Time",1,IF($D$2="Today",Releases!J5:J84=TODAY(),IF($D$2="This Week",(Releases!J5:J84>=TODAY())*(Releases!J5:J84<=TODAY()+7),IF($D$2="This Month",(Releases!J5:J84>=TODAY())*(Releases!J5:J84<=TODAY()+30),(Releases!J5:J84>=DATE(YEAR(TODAY()),1,1))*(Releases!J5:J84<=DATE(YEAR(TODAY()),12,31)))))))* (IF($F$2="All",1,Releases!C5:C84=$F$2))* (IF($H$2="All",1,Releases!D5:D84=$H$2)) )} -> 0 | H30: Rollback At Risk | I30: {=SUMPRODUCT( (Releases!Y5:Y84="At Risk")* (IF($D$2="All Time",1,IF($D$2="Today",Releases!J5:J84=TODAY(),IF($D$2="This Week",(Releases!J5:J84>=TODAY())*(Releases!J5:J84<=TODAY()+7),IF($D$2="This Month",(Releases!J5:J84>=TODAY())*(Releases!J5:J84<=TODAY()+30),(Releases!J5:J84>=DATE(YEAR(TODAY()),1,1))*(Releases!J5:J84<=DATE(YEAR(TODAY()),12,31)))))))* (IF($F$2="All",1,Releases!C5:C84=$F$2))* (IF($H$2="All",1,Releases!D5:D84=$H$2)) )} -> 1
B31: ="Total Maintenance ("&IF($D$2="Today","Today",IF($D$2="This Week","7 Days",IF($D$2="This Month","30 Days",IF($D$2="This Year","Year","All"))))&")" -> Total Maintenance (30 Days) | C31: {=SUMPRODUCT( ('Planned Maintenance'!A:A<>"")* ('Planned Maintenance'!A:A<>"Maintenance ID")* ('Planned Maintenance'!B:B>=TODAY())* ('Planned Maintenance'!B:B<=TODAY()+IF($D$2="Today",0,IF($D$2="This Week",7,IF($D$2="This Month",30,365))))* (IF($F$2="All",1,'Planned Maintenance'!H:H=$F$2)) )} -> 15 | E31: Total Frozen Releases | F31: {=SUMPRODUCT( (Releases!T5:T84<>"")* (IF($D$2="All Time",1,IF($D$2="Today",Releases!J5:J84=TODAY(),IF($D$2="This Week",(Releases!J5:J84>=TODAY())*(Releases!J5:J84<=TODAY()+7),IF($D$2="This Month",(Releases!J5:J84>=TODAY())*(Releases!J5:J84<=TODAY()+30),(Releases!J5:J84>=DATE(YEAR(TODAY()),1,1))*(Releases!J5:J84<=DATE(YEAR(TODAY()),12,31)))))))* (IF($F$2="All",1,Releases!C5:C84=$F$2))* (IF($H$2="All",1,Releases!D5:D84=$H$2)) )} -> 1 | H31: Avg Go-Live Checklist % | I31: =IFERROR(TEXT(AVERAGEIF(Releases!Z5:Z84,"<>",Releases!Z5:Z84),"0%"),"N/A") -> 18%
B35: 🚦 OVERALL HEALTH STATUS
B36: Release Pipeline | D36: Environment Health | F36: Incident Status | H36: Alert Status
B37: =IF(C6>2,"🔴 Critical",IF(C6>=1,"🟡 Warning","🟢 Healthy")) -> 🟡 Warning | D37: =IF(I18>2,"🔴 Critical",IF(I18>=1,"🟡 Warning","🟢 Healthy")) -> 🔴 Critical | F37: =IF(F18>2,"🔴 Critical",IF(F18>=1,"🟡 Warning","🟢 Healthy")) -> 🔴 Critical | H37: =IF(C18>5,"🔴 Critical",IF(C18>=1,"🟡 Warning","🟢 Healthy")) -> 🔴 Critical
B39: 📊 SUMMARY TOTALS
B40: Total Releases | C40: =C5 -> 9 | D40: Active Incidents | E40: =F23 -> 13 | F40: Active Alerts | G40: =C23 -> 34 | H40: Apps Down | I40: =I18+I21 -> 9
B42: 📈 RELEASE TREND (Next 4 Weeks)
B43: Week 1 | C43: Week 2 | D43: Week 3 | E43: Week 4 | F43: Trend
A44: Releases | B44: {=SUMPRODUCT((Releases!J5:J84>=TODAY())*(Releases!J5:J84<TODAY()+7)*(IF($F$2="All",1,Releases!C5:C84=$F$2))*(IF($H$2="All",1,Releases!D5:D84=$H$2)))} -> 5 | C44: {=SUMPRODUCT((Releases!J5:J84>=TODAY()+7)*(Releases!J5:J84<TODAY()+14)*(IF($F$2="All",1,Releases!C5:C84=$F$2))*(IF($H$2="All",1,Releases!D5:D84=$H$2)))} -> 1 | D44: {=SUMPRODUCT((Releases!J5:J84>=TODAY()+14)*(Releases!J5:J84<TODAY()+21)*(IF($F$2="All",1,Releases!C5:C84=$F$2))*(IF($H$2="All",1,Releases!D5:D84=$H$2)))} -> 3 | E44: {=SUMPRODUCT((Releases!J5:J84>=TODAY()+21)*(Releases!J5:J84<TODAY()+28)*(IF($F$2="All",1,Releases!C5:C84=$F$2))*(IF($H$2="All",1,Releases!D5:D84=$H$2)))} -> 0 | F44: =IF(E44>B44,"📈 ↑ Increasing",IF(E44<B44,"📉 ↓ Decreasing","➡️ Stable")) -> 📉 ↓ Decreasing
B45: =REPT("█",B44) -> █████ | C45: =REPT("█",C44) -> █ | D45: =REPT("█",D44) -> ███ | E45: =REPT("█",E44)
A46: Incidents | B46: P1 | C46: P2 | D46: P3 | E46: Total | F46: Trend
B47: =F18 -> 4 | C47: =F19 -> 6 | D47: =F20 -> 3 | E47: =F23 -> 13 | F47: =IF(F18>0,"🔴 P1 Active!",IF(F19>2,"🟠 Watch P2","🟢 Stable")) -> 🔴 P1 Active!

Sheet README
A1: ═══════════════════════════════════════════════════════════════════════════════════════════════════════════════════
A2: RELEASEDESK - SAMPLE DATA SPECIFICATION FOR PROTOTYPE BUILDER
A3: ═══════════════════════════════════════════════════════════════════════════════════════════════════════════════════
A5: DOCUMENT PURPOSE
A6: This workbook provides structured sample/seed data for a Release Management System prototype.
A7: It is designed to be parsed and interpreted by an AI/Machine that generates wireframes and UI prototypes.
A8: Each sheet represents a distinct data entity with defined schemas, relationships, and business rules.
A10: HOW TO USE THIS DOCUMENT
A11: 1. Start with this README to understand the data model and relationships
A12: 2. Reference the 'Reference Data' sheet for all lookup values, status codes, and enumeration tables
A13: 3. Each data sheet has a defined schema (column headers in Row 1 or as specified)
A14: 4. Foreign keys (FK) link entities - always validate relationships exist
... A26: ENTITY COUNTS (for prototype sizing)
A27: Entity | B27: Count | C27: Primary Key | D27: Source Sheet
A28: Departments | B28: 8 | C28: DEPT-## | D28: Reference Data (Row 40)
A29: Applications | B29: 84 | C29: Composite (Dept+App) | D29: Applications
A30: Environment Instances | B30: 504 | C30: Composite (App+Env) | D30: Applications (84 apps × 6 envs)
A31: Users | B31: 100 | C31: USR-### | D31: Users
A32: Release Managers | B32: 12 | C32: RM-### | D32: Admin (Release Managers)
A33: Super Admins | B33: 12 | C33: SA-### | D33: Super Admins
A34: Releases | B34: 80 | C34: REL-#### | D34: Releases
A35: Environment Bookings | B35: 80+ | C35: ENV-#### | D35: Env booking
A36: Calendar Events | B36: 166 | C36: Row-based | D36: Calendar
A37: Risk Records | B37: 31 | C37: RSK-### | D37: Risk
A38: Drift Issues | B38: 7 | C38: DFT-### | D38: Drift
A39: Dependencies | B39: 26 | C39: DEP-### | D39: Dependencies
A40: Approvals | B40: 27 | C40: APR-### | D40: Approvals
A41: Leave Records | B41: 30 | C41: LV-### | D41: Leave Calendar
A42: Version Records | B42: 180 | C42: APP-### | D42: Versions
A43: Risk Factors | B43: 44-46 | C43: Category+Factor | D43: Risk Factors
A45: TIME SPAN
A46: Release Calendar Period: July 2026 - June 2027 (12 months)
A47: Simulated 'Today' Date: June 25, 2026
A49: KEY METRICS FOR PROTOTYPE
A50: Conflict Rate: ~32% (26 releases have resource conflicts)
A51: Environments per Application: 6 (Dev, Test, UAT, Pre-prod, Prod, DR)
A52: Average Releases per Month: 6-7
A53: Risk Score Range: 1-25 (Likelihood × Impact)
A55: ═══════════════════════════════════════════════════════════════════════════════════════════════════════════════════
A56: SECTION 2: SHEET INVENTORY & NAVIGATION
A57: ═══════════════════════════════════════════════════════════════════════════════════════════════════════════════════
A59: SHEET INDEX (in logical order)
A60: # | B60: Sheet Name | C60: Range | D60: Rows | E60: Purpose | F60: UI Screen Suggestion
A61: 0 | B61: Landing Page | C61: A1:H60 | D61: 60 | E61: Web application home page with navigation | F61: Home Page, Entry Point
A62: 1 | B62: Dashboard | C62: A1:J47 | D62: 47 | E62: Real-time metrics and status overview | F62: Executive Dashboard
A63: 2 | B63: README | C63: A1:F489 | D63: 489 | E63: User guide for wireframe/prototype builders | F63: Help, Documentation
A64: 3 | B64: Technical Specifications | C64: A1:F309 | D64: 309 | E64: Database schema, FK/PK for developers | F64: Developer Reference
A65: 4 | B65: Reference Data | C65: A1:F244 | D65: 244 | E65: All lookup tables & enums | F65: Admin Settings, Dropdowns
A66: 5 | B66: Applications | C66: A1:F505 | D66: 505 | E66: Master app inventory (84 apps × 6 envs) | F66: Application Catalog
A67: 6 | B67: Users | C67: A1:I101 | D67: 101 | E67: 100 users across roles | F67: User Management, Directory
A68: 7 | B68: Admin (Release Managers) | C68: A1:I13 | D68: 13 | E68: 12 release managers | F68: RM Admin Panel
A69: 8 | B69: Super Admins | C69: A1:K15 | D69: 15 | E69: 12 elevated-privilege admins | F69: System Admin Panel
A70: 9 | B70: Releases | C70: A1:AC84 | D70: 84 | E70: 80 releases (core transactional data) | F70: Release Dashboard, Pipeline
A71: 10 | B71: Calendar | C71: A1:J180 | D71: 180 | E71: 166+ events (releases, CAB, freezes) | F71: Calendar View, Gantt Chart
A72: 11 | B72: Env booking | C72: A1:V115 | D72: 115 | E72: Environment scheduling with conflicts | F72: Resource Planner, Booking Grid
... A84: 23 | B84: Planned Maintenance | C84: A1:L89 | D84: 89 | E84: Scheduled maintenance windows | F84: Maintenance Calendar
A85: ═══════════════════════════════════════════════════════════════════════════════════════════════════════════════════
A86: SECTION 3: TECHNICAL SPECIFICATIONS
A87: ═══════════════════════════════════════════════════════════════════════════════════════════════════════════════════
A89: 📋 FOR TECHNICAL DETAILS (Entity Relationships, Foreign Keys, Data Types, Validation Rules):
A90: → See the 'Technical Specifications' sheet (Sheet #3)
A92: This README focuses on helping wireframe/prototype builders understand:
A93: • What each sheet contains (Section 2: Sheet Inventory)
A94: • Business rules and workflows (Section 4)
A95: • UI screen suggestions (Section 5)
A96: • Test scenarios for prototypes (Section 6)
A98: ═══════════════════════════════════════════════════════════════════════════════════════════════════════════════════
A99: SECTION 4: BUSINESS RULES & SIMULATION SCENARIOS
... A114: ─────────────────────────────────────────────────────────────────────────────────────────────────────────────────────
A116: Freeze Period | B116: Dates | C116: Rule
A117: Year-End Freeze | B117: Dec 15, 2026 - Jan 5, 2027 | C117: NO production deployments; exceptions require VP approval
A118: Q1 Quarter-End | B118: Mar 29-31, 2027 | C118: LIMITED deployments; only critical/regulatory allowed
A119: Q2 Quarter-End | B119: Jun 28-30, 2027 | C119: LIMITED deployments; only critical/regulatory allowed
A121: • Releases with Regulatory='GDPR/SOX/SOC2' may request freeze exemption
A122: • All freeze exemptions require documented business justification and CAB approval
A124: CAB APPROVAL WORKFLOW
A125: ─────────────────────────────────────────────────────────────────────────────────────────────────────────────────────
A127: Workflow Stages:
A128: Stage | B128: Description | C128: Required Actions
A129: 1. Draft | B129: Release created, initial planning | C129: Complete release scope and impact assessment
A130: 2. Planning | B130: Detailed planning underway | C130: Assign resources, define test strategy
A131: 3. Testing | B131: Test phase in progress | C131: Complete all test cases, document results
A132: 4. CAB Submitted | B132: Submitted for CAB review | C132: Package sent 2-3 days before CAB date
A133: 5. CAB Approved | B133: Approved by Change Advisory Board | C133: Proceed to deployment preparation
A134: 6. Deploying | B134: Deployment in progress | C134: Execute deployment runbook
A135: 7. Deployed | B135: Successfully deployed to production | C135: Verify deployment, monitor
A136: 8. PIR Complete | B136: Post-Implementation Review done | C136: Lessons learned documented
A137: 9. Closed | B137: Release officially closed | C137: All artifacts archived
A139: CAB Lead Time Requirements:
A140: • Large releases: 3 days before Prod date
A141: • Medium/Small releases: 2 days before Prod date
A143: RISK CALCULATION METHODOLOGY
A144: ─────────────────────────────────────────────────────────────────────────────────────────────────────────────────────
A146: Simple Risk Score (Risk sheet):
A147: Risk Score = Likelihood (1-5) × Impact (1-5) = 1-25
A149: Weighted Risk Score (Risk Factors sheet):
A150: Weighted Score = Σ (Factor Score × Factor Weight) for all 44-46 factors
A151: Each factor scored 1-5, weights sum to 100%
A152: Final score range: 1.00 - 5.00
A154: Risk Action Thresholds:
...

Sheet Technical Specifications
A1: TECHNICAL SPECIFICATIONS - Release Desk Data Dictionary
A3: PURPOSE OF THIS DOCUMENT
A4: ═══════════════════════════════════════════════════════════════════════════════════════════════════════════════════════════════════════════
A6: This sheet contains technical specifications for developers building the Release Desk application.
A8: CONTENTS:
A9: • Data types, Primary Keys (PK), and Foreign Keys (FK) for each table/sheet
A10: • Entity relationship diagrams showing how data connects
A11: • Validation rules and integrity constraints
A12: • Cardinality (1:1, 1:M, M:M relationships)
A14: WHO SHOULD USE THIS:
A15: • Backend developers implementing the database schema
A16: • API developers creating endpoints
... A68: FOREIGN KEY REFERENCE TABLE
A70: Source Sheet | B70: FK Column | C70: → | D70: Target Sheet | E70: PK Column
A71: Releases | B71: Department | C71: → | D71: Reference Data | E71: Dept Code
A72: Releases | B72: Application | C72: → | D72: Applications | E72: Application Name
A73: Releases | B73: Release Owner ID | C73: → | D73: Users | E73: User ID
A74: Releases | B74: Stakeholder IDs | C74: → | D74: Users | E74: User ID (M:M)
A75: Applications | B75: Department | C75: → | D75: Reference Data | E75: Dept Code
A76: Env booking | B76: Release ID | C76: → | D76: Releases | E76: Release ID
A77: Env booking | B77: Application | C77: → | D77: Applications | E77: Application Name
A78: Risk | B78: Release ID | C78: → | D78: Releases | E78: Release ID
A79: Risk | B79: Risk Owner ID | C79: → | D79: Users | E79: User ID
A80: Drift | B80: Release ID | C80: → | D80: Releases | E80: Release ID
A81: Drift | B81: Application | C81: → | D81: Applications | E81: Application Name
... A94: Planned Maintenance | B94: Application | C94: → | D94: Applications | E94: Application Name
A98: SECTION 2: DETAILED SCHEMA DOCUMENTATION
A99: ═══════════════════════════════════════════════════════════════════════════════════════════════════════════════════
A101: Each sheet's schema is documented below with column definitions, data types, and validation rules.
A103: DATA TYPE LEGEND:
A104: • TEXT: Free-form text string
A105: • INT: Integer number
A106: • DATE: Date in YYYY-MM-DD format
A107: • DECIMAL: Number with decimal places
A108: • ENUM: Value from predefined list (see Reference Data sheet)
A109: • FK: Foreign key - must match value in referenced table
A110: • BOOL: Boolean (Yes/No or True/False)
A111: • ID: Auto-generated unique identifier
... A116: ───────────────────────────────────────────────────────────────────────────────────────────────────────────────────
A119: Column | B119: Header Name | C119: Data Type | D119: Required | E119: Validation/Constraints | F119: Description
A120: A | B120: Department | C120: ENUM | D120: Yes | E120: Valid: Finance, Logistics, CRM, Manufacturing, IT, HR, Legal, Security | F120: Business unit that owns the application
A121: B | B121: Application | C121: TEXT | D121: Yes | E121: Max 100 chars; Must be unique within department | F121: Name of the software application
A122: C | B122: Env | C122: ENUM | D122: Yes | E122: Valid: Dev, Test, UAT, Pre-prod, Prod, DR | F122: Environment type (6 per application)
A123: D | B123: Application Owner | C123: TEXT | D123: No | E123: Business owner name (first row only) | F123: Primary business owner
A124: E | B124: Tech Lead | C124: TEXT | D124: No | E124: Technical lead name (first row only) | F124: Technical lead contact
A125: F | B125: Env Owner | C125: TEXT | D125: Yes | E125: Environment-specific owner | F125: Person responsible for this environment
A127: Business Rules:
A128: • Each application appears 6 times (once per environment type: Dev, Test, UAT, Pre-prod, Prod, DR)
A129: • Department value only shown on first row of each application group
A130: • Application Owner and Tech Lead only populated on Dev environment row
A131: • Env Owner varies by environment type (Dev Mgr, QA Lead, Business Analyst, Release Mgr, Ops Mgr, Infra Lead)
A134: ───────────────────────────────────────────────────────────────────────────────────────────────────────────────────
A135: SHEET: Releases | Range: A1:AB81 | Records: 80 releases
A136: ───────────────────────────────────────────────────────────────────────────────────────────────────────────────────
A139: Column | B139: Header Name | C139: Data Type | D139: Required | E139: Validation/Constraints | F139: Description
A140: A | B140: Release ID | C140: ID | D140: Yes | E140: Format: REL-NNNN; Auto-generated; PK | F140: Unique release identifier
A141: B | B141: Release Name | C141: TEXT | D141: Yes | E141: Max 200 chars; Include version number | F141: Descriptive name with version
A142: C | B142: Department | C142: ENUM/FK | D142: Yes | E142: Must exist in Reference Data sheet | F142: Owning business unit
A143: D | B143: Application | C143: TEXT/FK | D143: Yes | E143: Must exist in Applications sheet | F143: Target application name
A144: E | B144: Dependencies | C144: TEXT | D144: No | E144: Comma-separated list or 'NA' | F144: Other releases this depends on
A145: F | B145: Release Size | C145: ENUM | D145: Yes | E145: Valid: Small, Medium, Large | F145: Effort estimation category
A146: G | B146: Impact | C146: ENUM | D146: Yes | E146: Valid: High, Medium, Low | F146: Business impact level
A147: H | B147: Priority | C147: ENUM | D147: Yes | E147: Valid: P1 - Critical, P2 - High, P3 - Medium, P4 - Low | F147: Urgency classification
A148: I | B148: CAB Date | C148: DATE | D148: Yes | E148: YYYY-MM-DD format | F148: Change Advisory Board review date
A149: J | B149: Start Date | C149: DATE | D149: Yes | E149: Must be >= CAB Date | F149: Planned deployment start
A150: K | B150: End Date | C150: DATE | D150: Yes | E150: Must be >= Start Date | F150: Planned deployment completion
... A167: AB | B167: Deployment Window | C167: ENUM | D167: Yes | E167: Valid: Business Hours, Off-Peak, Weekend | F167: Deployment timing preference
A170: ───────────────────────────────────────────────────────────────────────────────────────────────────────────────────
A171: SHEET: Env booking | Range: A1:I102 | Records: 101 environment bookings
A172: ───────────────────────────────────────────────────────────────────────────────────────────────────────────────────
A175: Column | B175: Header Name | C175: Data Type | D175: Required | E175: Validation/Constraints | F175: Description
A176: A | B176: Booking ID | C176: ID | D176: Yes | E176: Format: ENV-NNNN; Auto-generated; PK | F176: Unique booking identifier
A177: B | B177: Release ID | C177: ID/FK | D177: Yes | E177: Must exist in Releases sheet | F177: Associated release
A178: C | B178: Application | C178: TEXT/FK | D178: Yes | E178: Must exist in Applications sheet | F178: Application requiring environment
A179: D | B179: Env Type | C179: ENUM | D179: Yes | E179: Valid: Dev, Test, UAT, Pre-prod, Prod, DR | F179: Environment type being booked
A180: E | B180: Start Date | C180: DATE | D180: Yes | E180: YYYY-MM-DD format | F180: Booking start date
A181: F | B181: End Date | C181: DATE | D181: Yes | E181: Must be >= Start Date | F181: Booking end date
A182: G | B182: Status | C182: ENUM | D182: Yes | E182: Valid: Confirmed, Pending, Cancelled | F182: Booking status
A183: H | B183: Conflict | C183: TEXT | D183: No | E183: Conflict description if overlapping | F183: Environment conflict indicator
A184: I | B184: Notes | C184: TEXT | D184: No | E184: Max 500 chars | F184: Additional booking notes
A187: ───────────────────────────────────────────────────────────────────────────────────────────────────────────────────
A188: SHEET: Risk | Range: A1:K32 | Records: 31 risks
A189: ───────────────────────────────────────────────────────────────────────────────────────────────────────────────────
A192: Column | B192: Header Name | C192: Data Type | D192: Required | E192: Validation/Constraints | F192: Description
A193: A | B193: Risk ID | C193: ID | D193: Yes | E193: Format: RSK-NNNN; Auto-generated; PK | F193: Unique risk identifier
A194: B | B194: Release ID | C194: ID/FK | D194: Yes | E194: Must exist in Releases sheet | F194: Associated release
A195: C | B195: Risk Category | C195: ENUM | D195: Yes | E195: Technical, Business, Resource, Timeline, External | F195: Classification of risk type
A196: D | B196: Risk Description | C196: TEXT | D196: Yes | E196: Max 500 chars | F196: Detailed risk description
A197: E | B197: Likelihood | C197: INT | D197: Yes | E197: 1-5 scale (see Reference Data) | F197: Probability of occurrence
A198: F | B198: Impact | C198: INT | D198: Yes | E198: 1-5 scale (see Reference Data) | F198: Severity if occurs
A199: G | B199: Risk Score | C199: INT | D199: Yes | E199: Formula: Likelihood × Impact (1-25) | F199: Composite risk score
A200: H | B200: Mitigation Plan | C200: TEXT | D200: No | E200: Max 500 chars | F200: Risk mitigation approach
A201: I | B201: Risk Owner ID | C201: ID/FK | D201: Yes | E201: Must exist in Users sheet | F201: Person responsible
A202: J | B202: Status | C202: ENUM | D202: Yes | E202: Open, Mitigating, Accepted, Closed | F202: Current risk status
A203: K | B203: Review Date | C203: DATE | D203: No | E203: YYYY-MM-DD format | F203: Next review date
A206: ───────────────────────────────────────────────────────────────────────────────────────────────────────────────────
A207: ADDITIONAL SHEET SCHEMAS (SUMMARY)
A208: ───────────────────────────────────────────────────────────────────────────────────────────────────────────────────
A210: The following sheets follow similar patterns. Key columns are listed below:
A212: SHEET: Calendar | Primary Key: Event ID | Foreign Keys: Release ID
...

Sheet Reference Data
A1: RELEASE DESK - REFERENCE DATA CATALOG
A2: Consolidated lookup tables, status codes, thresholds, and configuration data
A3: Version 1.0 | Generated: June 2026
A6: WORKBOOK STATISTICS
A7: Metric | B7: Value | C7: Source
A8: Total Departments | B8: 8 | C8: Applications sheet
A9: Total Applications | B9: 84 | C9: Applications sheet
A10: Total Releases | B10: 80 | C10: Releases sheet
A11: Total Users | B11: 100+ | C11: Users, Release Managers, Super Admins
A12: Risk Factors | B12: 44-46 | C12: Risk Factors sheet
A14: 1. DEPARTMENTS
A15: Dept ID | B15: Dept Code | C15: Dept Name | D15: Primary Focus
A16: DEPT-01 | B16: FIN | C16: Finance | D16: Financial planning, reporting, treasury
A17: DEPT-02 | B17: LOG | C17: Logistics | D17: Warehouse, transportation, supply chain
A18: DEPT-03 | B18: CRM | C18: CRM | D18: Sales, marketing, customer service
A19: DEPT-04 | B19: MFG | C19: Manufacturing | D19: Production, quality, MES systems
A20: DEPT-05 | B20: IT | C20: IT | D20: Infrastructure, monitoring, service desk
A21: DEPT-06 | B21: HR | C21: HR | D21: HCM, payroll, learning, talent
A22: DEPT-07 | B22: LEG | C22: Legal | D22: Contracts, compliance, document management
A23: DEPT-08 | B23: SEC | C23: Security | D23: Identity, access, threat detection
A26: 2. ENVIRONMENTS
A27: Env Code | B27: Env Name | C27: Promotion Order | D27: Availability | E27: Description
A28: DEV | B28: Development | C28: 1 | D28: 24/7 | E28: Developer sandbox environment
A29: TEST | B29: Testing | C29: 2 | D29: Business Hours | E29: QA and integration testing
A30: UAT | B30: User Acceptance | C30: 3 | D30: Business Hours | E30: Business validation environment
A31: PREPROD | B31: Pre-Production | C31: 4 | D31: Business Hours | E31: Production mirror for final validation
A32: PROD | B32: Production | C32: 5 | D32: 24/7 | E32: Live production environment
A33: DR | B33: Disaster Recovery | C33: 6 | D33: 24/7 | E33: Business continuity failover
A36: 3. RELEASE SIZES
A37: Size | B37: Test Days | C37: UAT Days | D37: Pre-Prod Days | E37: Total Lead Time | F37: Examples
A38: Small | B38: 3 | C38: 2 | D38: 1 | E38: ~8 days | F38: Bug fixes, minor UI changes
A39: Medium | B39: 5 | C39: 3 | D39: 2 | E39: ~12 days | F39: Feature enhancements, integrations
A40: Large | B40: 10 | C40: 5 | D40: 4 | E40: ~22 days | F40: Major releases, platform upgrades
A42: 4. IMPACT LEVELS
A43: Level | B43: Code | C43: Color | D43: Description | E43: Examples
A44: High | B44: H | C44: #FF0000 | D44: Critical business impact | E44: Core ERP, Payment Systems
A45: Medium | B45: M | C45: #FFC000 | D45: Moderate impact, workarounds exist | E45: Reporting, Secondary CRM
A46: Low | B46: L | C46: #00B050 | D46: Minimal impact, easily recoverable | E46: UI changes, Minor enhancements
A48: 5. PRIORITY LEVELS
A49: Priority | B49: Code | C49: Response Time | D49: Escalation | E49: Description
A50: Critical | B50: P1 | C50: Immediate | D50: CIO/VP Level | E50: Business-stopping issues, security breaches
A51: High | B51: P2 | C51: 4 hours | D51: Director Level | E51: Major degradation, customer impacting
A52: Medium | B52: P3 | C52: 1 business day | D52: Manager Level | E52: Important but not urgent issues
A53: Low | B53: P4 | C53: 5 business days | D53: Standard | E53: Minor issues, enhancements
A55: 6. RELEASE STATUS CODES
A56: Status Code | B56: Display Name | C56: Stage | D56: Description
A57: DRAFT | B57: Draft | C57: Initial | D57: Release being planned, not yet submitted
A58: SUBMITTED | B58: Submitted | C58: Review | D58: Release submitted for review and approval
A59: PENDING_CAB | B59: Pending CAB | C59: Review | D59: Awaiting Change Advisory Board review
A60: APPROVED | B60: Approved | C60: Ready | D60: All approvals obtained, ready to proceed
A61: IN_PROGRESS | B61: In Progress | C61: Active | D61: Release deployment actively underway
A62: BLOCKED | B62: Blocked | C62: Hold | D62: Release halted due to dependency or issue
A63: ON_HOLD | B63: On Hold | C63: Hold | D63: Temporarily paused for business reasons
A64: COMPLETED | B64: Completed | C64: Closed | D64: Release successfully deployed
A65: FAILED | B65: Failed | C65: Closed | D65: Release deployment failed, rollback executed
A66: CANCELLED | B66: Cancelled | C66: Closed | D66: Release cancelled before deployment
A68: 7. RISK SCORE THRESHOLDS
A69: Risk Level | B69: Score Range | C69: Color Code | D69: Action Required | E69: Approval Level
A70: LOW | B70: < 1.5 | C70: #00B050 | D70: Standard process | E70: Release Manager
A71: MEDIUM | B71: 1.5 - 2.5 | C71: #FFC000 | D71: Enhanced monitoring | E71: Release Manager + Tech Lead
A72: HIGH | B72: 2.5 - 3.5 | C72: #FF6600 | D72: Risk mitigation plan required | E72: Director Approval
A73: CRITICAL | B73: 3.5 - 4.0 | C73: #FF0000 | D73: Executive review, CAB escalation | E73: VP/CIO Approval
A74: SEVERE | B74: ≥ 4.0 | C74: #7030A0 | D74: Consider postponement | E74: Emergency CAB
A76: 8. APPROVAL TYPES & WORKFLOW
A77: Approval Type | B77: Code | C77: Approver Role | D77: SLA (Hours) | E77: Sequence
A78: Technical Review | B78: TECH | C78: Tech Lead / Architect | D78: 24 | E78: 1
A79: Security Review | B79: SEC | C79: Security Team | D79: 48 | E79: 2
A80: Business Review | B80: BIZ | C80: Business Owner | D80: 24 | E80: 3
A81: QA Sign-off | B81: QA | C81: QA Lead | D81: 8 | E81: 4
A82: CAB Review | B82: CAB | C82: Change Advisory Board | D82: 48 | E82: 5
A83: Final Approval | B83: FINAL | C83: Release Manager | D83: 4 | E83: 6
A85: 9. DEPENDENCY TYPES
A86: Type | B86: Code | C86: Impact | D86: Description
A87: Hard | B87: HARD | C87: Blocking | D87: Must be resolved before release can proceed
A88: Soft | B88: SOFT | C88: Advisory | D88: Recommended but not mandatory
A89: Technical | B89: TECH | C89: Blocking | D89: Code or infrastructure dependencies
A90: Data | B90: DATA | C90: Blocking | D90: Data migration or sync requirements
A91: Integration | B91: INTG | C91: Variable | D91: External system integration points
A93: 10. DEPENDENCY STATUS
A94: Status | B94: Code | C94: Color | D94: Description
A95: Clear | B95: CLR | C95: #00B050 | D95: Dependency resolved, no action needed
A96: At Risk | B96: RISK | C96: #FFC000 | D96: Potential issue, requires monitoring
A97: Blocked | B97: BLK | C97: #FF0000 | D97: Active blocker, must be resolved
A98: Resolved | B98: RES | C98: #0070C0 | D98: Previously blocked, now cleared
A100: 11. LEAVE TYPES
A101: Leave Type | B101: Code | C101: Risk Impact | D101: Coverage Required
A102: Annual Leave | B102: AL | C102: Low-Medium | D102: If key resource, backup needed
A103: Personal Leave | B103: PL | C103: Low | D103: Standard handover
A104: Sick Leave | B104: SL | C104: Variable | D104: Emergency coverage protocol
A105: Conference | B105: CONF | C105: Low | D105: Planned, backup assigned
A106: Training | B106: TRN | C106: Low | D106: Planned, limited availability
A108: 12. USER ROLES & PERMISSIONS
A109: Role | B109: Code | C109: Create Release | D109: Approve | E109: Admin
A110: Super Admin | B110: SADM | C110: Yes | D110: Yes | E110: Yes
A111: Release Manager | B111: RELMGR | C111: Yes | D111: Yes | E111: Limited
A112: Development Manager | B112: DEVMGR | C112: Yes | D112: Yes | E112: No
A113: QA Lead | B113: QALEAD | C113: No | D113: Yes | E113: No
A114: Tech Lead | B114: TLEAD | C114: Yes | D114: Yes | E114: No
A115: Business Analyst | B115: BA | C115: Yes | D115: No | E115: No
A116: Developer | B116: DEV | C116: Limited | D116: No | E116: No
...

Sheet Applications
A1: Department | B1: Application | C1: Env | D1: Application Owner | E1: Tech Lead | F1: Env Owner
A2: Finance | B2: SAP S/4HANA Finance (FICO) | C2: Dev | D2: Sarah Mitchell | E2: James Wilson | F2: Alex Rivera (Dev Mgr)
B3: SAP S/4HANA Finance (FICO) | C3: Test | F3: Sam Anderson (QA Lead)
B4: SAP S/4HANA Finance (FICO) | C4: UAT | F4: Rachel Green (Bus Analyst)
B5: SAP S/4HANA Finance (FICO) | C5: Pre-prod | F5: Nathan Cole (Release Mgr)
B6: SAP S/4HANA Finance (FICO) | C6: Prod | F6: Victoria Sterling (Ops Mgr)
B7: SAP S/4HANA Finance (FICO) | C7: DR | F7: Robert Shield (Infra Lead)
B8: Anaplan | C8: Dev | D8: David Chen | E8: Emily Zhang | F8: Jordan Lee (Dev Mgr)
B9: Anaplan | C9: Test | F9: Chris Park (QA Lead)
B10: Anaplan | C10: UAT | F10: Monica Geller (Bus Analyst)
B11: Anaplan | C11: Pre-prod | F11: Ethan Black (Release Mgr)
B12: Anaplan | C12: Prod | F12: Elizabeth Crown (Ops Mgr)
B13: Anaplan | C13: DR | F13: William Guard (Infra Lead)
B14: Oracle Hyperion HFM | C14: Dev | D14: Jennifer Walsh | E14: Michael Brown | F14: Casey Chen (Dev Mgr)
B15: Oracle Hyperion HFM | C15: Test | F15: Pat Murphy (QA Lead)
B16: Oracle Hyperion HFM | C16: UAT | F16: Phoebe Buffay (Bus Analyst)
B17: Oracle Hyperion HFM | C17: Pre-prod | F17: Lucas White (Release Mgr)
B18: Oracle Hyperion HFM | C18: Prod | F18: Catherine Royal (Ops Mgr)
B19: Oracle Hyperion HFM | C19: DR | F19: James Fortress (Infra Lead)
B20: Kyriba | C20: Dev | D20: Robert Kim | E20: Priya Sharma | F20: Morgan Taylor (Dev Mgr)
B21: Kyriba | C21: Test | F21: Jesse Garcia (QA Lead)
B22: Kyriba | C22: UAT | F22: Emma Watson (Bus Analyst)
B23: Kyriba | C23: Pre-prod | F23: Mason Gray (Release Mgr)
B24: Kyriba | C24: Prod | F24: Margaret Noble (Ops Mgr)
B25: Kyriba | C25: DR | F25: Michael Bastion (Infra Lead)
B26: Coupa | C26: Dev | D26: Michelle Torres | E26: Christopher Davis | F26: Jamie Patel (Dev Mgr)
B27: Coupa | C27: Test | F27: Robin Chen (QA Lead)
B28: Coupa | C28: UAT | F28: Sophie Turner (Bus Analyst)
B29: Coupa | C29: Pre-prod | F29: Logan Stone (Release Mgr)
B30: Coupa | C30: Prod | F30: Diana Prince (Ops Mgr)
B31: Coupa | C31: DR | F31: David Tower (Infra Lead)
B32: Zuora | C32: Dev | D32: Andrew Patel | E32: Angela Liu | F32: Riley Kim (Dev Mgr)
B33: Zuora | C33: Test | F33: Dana Wilson (QA Lead)
B34: Zuora | C34: UAT | F34: Mia Collins (Bus Analyst)
B35: Zuora | C35: Pre-prod | F35: Jacob Hill (Release Mgr)
B36: Zuora | C36: Prod | F36: Helena Troy (Ops Mgr)
B37: Zuora | C37: DR | F37: Richard Wall (Infra Lead)
B38: RevPro | C38: Dev | D38: Lisa Thompson | E38: Daniel Park | F38: Quinn Johnson (Dev Mgr)
B39: RevPro | C39: Test | F39: Kelly Nguyen (QA Lead)
B40: RevPro | C40: UAT | F40: Isabella Moore (Bus Analyst)
B41: RevPro | C41: Pre-prod | F41: Aiden Clark (Release Mgr)
B42: RevPro | C42: Prod | F42: Sophia Grace (Ops Mgr)
B43: RevPro | C43: DR | F43: Thomas Castle (Infra Lead)
B44: Thomson Reuters ONESOURCE | C44: Dev | D44: Mark Rodriguez | E44: Jessica Nguyen | F44: Avery Williams (Dev Mgr)
B45: Thomson Reuters ONESOURCE | C45: Test | F45: Terry Brooks (QA Lead)
B46: Thomson Reuters ONESOURCE | C46: UAT | F46: Olivia James (Bus Analyst)
B47: Thomson Reuters ONESOURCE | C47: Pre-prod | F47: Jackson Moore (Release Mgr)
B48: Thomson Reuters ONESOURCE | C48: Prod | F48: Alexandra Reid (Ops Mgr)
B49: Thomson Reuters ONESOURCE | C49: DR | F49: Charles Vault (Infra Lead)
B50: SAP Concur | C50: Dev | D50: Amanda Foster | E50: Ryan Cooper | F50: Drew Martinez (Dev Mgr)
B51: SAP Concur | C51: Test | F51: Skyler Davis (QA Lead)
B52: SAP Concur | C52: UAT | F52: Ava Mitchell (Bus Analyst)
B53: SAP Concur | C53: Pre-prod | F53: Sebastian Hall (Release Mgr)
B54: SAP Concur | C54: Prod | F54: Christina Vale (Ops Mgr)
B55: SAP Concur | C55: DR | F55: Daniel Bunker (Infra Lead)
B56: Workday Financials | C56: Dev | D56: Kevin O'Brien | E56: Samantha Reed | F56: Cameron Brown (Dev Mgr)
B57: Workday Financials | C57: Test | F57: Jordan Reed (QA Lead)
B58: Workday Financials | C58: UAT | F58: Charlotte Price (Bus Analyst)
B59: Workday Financials | C59: Pre-prod | F59: Caleb Young (Release Mgr)
B60: Workday Financials | C60: Prod | F60: Natasha Roman (Ops Mgr)
B61: Workday Financials | C61: DR | F61: Matthew Haven (Infra Lead)
B62: MetricStream | C62: Dev | D62: Rachel Green | E62: William Chen | F62: Taylor Singh (Dev Mgr)
B63: MetricStream | C63: Test | F63: Alex Foster (QA Lead)
B64: MetricStream | C64: UAT | F64: Amelia Scott (Bus Analyst)
B65: MetricStream | C65: Pre-prod | F65: Owen King (Release Mgr)
B66: MetricStream | C66: Prod | F66: Amanda Cross (Ops Mgr)
B67: MetricStream | C67: DR | F67: Anthony Secure (Infra Lead)
B68: IBM Cognos | C68: Dev | D68: Thomas Wright | E68: Olivia Martinez | F68: Blake Thompson (Dev Mgr)
B69: IBM Cognos | C69: Test | F69: Morgan Hayes (QA Lead)
B70: IBM Cognos | C70: UAT | F70: Harper Lewis (Bus Analyst)
B71: IBM Cognos | C71: Pre-prod | F71: Liam Wright (Release Mgr)
B72: IBM Cognos | C72: Prod | F72: Rebecca Stone (Ops Mgr)
B73: IBM Cognos | C73: DR | F73: Mark Backup (Infra Lead)
B74: HighRadius | C74: Dev | D74: Diana Lee | E74: Nathan Brooks | F74: Alex Rivera (Dev Mgr)
B75: HighRadius | C75: Test | F75: Sam Anderson (QA Lead)
B76: HighRadius | C76: UAT | F76: Rachel Green (Bus Analyst)
B77: HighRadius | C77: Pre-prod | F77: Nathan Cole (Release Mgr)
B78: HighRadius | C78: Prod | F78: Victoria Sterling (Ops Mgr)
B79: HighRadius | C79: DR | F79: Robert Shield (Infra Lead)
B80: Basware | C80: Dev | D80: Steven Martinez | E80: Karen Singh | F80: Jordan Lee (Dev Mgr)
B81: Basware | C81: Test | F81: Chris Park (QA Lead)
B82: Basware | C82: UAT | F82: Monica Geller (Bus Analyst)
B83: Basware | C83: Pre-prod | F83: Ethan Black (Release Mgr)
B84: Basware | C84: Prod | F84: Elizabeth Crown (Ops Mgr)
B85: Basware | C85: DR | F85: William Guard (Infra Lead)
A86: Logistics | B86: SAP Transportation Management (TM) | C86: Dev | D86: Brian Murphy | E86: Marcus Johnson | F86: Alex Rivera (Dev Mgr)
B87: SAP Transportation Management (TM) | C87: Test | F87: Sam Anderson (QA Lead)
B88: SAP Transportation Management (TM) | C88: UAT | F88: Rachel Green (Bus Analyst)
B89: SAP Transportation Management (TM) | C89: Pre-prod | F89: Nathan Cole (Release Mgr)
B90: SAP Transportation Management (TM) | C90: Prod | F90: Victoria Sterling (Ops Mgr)
B91: SAP Transportation Management (TM) | C91: DR | F91: Robert Shield (Infra Lead)
B92: Oracle Transportation Management | C92: Dev | D92: Catherine Hayes | E92: Tina Wang | F92: Jordan Lee (Dev Mgr)
B93: Oracle Transportation Management | C93: Test | F93: Chris Park (QA Lead)
B94: Oracle Transportation Management | C94: UAT | F94: Monica Geller (Bus Analyst)
B95: Oracle Transportation Management | C95: Pre-prod | F95: Ethan Black (Release Mgr)
B96: Oracle Transportation Management | C96: Prod | F96: Elizabeth Crown (Ops Mgr)
B97: Oracle Transportation Management | C97: DR | F97: William Guard (Infra Lead)
B98: Blue Yonder WMS | C98: Dev | D98: Eric Johansson | E98: Alexander Petrov | F98: Casey Chen (Dev Mgr)
B99: Blue Yonder WMS | C99: Test | F99: Pat Murphy (QA Lead)
B100: Blue Yonder WMS | C100: UAT | F100: Phoebe Buffay (Bus Analyst)
...

Sheet Users
A1: User ID | B1: Name | C1: Email | D1: Role | E1: Department | F1: Manager | G1: Access Level | H1: Status | I1: Last Login
A2: USR-001 | B2: Alex Rivera | C2: alex.rivera@company.com | D2: Development Manager | E2: IT | F2: CTO Office | G2: Admin | H2: Active | I2: 46198
A3: USR-002 | B3: Jordan Lee | C3: jordan.lee@company.com | D3: Development Manager | E3: IT | F3: CTO Office | G3: Admin | H3: Active | I3: 46198
A4: USR-003 | B4: Casey Chen | C4: casey.chen@company.com | D4: Development Manager | E4: IT | F4: CTO Office | G4: Admin | H4: Active | I4: 46197
A5: USR-004 | B5: Morgan Taylor | C5: morgan.taylor@company.com | D5: Development Manager | E5: IT | F5: CTO Office | G5: Admin | H5: Active | I5: 46198
A6: USR-005 | B6: Jamie Patel | C6: jamie.patel@company.com | D6: Development Manager | E6: IT | F6: CTO Office | G6: Admin | H6: Active | I6: 46197
A7: USR-006 | B7: Riley Kim | C7: riley.kim@company.com | D7: Development Manager | E7: IT | F7: CTO Office | G7: Admin | H7: Active | I7: 46198
A8: USR-007 | B8: Quinn Johnson | C8: quinn.johnson@company.com | D8: Development Manager | E8: IT | F8: CTO Office | G8: Admin | H8: Active | I8: 46196
A9: USR-008 | B9: Avery Williams | C9: avery.williams@company.com | D9: Development Manager | E9: IT | F9: CTO Office | G9: Admin | H9: Active | I9: 46198
A10: USR-009 | B10: Drew Martinez | C10: drew.martinez@company.com | D10: Development Manager | E10: IT | F10: CTO Office | G10: Admin | H10: Active | I10: 46197
A11: USR-010 | B11: Cameron Brown | C11: cameron.brown@company.com | D11: Development Manager | E11: IT | F11: CTO Office | G11: Admin | H11: Active | I11: 46198
A12: USR-011 | B12: Taylor Singh | C12: taylor.singh@company.com | D12: Development Manager | E12: IT | F12: CTO Office | G12: Admin | H12: Active | I12: 46195
A13: USR-012 | B13: Blake Thompson | C13: blake.thompson@company.com | D13: Development Manager | E13: IT | F13: CTO Office | G13: Admin | H13: Active | I13: 46198
... A101: USR-100 | B101: Michelle Davis | C101: michelle.davis@company.com | D101: Project Manager | E101: PMO | F101: PMO Director | G101: Standard | H101: Active | I101: 46198

Sheet Admin (Release Managers)
A1: ID | B1: Name | C1: Email | D1: Department | E1: Region | F1: Phone | G1: Status | H1: Start Date | I1: Specialization
A2: RM-001 | B2: Nathan Cole | C2: nathan.cole@company.com | D2: IT | E2: North America | F2: +1-555-0101 | G2: Active | H2: 43905 | I2: Finance & HR Systems
A3: RM-002 | B3: Ethan Black | C3: ethan.black@company.com | D3: IT | E3: North America | F3: +1-555-0102 | G3: Active | H3: 43636 | I3: Manufacturing & Logistics
A4: RM-003 | B4: Lucas White | C4: lucas.white@company.com | D4: IT | E4: EMEA | F4: +44-20-5550103 | G4: Active | H4: 44206 | I4: CRM & Sales Systems
A5: RM-004 | B5: Mason Gray | C5: mason.gray@company.com | D5: IT | E5: EMEA | F5: +44-20-5550104 | G5: Active | H5: 43344 | I5: Security & Infrastructure
A6: RM-005 | B6: Logan Stone | C6: logan.stone@company.com | D6: IT | E6: APAC | F6: +61-2-5550105 | G6: Active | H6: 44150 | I6: Legal & Compliance
A7: RM-006 | B7: Jacob Hill | C7: jacob.hill@company.com | D7: IT | E7: APAC | F7: +61-2-5550106 | G7: Active | H7: 44620 | I7: HR & Talent Systems
A8: RM-007 | B8: Aiden Clark | C8: aiden.clark@company.com | D8: IT | E8: North America | F8: +1-555-0107 | G8: Active | H8: 43567 | I8: Integration & Middleware
A9: RM-008 | B9: Jackson Moore | C9: jackson.moore@company.com | D9: IT | E9: EMEA | F9: +44-20-5550108 | G9: Active | H9: 44399 | I9: Data & Analytics
A10: RM-009 | B10: Sebastian Hall | C10: sebastian.hall@company.com | D10: IT | E10: LATAM | F10: +55-11-5550109 | G10: Active | H10: 44048 | I10: ERP Systems
A11: RM-010 | B11: Caleb Young | C11: caleb.young@company.com | D11: IT | E11: North America | F11: +1-555-0110 | G11: Active | H11: 43070 | I11: Cloud & SaaS Platforms
A12: RM-011 | B12: Owen King | C12: owen.king@company.com | D12: IT | E12: APAC | F12: +65-5550111 | G12: Active | H12: 44699 | I12: Manufacturing Execution
A13: RM-012 | B13: Liam Wright | C13: liam.wright@company.com | D13: IT | E13: EMEA | F13: +49-30-5550112 | G13: On Leave | H13: 43768 | I13: Finance Reporting

Sheet Super Admins
A1: Admin ID | B1: Name | C1: Email | D1: Title | E1: Department | F1: Access Scope | G1: Granted Date | H1: Granted By | I1: Status | J1: Expiry Date | K1: Notes
A2: SA-001 | B2: Michael Stevens | C2: michael.stevens@company.com | D2: Chief Information Officer | E2: IT | F2: Global - All Systems | G2: 44635 | H2: CEO Office | I2: Active | J2: 46461 | K2: Executive sponsor for all IT initiatives
A3: SA-002 | B3: Jennifer Walsh | C3: jennifer.walsh@company.com | D3: VP of Enterprise Applications | E3: IT | F3: Global - All Systems | G3: 44936 | H3: Michael Stevens | I3: Active | J3: 46397 | K3: Oversight of all enterprise systems
A4: SA-003 | B4: Christopher Blake | C4: christopher.blake@company.com | D4: Director of IT Operations | E4: IT | F4: Global - Infrastructure | G4: 45097 | H4: Jennifer Walsh | I4: Active | J4: 46387 | K4: 24/7 operations oversight
A5: SA-004 | B5: Elizabeth Morgan | C5: elizabeth.morgan@company.com | D5: Head of Cybersecurity | E5: Security | F5: Global - All Systems | G5: 44774 | H5: Michael Stevens | I5: Active | J5: 46600 | K5: Security incident response authority
A6: SA-005 | B6: Robert Chen | C6: robert.chen@company.com | D6: Chief Technology Officer | E6: IT | F6: Global - All Systems | G6: 44326 | H6: CEO Office | I6: Active | J6: 46517 | K6: Technical architecture decisions
A7: SA-006 | B7: Patricia Wong | C7: patricia.wong@company.com | D7: Director of Release Management | E7: IT | F7: Global - Release Systems | G7: 45337 | H7: Jennifer Walsh | I7: Active | J7: 46249 | K7: Emergency release authority
A8: SA-007 | B8: Daniel Crawford | C8: daniel.crawford@company.com | D8: VP of HR Technology | E8: HR | F8: HR Systems - Global | G8: 45170 | H8: Jennifer Walsh | I8: Active | J8: 46266 | K8: HR data governance
A9: SA-008 | B9: Sarah Mitchell | C9: sarah.mitchell@company.com | D9: VP of Finance Systems | E9: Finance | F9: Finance Systems - Global | G9: 45031 | H9: Michael Stevens | I9: Active | J9: 46310 | K9: Financial data authority
A10: SA-009 | B10: Raymond Diaz | C10: raymond.diaz@company.com | D10: Cloud Platform Architect | E10: IT | F10: Global - Cloud Infrastructure | G10: 45296 | H10: Robert Chen | I10: Active | J10: 46208 | K10: AWS/Azure/GCP root access
A11: SA-010 | B11: Margaret Sullivan | C11: margaret.sullivan@company.com | D11: Identity & Access Manager | E11: Security | F11: Global - IAM Systems | G11: 45250 | H11: Elizabeth Morgan | I11: Active | J11: 46346 | K11: Identity management authority
A12: SA-011 | B12: Timothy Foster | C12: timothy.foster@company.com | D12: Disaster Recovery Manager | E12: IT | F12: Global - DR Systems | G12: 45361 | H12: Christopher Blake | I12: Active | J12: 46275 | K12: DR failover authority
A13: SA-012 | B13: Diane Wilson | C13: diane.wilson@company.com | D13: Database Administrator Lead | E13: IT | F13: Global - Databases | G13: 45122 | H13: Christopher Blake | I13: Active | J13: 46218 | K13: DBA root access all environments
A15: ⚠️ RESTRICTED ACCESS: Super Admin privileges require CIO or CEO approval. Access is audited and reviewed quarterly.

Sheet Releases
A1: 🔍 FILTERS
A2: Department: | B2: All | C2: Application: | D2: All | E2: Time Period: | F2: All Time | G2: Status: | H2: All | I2: Conflict: | J2: All
A3: Showing: | B3: =COUNTIF(AC5:AC84,TRUE)&" of "&COUNTA(A5:A84)&" releases" -> 80 of 80 releases | L3: 💡 Change filter values above to filter releases. Matching rows are highlighted in green; non-matching rows are greyed out.
A4: Release ID | B4: Release Name | C4: Department | D4: Application | E4: Dependencies | F4: Release Size | G4: Impact | H4: Priority | I4: CAB Date | J4: Start Date | K4: End Date | L4: Test Env Required | M4: UAT Env Required | N4: Status | O4: Conflict Flag | P4: Notes | Q4: Readiness % | R4: Blockers | S4: Vendor Maintenance | T4: Change Freeze | U4: Regulatory | V4: Release Owner ID | W4: Approval Status | X4: Depends On | Y4: Rollback Plan | Z4: Go-Live Checklist % | AA4: Stakeholder IDs | AB4: Deployment Window | AC4: Filter Match
A5: REL-0001 | B5: Kyriba UI Tweak v4.5 | C5: Finance | D5: Kyriba | E5: NA | F5: Small | G5: Low | H5: P4 - Low | I5: 46201 | J5: 46203 | K5: 46203 | L5: FIN-TEST-01 | M5: FIN-UAT-01 | N5: Blocked | O5: ⚠️ CONFLICT | P5: Resource conflict with REL-0003 - Same Test/UAT env required | Q5: 0.75 | R5: Environment conflict with REL-0003; awaiting conflict resolution meeting | T5: Quarter-End Freeze | V5: USR-061 | W5: On Hold | Y5: At Risk | Z5: 0.79 | AA5: USR-073,USR-085,USR-097 | AB5: Off-Peak | AC5: =AND( IF($B$2="All",TRUE,$C5=$B$2), IF($D$2="All",TRUE,$D5=$D$2), IF($H$2="All",TRUE,$N5=$H$2), IF($J$2="All",TRUE,IF($J$2="Has Conflict",$O5<>"",IF($J$2="No Conflict",$O5="",TRUE))), IF($F$2="All Time",TRUE,IF($F$2="Today",$J5=TODAY(),IF($F$2="This Week",AND($J5>=TODAY(),$J5<=TODAY()+7),IF($F$2="This Month",AND($J5>=TODAY(),$J5<=TODAY()+30),AND($J5>=DATE(YEAR(TODAY()),1,1),$J5<=DATE(YEAR(TODAY()),12,31)))))) ) -> TRUE
A6: REL-0002 | B6: Blue Workflow Automation v2.1 | C6: Logistics | D6: Blue Yonder WMS | E6: NA | F6: Medium | G6: High | H6: P1 - Critical | I6: 46205 | J6: 46207 | K6: 46208 | L6: LOG-TEST-01 | M6: LOG-UAT-01 | N6: Approved | P6: Executive sponsor: CFO | Q6: 0.95 | V6: USR-062 | W6: CAB Approved | Y6: Ready | Z6: 0.85 | AA6: USR-074,USR-086,USR-098 | AB6: Weekend | AC6: =AND( IF($B$2="All",TRUE,$C6=$B$2), IF($D$2="All",TRUE,$D6=$D$2), IF($H$2="All",TRUE,$N6=$H$2), IF($J$2="All",TRUE,IF($J$2="Has Conflict",$O6<>"",IF($J$2="No Conflict",$O6="",TRUE))), IF($F$2="All Time",TRUE,IF($F$2="Today",$J6=TODAY(),IF($F$2="This Week",AND($J6>=TODAY(),$J6<=TODAY()+7),IF($F$2="This Month",AND($J6>=TODAY(),$J6<=TODAY()+30),AND($J6>=DATE(YEAR(TODAY()),1,1),$J6<=DATE(YEAR(TODAY()),12,31)))))) ) -> TRUE
A7: REL-0003 | B7: Zendesk Minor Update v4.3 | C7: CRM | D7: Zendesk | E7: NA | F7: Small | G7: Low | H7: P3 - Medium | I7: 46203 | J7: 46205 | K7: 46205 | L7: FIN-TEST-01 | M7: FIN-UAT-01 | N7: Approved | O7: ⚠️ CONFLICT | P7: Resource conflict with REL-0007 - Same Test/UAT env required | Q7: 0.7 | R7: Shared UAT env with REL-0001; QA sign-off pending | V7: USR-063 | W7: CAB Approved | Y7: Ready | Z7: 0.91 | AA7: USR-075,USR-087,USR-097 | AB7: Business Hours | AC7: =AND( IF($B$2="All",TRUE,$C7=$B$2), IF($D$2="All",TRUE,$D7=$D$2), IF($H$2="All",TRUE,$N7=$H$2), IF($J$2="All",TRUE,IF($J$2="Has Conflict",$O7<>"",IF($J$2="No Conflict",$O7="",TRUE))), IF($F$2="All Time",TRUE,IF($F$2="Today",$J7=TODAY(),IF($F$2="This Week",AND($J7>=TODAY(),$J7<=TODAY()+7),IF($F$2="This Month",AND($J7>=TODAY(),$J7<=TODAY()+30),AND($J7>=DATE(YEAR(TODAY()),1,1),$J7<=DATE(YEAR(TODAY()),12,31)))))) ) -> TRUE
A8: REL-0004 | B8: AVEVA Dashboard Upgrade v5.5 | C8: Manufacturing | D8: AVEVA MES | E8: NA | F8: Medium | G8: High | H8: P1 - Critical | I8: 46213 | J8: 46215 | K8: 46216 | L8: MAN-TEST-03 | M8: MAN-UAT-01 | N8: Pending CAB | P8: Blackout period consideration | Q8: 0.88 | V8: USR-064 | W8: CAB Submitted | Y8: In Progress | Z8: 0.78 | AA8: USR-076,USR-088,USR-098 | AB8: Weekend | AC8: =AND( IF($B$2="All",TRUE,$C8=$B$2), IF($D$2="All",TRUE,$D8=$D$2), IF($H$2="All",TRUE,$N8=$H$2), IF($J$2="All",TRUE,IF($J$2="Has Conflict",$O8<>"",IF($J$2="No Conflict",$O8="",TRUE))), IF($F$2="All Time",TRUE,IF($F$2="Today",$J8=TODAY(),IF($F$2="This Week",AND($J8>=TODAY(),$J8<=TODAY()+7),IF($F$2="This Month",AND($J8>=TODAY(),$J8<=TODAY()+30),AND($J8>=DATE(YEAR(TODAY()),1,1),$J8<=DATE(YEAR(TODAY()),12,31)))))) ) -> TRUE
A9: REL-0005 | B9: Datadog Security Patch Bundle v3.5 | C9: IT | D9: Datadog | E9: NA | F9: Medium | G9: High | H9: P2 - High | I9: 46217 | J9: 46219 | K9: 46220 | L9: IT-TEST-01 | M9: IT-UAT-01 | N9: Testing | O9: ⚠️ CONFLICT | P9: Resource conflict with REL-0010 - Same Test/UAT env required | Q9: 0.8 | R9: Security review in progress; awaiting CISO approval | V9: USR-065 | W9: Testing | Y9: In Progress | Z9: 0.52 | AA9: USR-077,USR-089,USR-097 | AB9: Off-Peak | AC9: =AND( IF($B$2="All",TRUE,$C9=$B$2), IF($D$2="All",TRUE,$D9=$D$2), IF($H$2="All",TRUE,$N9=$H$2), IF($J$2="All",TRUE,IF($J$2="Has Conflict",$O9<>"",IF($J$2="No Conflict",$O9="",TRUE))), IF($F$2="All Time",TRUE,IF($F$2="Today",$J9=TODAY(),IF($F$2="This Week",AND($J9>=TODAY(),$J9<=TODAY()+7),IF($F$2="This Month",AND($J9>=TODAY(),$J9<=TODAY()+30),AND($J9>=DATE(YEAR(TODAY()),1,1),$J9<=DATE(YEAR(TODAY()),12,31)))))) ) -> TRUE
A10: REL-0006 | B10: SAP Configuration Change v5.2 | C10: HR | D10: SAP SuccessFactors | E10: NA | F10: Small | G10: Medium | H10: P2 - High | I10: 46221 | J10: 46223 | K10: 46223 | L10: HR-TEST-01 | M10: HR-UAT-01 | N10: Testing | P10: Integration testing with downstream systems | Q10: 0.82 | V10: USR-066 | W10: Testing | Y10: In Progress | Z10: 0.64 | AA10: USR-078,USR-090,USR-098 | AB10: Business Hours | AC10: =AND( IF($B$2="All",TRUE,$C10=$B$2), IF($D$2="All",TRUE,$D10=$D$2), IF($H$2="All",TRUE,$N10=$H$2), IF($J$2="All",TRUE,IF($J$2="Has Conflict",$O10<>"",IF($J$2="No Conflict",$O10="",TRUE))), IF($F$2="All Time",TRUE,IF($F$2="Today",$J10=TODAY(),IF($F$2="This Week",AND($J10>=TODAY(),$J10<=TODAY()+7),IF($F$2="This Month",AND($J10>=TODAY(),$J10<=TODAY()+30),AND($J10>=DATE(YEAR(TODAY()),1,1),$J10<=DATE(YEAR(TODAY()),12,31)))))) ) -> TRUE
A11: REL-0007 | B11: Mitratech Integration Enhancement v5.2 | C11: Legal | D11: Mitratech TeamConnect | E11: NA | F11: Medium | G11: High | H11: P2 - High | I11: 46205 | J11: 46207 | K11: 46208 | L11: FIN-TEST-01 | M11: FIN-UAT-01 | N11: Approved | O11: ⚠️ CONFLICT | P11: Resource conflict with REL-0012 - Same Test/UAT env required | Q11: 0.65 | R11: Integration testing delayed; 3rd party API dependency unresolved | V11: USR-067 | W11: CAB Approved | Y11: Ready | Z11: 0.88 | AA11: USR-079,USR-091,USR-097 | AB11: Weekend | AC11: =AND( IF($B$2="All",TRUE,$C11=$B$2), IF($D$2="All",TRUE,$D11=$D$2), IF($H$2="All",TRUE,$N11=$H$2), IF($J$2="All",TRUE,IF($J$2="Has Conflict",$O11<>"",IF($J$2="No Conflict",$O11="",TRUE))), IF($F$2="All Time",TRUE,IF($F$2="Today",$J11=TODAY(),IF($F$2="This Week",AND($J11>=TODAY(),$J11<=TODAY()+7),IF($F$2="This Month",AND($J11>=TODAY(),$J11<=TODAY()+30),AND($J11>=DATE(YEAR(TODAY()),1,1),$J11<=DATE(YEAR(TODAY()),12,31)))))) ) -> TRUE
A12: REL-0008 | B12: CrowdStrike Minor Update v3.6 | C12: Security | D12: CrowdStrike Falcon | E12: NA | F12: Small | G12: Low | H12: P3 - Medium | I12: 46232 | J12: 46234 | K12: 46234 | L12: SEC-TEST-01 | M12: SEC-UAT-02 | N12: Planning | P12: Data migration included | Q12: 0.7 | V12: USR-068 | W12: Planning | Y12: Not Started | Z12: 0.26 | AA12: USR-080,USR-092,USR-098 | AB12: Off-Peak | AC12: =AND( IF($B$2="All",TRUE,$C12=$B$2), IF($D$2="All",TRUE,$D12=$D$2), IF($H$2="All",TRUE,$N12=$H$2), IF($J$2="All",TRUE,IF($J$2="Has Conflict",$O12<>"",IF($J$2="No Conflict",$O12="",TRUE))), IF($F$2="All Time",TRUE,IF($F$2="Today",$J12=TODAY(),IF($F$2="This Week",AND($J12>=TODAY(),$J12<=TODAY()+7),IF($F$2="This Month",AND($J12>=TODAY(),$J12<=TODAY()+30),AND($J12>=DATE(YEAR(TODAY()),1,1),$J12<=DATE(YEAR(TODAY()),12,31)))))) ) -> TRUE
A13: REL-0009 | B13: Oracle Report Fix v3.4 | C13: Finance | D13: Oracle Hyperion HFM | E13: {=IFERROR(_xlfn.TEXTJOIN(CHAR(10),TRUE,_xlfn._xlws.FILTER(#REF!&": "&#REF!,#REF!=$A13,"")),"")} | F13: Small | G13: Medium | H13: P2 - High | I13: 46236 | J13: 46238 | K13: 46238 | L13: FIN-TEST-03 | M13: FIN-UAT-01 | N13: Planning | O13: ⚠️ CONFLICT | P13: Resource conflict with REL-0014 - Same Test/UAT env required | Q13: 0.55 | R13: UAT defects being triaged; 2 P2 bugs outstanding | V13: USR-001 | W13: Planning | X13: REL-0007 | Y13: Not Started | Z13: 0.27 | AA13: USR-073,USR-085,USR-097 | AB13: Business Hours | AC13: =AND( IF($B$2="All",TRUE,$C13=$B$2), IF($D$2="All",TRUE,$D13=$D$2), IF($H$2="All",TRUE,$N13=$H$2), IF($J$2="All",TRUE,IF($J$2="Has Conflict",$O13<>"",IF($J$2="No Conflict",$O13="",TRUE))), IF($F$2="All Time",TRUE,IF($F$2="Today",$J13=TODAY(),IF($F$2="This Week",AND($J13>=TODAY(),$J13<=TODAY()+7),IF($F$2="This Month",AND($J13>=TODAY(),$J13<=TODAY()+30),AND($J13>=DATE(YEAR(TODAY()),1,1),$J13<=DATE(YEAR(TODAY()),12,31)))))) ) -> TRUE
A14: REL-0010 | B14: Manhattan Major Enhancement v5.2 | C14: Logistics | D14: Manhattan Associates WMS | E14: NA | F14: Large | G14: Medium | H14: P2 - High | I14: 46218 | J14: 46221 | K14: 46223 | L14: IT-TEST-01 | M14: IT-UAT-01 | N14: Testing | O14: ⚠️ CONFLICT | P14: Resource conflict with REL-0005 - Same Test/UAT env required | Q14: 0.6 | R14: Performance testing incomplete; DB migration script needs optimization | V14: USR-002 | W14: Testing | Y14: In Progress | Z14: 0.64 | AA14: USR-074,USR-086,USR-098 | AB14: Weekend | AC14: =AND( IF($B$2="All",TRUE,$C14=$B$2), IF($D$2="All",TRUE,$D14=$D$2), IF($H$2="All",TRUE,$N14=$H$2), IF($J$2="All",TRUE,IF($J$2="Has Conflict",$O14<>"",IF($J$2="No Conflict",$O14="",TRUE))), IF($F$2="All Time",TRUE,IF($F$2="Today",$J14=TODAY(),IF($F$2="This Week",AND($J14>=TODAY(),$J14<=TODAY()+7),IF($F$2="This Month",AND($J14>=TODAY(),$J14<=TODAY()+30),AND($J14>=DATE(YEAR(TODAY()),1,1),$J14<=DATE(YEAR(TODAY()),12,31)))))) ) -> TRUE
A15: REL-0011 | B15: HubSpot Minor Update v3.7 | C15: CRM | D15: HubSpot CRM | E15: NA | F15: Small | G15: Low | H15: P3 - Medium | I15: 46244 | J15: 46246 | K15: 46246 | L15: CRM-TEST-02 | M15: CRM-UAT-01 | N15: Planning | O15: ⚠️ CONFLICT | P15: Resource conflict with REL-0014 - Same Test/UAT env required | Q15: 0.4 | V15: USR-003 | W15: Planning | Y15: Not Started | Z15: 0.29 | AA15: USR-075,USR-087,USR-097 | AB15: Business Hours | AC15: =AND( IF($B$2="All",TRUE,$C15=$B$2), IF($D$2="All",TRUE,$D15=$D$2), IF($H$2="All",TRUE,$N15=$H$2), IF($J$2="All",TRUE,IF($J$2="Has Conflict",$O15<>"",IF($J$2="No Conflict",$O15="",TRUE))), IF($F$2="All Time",TRUE,IF($F$2="Today",$J15=TODAY(),IF($F$2="This Week",AND($J15>=TODAY(),$J15<=TODAY()+7),IF($F$2="This Month",AND($J15>=TODAY(),$J15<=TODAY()+30),AND($J15>=DATE(YEAR(TODAY()),1,1),$J15<=DATE(YEAR(TODAY()),12,31)))))) ) -> TRUE
A16: REL-0012 | B16: Plex Report Fix v2.5 | C16: Manufacturing | D16: Plex Smart Manufacturing | E16: NA | F16: Small | G16: Medium | H16: P3 - Medium | I16: 46207 | J16: 46209 | K16: 46209 | L16: FIN-TEST-01 | M16: FIN-UAT-01 | N16: Approved | O16: ⚠️ CONFLICT | P16: Resource conflict with REL-0007 - Same Test/UAT env required | Q16: 0.72 | R16: Test data refresh pending; blocked on DBA availability | V16: USR-004 | W16: CAB Approved | Y16: Ready | Z16: 0.89 | AA16: USR-076,USR-088,USR-098 | AB16: Off-Peak | AC16: =AND( IF($B$2="All",TRUE,$C16=$B$2), IF($D$2="All",TRUE,$D16=$D$2), IF($H$2="All",TRUE,$N16=$H$2), IF($J$2="All",TRUE,IF($J$2="Has Conflict",$O16<>"",IF($J$2="No Conflict",$O16="",TRUE))), IF($F$2="All Time",TRUE,IF($F$2="Today",$J16=TODAY(),IF($F$2="This Week",AND($J16>=TODAY(),$J16<=TODAY()+7),IF($F$2="This Month",AND($J16>=TODAY(),$J16<=TODAY()+30),AND($J16>=DATE(YEAR(TODAY()),1,1),$J16<=DATE(YEAR(TODAY()),12,31)))))) ) -> TRUE
A17: REL-0013 | B17: Dynatrace UI Tweak v3.1 | C17: IT | D17: Dynatrace | E17: {=IFERROR(_xlfn.TEXTJOIN(CHAR(10),TRUE,_xlfn._xlws.FILTER(#REF!&": "&#REF!,#REF!=$A17,"")),"")} | F17: Small | G17: Low | H17: P3 - Medium | I17: 46252 | J17: 46254 | K17: 46254 | L17: IT-TEST-03 | M17: IT-UAT-01 | N17: Planning | O17: ⚠️ CONFLICT | P17: Resource conflict with REL-0015 - Same Test/UAT env required | Q17: 0.35 | V17: USR-005 | W17: Planning | X17: REL-0012 | Y17: Not Started | Z17: 0.49 | AA17: USR-077,USR-089,USR-097 | AB17: Business Hours | AC17: =AND( IF($B$2="All",TRUE,$C17=$B$2), IF($D$2="All",TRUE,$D17=$D$2), IF($H$2="All",TRUE,$N17=$H$2), IF($J$2="All",TRUE,IF($J$2="Has Conflict",$O17<>"",IF($J$2="No Conflict",$O17="",TRUE))), IF($F$2="All Time",TRUE,IF($F$2="Today",$J17=TODAY(),IF($F$2="This Week",AND($J17>=TODAY(),$J17<=TODAY()+7),IF($F$2="This Month",AND($J17>=TODAY(),$J17<=TODAY()+30),AND($J17>=DATE(YEAR(TODAY()),1,1),$J17<=DATE(YEAR(TODAY()),12,31)))))) ) -> TRUE
A18: REL-0014 | B18: Oracle Global Rollout v2.2 | C18: HR | D18: Oracle HCM Cloud | E18: NA | F18: Large | G18: High | H18: P2 - High | I18: 46245 | J18: 46248 | K18: 46250 | L18: CRM-TEST-02 | M18: CRM-UAT-01 | N18: Planning | O18: ⚠️ CONFLICT | P18: Resource conflict with REL-0011 - Same Test/UAT env required | Q18: 0.45 | R18: Global rollout coordination pending; APAC team capacity constrained | V18: USR-006 | W18: Planning | Y18: Not Started | Z18: 0.21 | AA18: USR-078,USR-090,USR-098 | AB18: Weekend | AC18: =AND( IF($B$2="All",TRUE,$C18=$B$2), IF($D$2="All",TRUE,$D18=$D$2), IF($H$2="All",TRUE,$N18=$H$2), IF($J$2="All",TRUE,IF($J$2="Has Conflict",$O18<>"",IF($J$2="No Conflict",$O18="",TRUE))), IF($F$2="All Time",TRUE,IF($F$2="Today",$J18=TODAY(),IF($F$2="This Week",AND($J18>=TODAY(),$J18<=TODAY()+7),IF($F$2="This Month",AND($J18>=TODAY(),$J18<=TODAY()+30),AND($J18>=DATE(YEAR(TODAY()),1,1),$J18<=DATE(YEAR(TODAY()),12,31)))))) ) -> TRUE
A19: REL-0015 | B19: DocuSign Core Transformation v1.0 | C19: Legal | D19: DocuSign CLM | E19: NA | F19: Large | G19: High | H19: P2 - High | I19: 46253 | J19: 46256 | K19: 46258 | L19: IT-TEST-03 | M19: IT-UAT-01 | N19: Planning | O19: ⚠️ CONFLICT | P19: Resource conflict with REL-0017 - Same Test/UAT env required | Q19: 0.38 | R19: Architecture review required; security scan findings need remediation | V19: USR-061 | W19: Planning | Y19: Not Started | Z19: 0.24 | AA19: USR-079,USR-091,USR-097 | AB19: Weekend | AC19: =AND( IF($B$2="All",TRUE,$C19=$B$2), IF($D$2="All",TRUE,$D19=$D$2), IF($H$2="All",TRUE,$N19=$H$2), IF($J$2="All",TRUE,IF($J$2="Has Conflict",$O19<>"",IF($J$2="No Conflict",$O19="",TRUE))), IF($F$2="All Time",TRUE,IF($F$2="Today",$J19=TODAY(),IF($F$2="This Week",AND($J19>=TODAY(),$J19<=TODAY()+7),IF($F$2="This Month",AND($J19>=TODAY(),$J19<=TODAY()+30),AND($J19>=DATE(YEAR(TODAY()),1,1),$J19<=DATE(YEAR(TODAY()),12,31)))))) ) -> TRUE
A20: REL-0016 | B20: CyberArk Enterprise Integration v2.0 | C20: Security | D20: CyberArk PAM | E20: NA | F20: Large | G20: High | H20: P2 - High | I20: 46266 | J20: 46269 | K20: 46271 | L20: SEC-TEST-01 | M20: SEC-UAT-02 | N20: Draft | P20: Change Advisory Board approval needed | U20: SOC2 Requirement | V20: USR-062 | W20: Draft | Y20: Not Started | Z20: 0.07 | AA20: USR-080,USR-092,USR-098 | AB20: Weekend | AC20: =AND( IF($B$2="All",TRUE,$C20=$B$2), IF($D$2="All",TRUE,$D20=$D$2), IF($H$2="All",TRUE,$N20=$H$2), IF($J$2="All",TRUE,IF($J$2="Has Conflict",$O20<>"",IF($J$2="No Conflict",$O20="",TRUE))), IF($F$2="All Time",TRUE,IF($F$2="Today",$J20=TODAY(),IF($F$2="This Week",AND($J20>=TODAY(),$J20<=TODAY()+7),IF($F$2="This Month",AND($J20>=TODAY(),$J20<=TODAY()+30),AND($J20>=DATE(YEAR(TODAY()),1,1),$J20<=DATE(YEAR(TODAY()),12,31)))))) ) -> TRUE
A21: REL-0017 | B21: HighRadius Report Fix v2.4 | C21: Finance | D21: HighRadius | E21: {=IFERROR(_xlfn.TEXTJOIN(CHAR(10),TRUE,_xlfn._xlws.FILTER(#REF!&": "&#REF!,#REF!=$A21,"")),"")} | F21: Small | G21: Low | H21: P3 - Medium | I21: 46256 | J21: 46258 | K21: 46258 | L21: IT-TEST-03 | M21: IT-UAT-01 | N21: Planning | O21: ⚠️ CONFLICT | P21: Resource conflict with REL-0022 - Same Test/UAT env required | Q21: 0.3 | V21: USR-063 | W21: Planning | X21: REL-0014,REL-0012 | Y21: Not Started | Z21: 0.35 | AA21: USR-073,USR-085,USR-097 | AB21: Off-Peak | AC21: =AND( IF($B$2="All",TRUE,$C21=$B$2), IF($D$2="All",TRUE,$D21=$D$2), IF($H$2="All",TRUE,$N21=$H$2), IF($J$2="All",TRUE,IF($J$2="Has Conflict",$O21<>"",IF($J$2="No Conflict",$O21="",TRUE))), IF($F$2="All Time",TRUE,IF($F$2="Today",$J21=TODAY(),IF($F$2="This Week",AND($J21>=TODAY(),$J21<=TODAY()+7),IF($F$2="This Month",AND($J21>=TODAY(),$J21<=TODAY()+30),AND($J21>=DATE(YEAR(TODAY()),1,1),$J21<=DATE(YEAR(TODAY()),12,31)))))) ) -> TRUE
A22: REL-0018 | B22: Oracle UI Tweak v2.0 | C22: Logistics | D22: Oracle Transportation Management | E22: NA | F22: Small | G22: Low | H22: P3 - Medium | I22: 46275 | J22: 46277 | K22: 46277 | L22: LOG-TEST-03 | M22: LOG-UAT-02 | N22: Draft | P22: Audit finding remediation | V22: USR-064 | W22: Draft | Y22: Not Started | Z22: 0.02 | AA22: USR-074,USR-086,USR-098 | AB22: Off-Peak | AC22: =AND( IF($B$2="All",TRUE,$C22=$B$2), IF($D$2="All",TRUE,$D22=$D$2), IF($H$2="All",TRUE,$N22=$H$2), IF($J$2="All",TRUE,IF($J$2="Has Conflict",$O22<>"",IF($J$2="No Conflict",$O22="",TRUE))), IF($F$2="All Time",TRUE,IF($F$2="Today",$J22=TODAY(),IF($F$2="This Week",AND($J22>=TODAY(),$J22<=TODAY()+7),IF($F$2="This Month",AND($J22>=TODAY(),$J22<=TODAY()+30),AND($J22>=DATE(YEAR(TODAY()),1,1),$J22<=DATE(YEAR(TODAY()),12,31)))))) ) -> TRUE
A23: REL-0019 | B23: Salesforce Minor Update v2.5 | C23: CRM | D23: Salesforce Service Cloud | E23: NA | F23: Small | G23: Low | H23: P3 - Medium | I23: 46279 | J23: 46281 | K23: 46281 | L23: CRM-TEST-01 | M23: CRM-UAT-02 | N23: Draft | O23: ⚠️ CONFLICT | P23: Resource conflict with REL-0021 - Same Test/UAT env required | V23: USR-065 | W23: Draft | Y23: Not Started | Z23: 0.05 | AA23: USR-075,USR-087,USR-097 | AB23: Business Hours | AC23: =AND( IF($B$2="All",TRUE,$C23=$B$2), IF($D$2="All",TRUE,$D23=$D$2), IF($H$2="All",TRUE,$N23=$H$2), IF($J$2="All",TRUE,IF($J$2="Has Conflict",$O23<>"",IF($J$2="No Conflict",$O23="",TRUE))), IF($F$2="All Time",TRUE,IF($F$2="Today",$J23=TODAY(),IF($F$2="This Week",AND($J23>=TODAY(),$J23<=TODAY()+7),IF($F$2="This Month",AND($J23>=TODAY(),$J23<=TODAY()+30),AND($J23>=DATE(YEAR(TODAY()),1,1),$J23<=DATE(YEAR(TODAY()),12,31)))))) ) -> TRUE
A24: REL-0020 | B24: Rockwell Quick Enhancement v1.5 | C24: Manufacturing | D24: Rockwell FactoryTalk | E24: NA | F24: Small | G24: Low | H24: P3 - Medium | I24: 46283 | J24: 46285 | K24: 46285 | L24: MAN-TEST-03 | M24: MAN-UAT-01 | N24: Draft | P24: Holiday freeze exception requested | V24: USR-066 | W24: Draft | Y24: Not Started | Z24: 0.16 | AA24: USR-076,USR-088,USR-098 | AB24: Business Hours | AC24: =AND( IF($B$2="All",TRUE,$C24=$B$2), IF($D$2="All",TRUE,$D24=$D$2), IF($H$2="All",TRUE,$N24=$H$2), IF($J$2="All",TRUE,IF($J$2="Has Conflict",$O24<>"",IF($J$2="No Conflict",$O24="",TRUE))), IF($F$2="All Time",TRUE,IF($F$2="Today",$J24=TODAY(),IF($F$2="This Week",AND($J24>=TODAY(),$J24<=TODAY()+7),IF($F$2="This Month",AND($J24>=TODAY(),$J24<=TODAY()+30),AND($J24>=DATE(YEAR(TODAY()),1,1),$J24<=DATE(YEAR(TODAY()),12,31)))))) ) -> TRUE
A25: REL-0021 | B25: Splunk Bug Fix Release v3.7 | C25: IT | D25: Splunk Enterprise | E25: {=IFERROR(_xlfn.TEXTJOIN(CHAR(10),TRUE,_xlfn._xlws.FILTER(#REF!&": "&#REF!,#REF!=$A25,"")),"")} | F25: Small | G25: Low | H25: P3 - Medium | I25: 46281 | J25: 46283 | K25: 46283 | L25: CRM-TEST-01 | M25: CRM-UAT-02 | N25: Draft | O25: ⚠️ CONFLICT | P25: Resource conflict with REL-0026 - Same Test/UAT env required | V25: USR-067 | W25: Draft | X25: REL-0019 | Y25: Not Started | Z25: 0.04 | AA25: USR-077,USR-089,USR-097 | AB25: Business Hours | AC25: =AND( IF($B$2="All",TRUE,$C25=$B$2), IF($D$2="All",TRUE,$D25=$D$2), IF($H$2="All",TRUE,$N25=$H$2), IF($J$2="All",TRUE,IF($J$2="Has Conflict",$O25<>"",IF($J$2="No Conflict",$O25="",TRUE))), IF($F$2="All Time",TRUE,IF($F$2="Today",$J25=TODAY(),IF($F$2="This Week",AND($J25>=TODAY(),$J25<=TODAY()+7),IF($F$2="This Month",AND($J25>=TODAY(),$J25<=TODAY()+30),AND($J25>=DATE(YEAR(TODAY()),1,1),$J25<=DATE(YEAR(TODAY()),12,31)))))) ) -> TRUE
A26: REL-0022 | B26: Oracle Dashboard Upgrade v2.5 | C26: HR | D26: Oracle HCM Cloud | E26: NA | F26: Medium | G26: Low | H26: P3 - Medium | I26: 46258 | J26: 46260 | K26: 46261 | L26: IT-TEST-03 | M26: IT-UAT-01 | N26: Planning | O26: ⚠️ CONFLICT | P26: Resource conflict with REL-0017 - Same Test/UAT env required | Q26: 0.28 | R26: Requirements still being finalized with business stakeholders | V26: USR-068 | W26: Planning | Y26: Not Started | Z26: 0.32 | AA26: USR-078,USR-090,USR-098 | AB26: Weekend | AC26: =AND( IF($B$2="All",TRUE,$C26=$B$2), IF($D$2="All",TRUE,$D26=$D$2), IF($H$2="All",TRUE,$N26=$H$2), IF($J$2="All",TRUE,IF($J$2="Has Conflict",$O26<>"",IF($J$2="No Conflict",$O26="",TRUE))), IF($F$2="All Time",TRUE,IF($F$2="Today",$J26=TODAY(),IF($F$2="This Week",AND($J26>=TODAY(),$J26<=TODAY()+7),IF($F$2="This Month",AND($J26>=TODAY(),$J26<=TODAY()+30),AND($J26>=DATE(YEAR(TODAY()),1,1),$J26<=DATE(YEAR(TODAY()),12,31)))))) ) -> TRUE
A27: REL-0023 | B27: DocuSign Feature Release v3.0 | C27: Legal | D27: DocuSign CLM | E27: NA | F27: Medium | G27: High | H27: P1 - Critical | I27: 46297 | J27: 46299 | K27: 46300 | L27: LEG-TEST-02 | M27: LEG-UAT-02 | N27: Draft | O27: ⚠️ CONFLICT | P27: Resource conflict with REL-0027 - Same Test/UAT env required | V27: USR-001 | W27: Draft | Y27: Not Started | Z27: 0.05 | AA27: USR-079,USR-091,USR-097 | AB27: Weekend | AC27: =AND( IF($B$2="All",TRUE,$C27=$B$2), IF($D$2="All",TRUE,$D27=$D$2), IF($H$2="All",TRUE,$N27=$H$2), IF($J$2="All",TRUE,IF($J$2="Has Conflict",$O27<>"",IF($J$2="No Conflict",$O27="",TRUE))), IF($F$2="All Time",TRUE,IF($F$2="Today",$J27=TODAY(),IF($F$2="This Week",AND($J27>=TODAY(),$J27<=TODAY()+7),IF($F$2="This Month",AND($J27>=TODAY(),$J27<=TODAY()+30),AND($J27>=DATE(YEAR(TODAY()),1,1),$J27<=DATE(YEAR(TODAY()),12,31)))))) ) -> TRUE
A28: REL-0024 | B28: Okta Minor Update v4.1 | C28: Security | D28: Okta Identity Cloud | E28: NA | F28: Small | G28: Low | H28: P3 - Medium | I28: 46301 | J28: 46303 | K28: 46303 | L28: SEC-TEST-01 | M28: SEC-UAT-02 | N28: Draft | P28: Security review pending | V28: USR-002 | W28: Draft | Y28: Not Started | Z28: 0.04 | AA28: USR-080,USR-092,USR-098 | AB28: Business Hours | AC28: =AND( IF($B$2="All",TRUE,$C28=$B$2), IF($D$2="All",TRUE,$D28=$D$2), IF($H$2="All",TRUE,$N28=$H$2), IF($J$2="All",TRUE,IF($J$2="Has Conflict",$O28<>"",IF($J$2="No Conflict",$O28="",TRUE))), IF($F$2="All Time",TRUE,IF($F$2="Today",$J28=TODAY(),IF($F$2="This Week",AND($J28>=TODAY(),$J28<=TODAY()+7),IF($F$2="This Month",AND($J28>=TODAY(),$J28<=TODAY()+30),AND($J28>=DATE(YEAR(TODAY()),1,1),$J28<=DATE(YEAR(TODAY()),12,31)))))) ) -> TRUE
A29: REL-0025 | B29: Coupa Dashboard Upgrade v5.8 | C29: Finance | D29: Coupa | E29: {=IFERROR(_xlfn.TEXTJOIN(CHAR(10),TRUE,_xlfn._xlws.FILTER(#REF!&": "&#REF!,#REF!=$A29,"")),"")} | F29: Medium | G29: Medium | H29: P3 - Medium | I29: 46305 | J29: 46307 | K29: 46308 | L29: FIN-TEST-03 | M29: FIN-UAT-02 | N29: Draft | P29: DR sync required post-deployment | U29: SOX Compliance | V29: USR-003 | W29: Draft | X29: REL-0022,REL-0020 | Y29: Not Started | Z29: 0.09 | AA29: USR-073,USR-085,USR-097 | AB29: Weekend | AC29: =AND( IF($B$2="All",TRUE,$C29=$B$2), IF($D$2="All",TRUE,$D29=$D$2), IF($H$2="All",TRUE,$N29=$H$2), IF($J$2="All",TRUE,IF($J$2="Has Conflict",$O29<>"",IF($J$2="No Conflict",$O29="",TRUE))), IF($F$2="All Time",TRUE,IF($F$2="Today",$J29=TODAY(),IF($F$2="This Week",AND($J29>=TODAY(),$J29<=TODAY()+7),IF($F$2="This Month",AND($J29>=TODAY(),$J29<=TODAY()+30),AND($J29>=DATE(YEAR(TODAY()),1,1),$J29<=DATE(YEAR(TODAY()),12,31)))))) ) -> TRUE
A30: REL-0026 | B30: Kinaxis Dashboard Upgrade v3.2 | C30: Logistics | D30: Kinaxis RapidResponse | E30: NA | F30: Medium | G30: Low | H30: P3 - Medium | I30: 46283 | J30: 46285 | K30: 46286 | L30: CRM-TEST-01 | M30: CRM-UAT-02 | N30: Draft | O30: ⚠️ CONFLICT | P30: Resource conflict with REL-0021 - Same Test/UAT env required | V30: USR-004 | W30: Draft | Y30: Not Started | Z30: 0.05 | AA30: USR-074,USR-086,USR-098 | AB30: Off-Peak | AC30: =AND( IF($B$2="All",TRUE,$C30=$B$2), IF($D$2="All",TRUE,$D30=$D$2), IF($H$2="All",TRUE,$N30=$H$2), IF($J$2="All",TRUE,IF($J$2="Has Conflict",$O30<>"",IF($J$2="No Conflict",$O30="",TRUE))), IF($F$2="All Time",TRUE,IF($F$2="Today",$J30=TODAY(),IF($F$2="This Week",AND($J30>=TODAY(),$J30<=TODAY()+7),IF($F$2="This Month",AND($J30>=TODAY(),$J30<=TODAY()+30),AND($J30>=DATE(YEAR(TODAY()),1,1),$J30<=DATE(YEAR(TODAY()),12,31)))))) ) -> TRUE
A31: REL-0027 | B31: Salesforce Hotfix v4.3 | C31: CRM | D31: Salesforce Sales Cloud | E31: NA | F31: Small | G31: Low | H31: P4 - Low | I31: 46299 | J31: 46301 | K31: 46301 | L31: LEG-TEST-02 | M31: LEG-UAT-02 | N31: Draft | O31: ⚠️ CONFLICT | P31: Resource conflict with REL-0023 - Same Test/UAT env required | V31: USR-005 | W31: Draft | Y31: Not Started | Z31: 0.19 | AA31: USR-075,USR-087,USR-097 | AB31: Business Hours | AC31: =AND( IF($B$2="All",TRUE,$C31=$B$2), IF($D$2="All",TRUE,$D31=$D$2), IF($H$2="All",TRUE,$N31=$H$2), IF($J$2="All",TRUE,IF($J$2="Has Conflict",$O31<>"",IF($J$2="No Conflict",$O31="",TRUE))), IF($F$2="All Time",TRUE,IF($F$2="Today",$J31=TODAY(),IF($F$2="This Week",AND($J31>=TODAY(),$J31<=TODAY()+7),IF($F$2="This Month",AND($J31>=TODAY(),$J31<=TODAY()+30),AND($J31>=DATE(YEAR(TODAY()),1,1),$J31<=DATE(YEAR(TODAY()),12,31)))))) ) -> TRUE
A32: REL-0028 | B32: SAP Architecture Overhaul v5.5 | C32: Manufacturing | D32: SAP S/4HANA Manufacturing | E32: NA | F32: Large | G32: High | H32: P2 - High | I32: 46316 | J32: 46319 | K32: 46321 | L32: MAN-TEST-03 | M32: MAN-UAT-01 | N32: Draft | P32: Critical for Q3 financial close | V32: USR-006 | W32: Draft | Y32: Not Started | Z32: 0.02 | AA32: USR-076,USR-088,USR-098 | AB32: Weekend | AC32: =AND( IF($B$2="All",TRUE,$C32=$B$2), IF($D$2="All",TRUE,$D32=$D$2), IF($H$2="All",TRUE,$N32=$H$2), IF($J$2="All",TRUE,IF($J$2="Has Conflict",$O32<>"",IF($J$2="No Conflict",$O32="",TRUE))), IF($F$2="All Time",TRUE,IF($F$2="Today",$J32=TODAY(),IF($F$2="This Week",AND($J32>=TODAY(),$J32<=TODAY()+7),IF($F$2="This Month",AND($J32>=TODAY(),$J32<=TODAY()+30),AND($J32>=DATE(YEAR(TODAY()),1,1),$J32<=DATE(YEAR(TODAY()),12,31)))))) ) -> TRUE
A33: REL-0029 | B33: Datadog Feature Release v2.2 | C33: IT | D33: Datadog | E33: {=IFERROR(_xlfn.TEXTJOIN(CHAR(10),TRUE,_xlfn._xlws.FILTER(#REF!&": "&#REF!,#REF!=$A33,"")),"")} | F33: Medium | G33: Medium | H33: P2 - High | I33: 46324 | J33: 46326 | K33: 46327 | L33: IT-TEST-03 | M33: IT-UAT-01 | N33: Draft | P33: Dependencies on infrastructure team | V33: USR-061 | W33: Draft | X33: REL-0027 | Y33: Not Started | Z33: 0.01 | AA33: USR-077,USR-089,USR-097 | AB33: Weekend | AC33: =AND( IF($B$2="All",TRUE,$C33=$B$2), IF($D$2="All",TRUE,$D33=$D$2), IF($H$2="All",TRUE,$N33=$H$2), IF($J$2="All",TRUE,IF($J$2="Has Conflict",$O33<>"",IF($J$2="No Conflict",$O33="",TRUE))), IF($F$2="All Time",TRUE,IF($F$2="Today",$J33=TODAY(),IF($F$2="This Week",AND($J33>=TODAY(),$J33<=TODAY()+7),IF($F$2="This Month",AND($J33>=TODAY(),$J33<=TODAY()+30),AND($J33>=DATE(YEAR(TODAY()),1,1),$J33<=DATE(YEAR(TODAY()),12,31)))))) ) -> TRUE
A34: REL-0030 | B34: Cornerstone Feature Release v1.7 | C34: HR | D34: Cornerstone OnDemand | E34: NA | F34: Medium | G34: High | H34: P2 - High | I34: 46328 | J34: 46330 | K34: 46331 | L34: HR-TEST-02 | M34: HR-UAT-01 | N34: Draft | P34: Dependent on vendor patch delivery | V34: USR-062 | W34: Draft | Y34: Not Started | Z34: 0.11 | AA34: USR-078,USR-090,USR-098 | AB34: Weekend | AC34: =AND( IF($B$2="All",TRUE,$C34=$B$2), IF($D$2="All",TRUE,$D34=$D$2), IF($H$2="All",TRUE,$N34=$H$2), IF($J$2="All",TRUE,IF($J$2="Has Conflict",$O34<>"",IF($J$2="No Conflict",$O34="",TRUE))), IF($F$2="All Time",TRUE,IF($F$2="Today",$J34=TODAY(),IF($F$2="This Week",AND($J34>=TODAY(),$J34<=TODAY()+7),IF($F$2="This Month",AND($J34>=TODAY(),$J34<=TODAY()+30),AND($J34>=DATE(YEAR(TODAY()),1,1),$J34<=DATE(YEAR(TODAY()),12,31)))))) ) -> TRUE
A35: REL-0031 | B35: Mitratech Data Patch v2.9 | C35: Legal | D35: Mitratech TeamConnect | E35: NA | F35: Small | G35: Low | H35: P3 - Medium | I35: 46332 | J35: 46334 | K35: 46334 | L35: LEG-TEST-02 | M35: LEG-UAT-02 | N35: Draft | P35: Executive sponsor: CIO | U35: GDPR Compliance | V35: USR-063 | W35: Draft | Y35: Not Started | Z35: 0.05 | AA35: USR-079,USR-091,USR-097 | AB35: Off-Peak | AC35: =AND( IF($B$2="All",TRUE,$C35=$B$2), IF($D$2="All",TRUE,$D35=$D$2), IF($H$2="All",TRUE,$N35=$H$2), IF($J$2="All",TRUE,IF($J$2="Has Conflict",$O35<>"",IF($J$2="No Conflict",$O35="",TRUE))), IF($F$2="All Time",TRUE,IF($F$2="Today",$J35=TODAY(),IF($F$2="This Week",AND($J35>=TODAY(),$J35<=TODAY()+7),IF($F$2="This Month",AND($J35>=TODAY(),$J35<=TODAY()+30),AND($J35>=DATE(YEAR(TODAY()),1,1),$J35<=DATE(YEAR(TODAY()),12,31)))))) ) -> TRUE
A36: REL-0032 | B36: CrowdStrike UI Tweak v1.5 | C36: Security | D36: CrowdStrike Falcon | E36: NA | F36: Small | G36: Low | H36: P4 - Low | I36: 46336 | J36: 46338 | K36: 46338 | L36: SEC-TEST-01 | M36: SEC-UAT-02 | N36: Draft | P36: Integration testing with downstream systems | V36: USR-064 | W36: Draft | Y36: Not Started | Z36: 0.04 | AA36: USR-080,USR-092,USR-098 | AB36: Business Hours | AC36: =AND( IF($B$2="All",TRUE,$C36=$B$2), IF($D$2="All",TRUE,$D36=$D$2), IF($H$2="All",TRUE,$N36=$H$2), IF($J$2="All",TRUE,IF($J$2="Has Conflict",$O36<>"",IF($J$2="No Conflict",$O36="",TRUE))), IF($F$2="All Time",TRUE,IF($F$2="Today",$J36=TODAY(),IF($F$2="This Week",AND($J36>=TODAY(),$J36<=TODAY()+7),IF($F$2="This Month",AND($J36>=TODAY(),$J36<=TODAY()+30),AND($J36>=DATE(YEAR(TODAY()),1,1),$J36<=DATE(YEAR(TODAY()),12,31)))))) ) -> TRUE
A37: REL-0033 | B37: Oracle Major Enhancement v5.3 | C37: Finance | D37: Oracle Hyperion HFM | E37: {=IFERROR(_xlfn.TEXTJOIN(CHAR(10),TRUE,_xlfn._xlws.FILTER(#REF!&": "&#REF!,#REF!=$A37,"")),"")} | F37: Large | G37: Medium | H37: P2 - High | I37: 46339 | J37: 46342 | K37: 46344 | L37: FIN-TEST-01 | M37: FIN-UAT-01 | N37: Draft | P37: Dependencies on infrastructure team | V37: USR-065 | W37: Draft | X37: REL-0030,REL-0028 | Y37: Not Started | Z37: 0.06 | AA37: USR-073,USR-085,USR-097 | AB37: Weekend | AC37: =AND( IF($B$2="All",TRUE,$C37=$B$2), IF($D$2="All",TRUE,$D37=$D$2), IF($H$2="All",TRUE,$N37=$H$2), IF($J$2="All",TRUE,IF($J$2="Has Conflict",$O37<>"",IF($J$2="No Conflict",$O37="",TRUE))), IF($F$2="All Time",TRUE,IF($F$2="Today",$J37=TODAY(),IF($F$2="This Week",AND($J37>=TODAY(),$J37<=TODAY()+7),IF($F$2="This Month",AND($J37>=TODAY(),$J37<=TODAY()+30),AND($J37>=DATE(YEAR(TODAY()),1,1),$J37<=DATE(YEAR(TODAY()),12,31)))))) ) -> TRUE
A38: REL-0034 | B38: Manhattan Module Update v2.8 | C38: Logistics | D38: Manhattan Associates WMS | E38: NA | F38: Medium | G38: Low | H38: P3 - Medium | I38: 46344 | J38: 46346 | K38: 46347 | L38: LOG-TEST-01 | M38: LOG-UAT-01 | N38: Draft | P38: Executive sponsor: CFO | V38: USR-066 | W38: Draft | Y38: Not Started | Z38: 0.11 | AA38: USR-074,USR-086,USR-098 | AB38: Off-Peak | AC38: =AND( IF($B$2="All",TRUE,$C38=$B$2), IF($D$2="All",TRUE,$D38=$D$2), IF($H$2="All",TRUE,$N38=$H$2), IF($J$2="All",TRUE,IF($J$2="Has Conflict",$O38<>"",IF($J$2="No Conflict",$O38="",TRUE))), IF($F$2="All Time",TRUE,IF($F$2="Today",$J38=TODAY(),IF($F$2="This Week",AND($J38>=TODAY(),$J38<=TODAY()+7),IF($F$2="This Month",AND($J38>=TODAY(),$J38<=TODAY()+30),AND($J38>=DATE(YEAR(TODAY()),1,1),$J38<=DATE(YEAR(TODAY()),12,31)))))) ) -> TRUE
A39: REL-0035 | B39: Salesforce Report Fix v5.8 | C39: CRM | D39: Salesforce Service Cloud | E39: NA | F39: Small | G39: Medium | H39: P2 - High | I39: 46348 | J39: 46350 | K39: 46350 | L39: CRM-TEST-01 | M39: CRM-UAT-02 | N39: Draft | P39: Change Advisory Board approval needed | V39: USR-067 | W39: Draft | Y39: Not Started | Z39: 0.04 | AA39: USR-075,USR-087,USR-097 | AB39: Business Hours | AC39: =AND( IF($B$2="All",TRUE,$C39=$B$2), IF($D$2="All",TRUE,$D39=$D$2), IF($H$2="All",TRUE,$N39=$H$2), IF($J$2="All",TRUE,IF($J$2="Has Conflict",$O39<>"",IF($J$2="No Conflict",$O39="",TRUE))), IF($F$2="All Time",TRUE,IF($F$2="Today",$J39=TODAY(),IF($F$2="This Week",AND($J39>=TODAY(),$J39<=TODAY()+7),IF($F$2="This Month",AND($J39>=TODAY(),$J39<=TODAY()+30),AND($J39>=DATE(YEAR(TODAY()),1,1),$J39<=DATE(YEAR(TODAY()),12,31)))))) ) -> TRUE
A40: REL-0036 | B40: Plex UI Tweak v3.6 | C40: Manufacturing | D40: Plex Smart Manufacturing | E40: NA | F40: Small | G40: Low | H40: P3 - Medium | I40: 46354 | J40: 46356 | K40: 46356 | L40: MAN-TEST-03 | M40: MAN-UAT-01 | N40: Draft | P40: Data migration included | V40: USR-068 | W40: Draft | Y40: Not Started | Z40: 0.02 | AA40: USR-076,USR-088,USR-098 | AB40: Off-Peak | AC40: =AND( IF($B$2="All",TRUE,$C40=$B$2), IF($D$2="All",TRUE,$D40=$D$2), IF($H$2="All",TRUE,$N40=$H$2), IF($J$2="All",TRUE,IF($J$2="Has Conflict",$O40<>"",IF($J$2="No Conflict",$O40="",TRUE))), IF($F$2="All Time",TRUE,IF($F$2="Today",$J40=TODAY(),IF($F$2="This Week",AND($J40>=TODAY(),$J40<=TODAY()+7),IF($F$2="This Month",AND($J40>=TODAY(),$J40<=TODAY()+30),AND($J40>=DATE(YEAR(TODAY()),1,1),$J40<=DATE(YEAR(TODAY()),12,31)))))) ) -> TRUE
A41: REL-0037 | B41: Dynatrace Platform Upgrade v4.0 | C41: IT | D41: Dynatrace | E41: {=IFERROR(_xlfn.TEXTJOIN(CHAR(10),TRUE,_xlfn._xlws.FILTER(#REF!&": "&#REF!,#REF!=$A41,"")),"")} | F41: Large | G41: High | H41: P1 - Critical | I41: 46357 | J41: 46360 | K41: 46362 | L41: IT-TEST-03 | M41: IT-UAT-02 | N41: Draft | P41: Customer-facing impact - coordinate with support | V41: USR-001 | W41: Draft | X41: REL-0035 | Y41: Not Started | Z41: 0.1 | AA41: USR-077,USR-089,USR-097 | AB41: Weekend | AC41: =AND( IF($B$2="All",TRUE,$C41=$B$2), IF($D$2="All",TRUE,$D41=$D$2), IF($H$2="All",TRUE,$N41=$H$2), IF($J$2="All",TRUE,IF($J$2="Has Conflict",$O41<>"",IF($J$2="No Conflict",$O41="",TRUE))), IF($F$2="All Time",TRUE,IF($F$2="Today",$J41=TODAY(),IF($F$2="This Week",AND($J41>=TODAY(),$J41<=TODAY()+7),IF($F$2="This Month",AND($J41>=TODAY(),$J41<=TODAY()+30),AND($J41>=DATE(YEAR(TODAY()),1,1),$J41<=DATE(YEAR(TODAY()),12,31)))))) ) -> TRUE
A42: REL-0038 | B42: SAP Bug Fix Release v5.5 | C42: HR | D42: SAP SuccessFactors | E42: NA | F42: Small | G42: Low | H42: P3 - Medium | I42: 46362 | J42: 46364 | K42: 46364 | L42: HR-TEST-02 | M42: HR-UAT-02 | N42: Draft | P42: Dependent on vendor patch delivery | V42: USR-002 | W42: Draft | Y42: Not Started | Z42: 0.03 | AA42: USR-078,USR-090,USR-098 | AB42: Off-Peak | AC42: =AND( IF($B$2="All",TRUE,$C42=$B$2), IF($D$2="All",TRUE,$D42=$D$2), IF($H$2="All",TRUE,$N42=$H$2), IF($J$2="All",TRUE,IF($J$2="Has Conflict",$O42<>"",IF($J$2="No Conflict",$O42="",TRUE))), IF($F$2="All Time",TRUE,IF($F$2="Today",$J42=TODAY(),IF($F$2="This Week",AND($J42>=TODAY(),$J42<=TODAY()+7),IF($F$2="This Month",AND($J42>=TODAY(),$J42<=TODAY()+30),AND($J42>=DATE(YEAR(TODAY()),1,1),$J42<=DATE(YEAR(TODAY()),12,31)))))) ) -> TRUE
A43: REL-0039 | B43: Agiloft Core Transformation v4.6 | C43: Legal | D43: Agiloft CLM | E43: NA | F43: Large | G43: High | H43: P1 - Critical | I43: 46365 | J43: 46368 | K43: 46370 | L43: LEG-TEST-03 | M43: LEG-UAT-01 | N43: Draft | P43: Holiday freeze exception requested | V43: USR-003 | W43: Draft | Y43: Not Started | Z43: 0.03 | AA43: USR-079,USR-091,USR-097 | AB43: Weekend | AC43: =AND( IF($B$2="All",TRUE,$C43=$B$2), IF($D$2="All",TRUE,$D43=$D$2), IF($H$2="All",TRUE,$N43=$H$2), IF($J$2="All",TRUE,IF($J$2="Has Conflict",$O43<>"",IF($J$2="No Conflict",$O43="",TRUE))), IF($F$2="All Time",TRUE,IF($F$2="Today",$J43=TODAY(),IF($F$2="This Week",AND($J43>=TODAY(),$J43<=TODAY()+7),IF($F$2="This Month",AND($J43>=TODAY(),$J43<=TODAY()+30),AND($J43>=DATE(YEAR(TODAY()),1,1),$J43<=DATE(YEAR(TODAY()),12,31)))))) ) -> TRUE
A44: REL-0040 | B44: Palo Quick Enhancement v3.7 | C44: Security | D44: Palo Alto Cortex XDR | E44: NA | F44: Small | G44: Low | H44: P4 - Low | I44: 46370 | J44: 46372 | K44: 46372 | L44: SEC-TEST-03 | M44: SEC-UAT-02 | N44: Draft | P44: Critical for Q3 financial close | T44: Year-End Freeze | U44: SOC2 Requirement | V44: USR-004 | W44: Draft | Y44: Not Started | Z44: 0.17 | AA44: USR-080,USR-092,USR-098 | AB44: Off-Peak | AC44: =AND( IF($B$2="All",TRUE,$C44=$B$2), IF($D$2="All",TRUE,$D44=$D$2), IF($H$2="All",TRUE,$N44=$H$2), IF($J$2="All",TRUE,IF($J$2="Has Conflict",$O44<>"",IF($J$2="No Conflict",$O44="",TRUE))), IF($F$2="All Time",TRUE,IF($F$2="Today",$J44=TODAY(),IF($F$2="This Week",AND($J44>=TODAY(),$J44<=TODAY()+7),IF($F$2="This Month",AND($J44>=TODAY(),$J44<=TODAY()+30),AND($J44>=DATE(YEAR(TODAY()),1,1),$J44<=DATE(YEAR(TODAY()),12,31)))))) ) -> TRUE
A45: REL-0041 | B45: Anaplan Bug Fix Release v3.3 | C45: Finance | D45: Anaplan | E45: {=IFERROR(_xlfn.TEXTJOIN(CHAR(10),TRUE,_xlfn._xlws.FILTER(#REF!&": "&#REF!,#REF!=$A45,"")),"")} | F45: Small | G45: Low | H45: P4 - Low | I45: 46374 | J45: 46376 | K45: 46376 | L45: FIN-TEST-01 | M45: FIN-UAT-01 | N45: Draft | O45: ⚠️ CONFLICT | P45: Resource conflict with REL-0043 - Overlapping Test/UAT window | T45: Year-End Freeze | V45: USR-005 | W45: Draft | X45: REL-0038,REL-0036 | Y45: Not Started | Z45: 0.09 | AA45: USR-073,USR-085,USR-097 | AB45: Business Hours | AC45: =AND( IF($B$2="All",TRUE,$C45=$B$2), IF($D$2="All",TRUE,$D45=$D$2), IF($H$2="All",TRUE,$N45=$H$2), IF($J$2="All",TRUE,IF($J$2="Has Conflict",$O45<>"",IF($J$2="No Conflict",$O45="",TRUE))), IF($F$2="All Time",TRUE,IF($F$2="Today",$J45=TODAY(),IF($F$2="This Week",AND($J45>=TODAY(),$J45<=TODAY()+7),IF($F$2="This Month",AND($J45>=TODAY(),$J45<=TODAY()+30),AND($J45>=DATE(YEAR(TODAY()),1,1),$J45<=DATE(YEAR(TODAY()),12,31)))))) ) -> TRUE
A46: REL-0042 | B46: Oracle Security Patch Bundle v5.6 | C46: Logistics | D46: Oracle Transportation Management | E46: NA | F46: Medium | G46: Medium | H46: P2 - High | I46: 46378 | J46: 46380 | K46: 46381 | L46: LOG-TEST-01 | M46: LOG-UAT-01 | N46: Draft | P46: Executive sponsor: CFO | S46: Oracle Patch Window | T46: Year-End Freeze | V46: USR-006 | W46: Draft | Y46: Not Started | Z46: 0.06 | AA46: USR-074,USR-086,USR-098 | AB46: Off-Peak | AC46: =AND( IF($B$2="All",TRUE,$C46=$B$2), IF($D$2="All",TRUE,$D46=$D$2), IF($H$2="All",TRUE,$N46=$H$2), IF($J$2="All",TRUE,IF($J$2="Has Conflict",$O46<>"",IF($J$2="No Conflict",$O46="",TRUE))), IF($F$2="All Time",TRUE,IF($F$2="Today",$J46=TODAY(),IF($F$2="This Week",AND($J46>=TODAY(),$J46<=TODAY()+7),IF($F$2="This Month",AND($J46>=TODAY(),$J46<=TODAY()+30),AND($J46>=DATE(YEAR(TODAY()),1,1),$J46<=DATE(YEAR(TODAY()),12,31)))))) ) -> TRUE
A47: REL-0043 | B47: Microsoft Integration Enhancement v1.9 | C47: CRM | D47: Microsoft Dynamics 365 CRM | E47: NA | F47: Medium | G47: Medium | H47: P2 - High | I47: 46377 | J47: 46379 | K47: 46380 | L47: FIN-TEST-01 | M47: FIN-UAT-01 | N47: Draft | O47: ⚠️ CONFLICT | P47: Resource conflict with REL-0041 - Overlapping Test/UAT window | T47: Year-End Freeze | V47: USR-061 | W47: Draft | Y47: Not Started | Z47: 0.16 | AA47: USR-075,USR-087,USR-097 | AB47: Off-Peak | AC47: =AND( IF($B$2="All",TRUE,$C47=$B$2), IF($D$2="All",TRUE,$D47=$D$2), IF($H$2="All",TRUE,$N47=$H$2), IF($J$2="All",TRUE,IF($J$2="Has Conflict",$O47<>"",IF($J$2="No Conflict",$O47="",TRUE))), IF($F$2="All Time",TRUE,IF($F$2="Today",$J47=TODAY(),IF($F$2="This Week",AND($J47>=TODAY(),$J47<=TODAY()+7),IF($F$2="This Month",AND($J47>=TODAY(),$J47<=TODAY()+30),AND($J47>=DATE(YEAR(TODAY()),1,1),$J47<=DATE(YEAR(TODAY()),12,31)))))) ) -> TRUE
A48: REL-0044 | B48: Siemens Integration Enhancement v2.2 | C48: Manufacturing | D48: Siemens Opcenter | E48: NA | F48: Medium | G48: High | H48: P2 - High | I48: 46389 | J48: 46391 | K48: 46392 | L48: MAN-TEST-01 | M48: MAN-UAT-01 | N48: Draft | P48: License renewal dependency | T48: Year-End Freeze | V48: USR-062 | W48: Draft | Y48: Not Started | Z48: 0.16 | AA48: USR-076,USR-088,USR-098 | AB48: Weekend | AC48: =AND( IF($B$2="All",TRUE,$C48=$B$2), IF($D$2="All",TRUE,$D48=$D$2), IF($H$2="All",TRUE,$N48=$H$2), IF($J$2="All",TRUE,IF($J$2="Has Conflict",$O48<>"",IF($J$2="No Conflict",$O48="",TRUE))), IF($F$2="All Time",TRUE,IF($F$2="Today",$J48=TODAY(),IF($F$2="This Week",AND($J48>=TODAY(),$J48<=TODAY()+7),IF($F$2="This Month",AND($J48>=TODAY(),$J48<=TODAY()+30),AND($J48>=DATE(YEAR(TODAY()),1,1),$J48<=DATE(YEAR(TODAY()),12,31)))))) ) -> TRUE
A49: REL-0045 | B49: Splunk Global Rollout v3.0 | C49: IT | D49: Splunk Enterprise | E49: {=IFERROR(_xlfn.TEXTJOIN(CHAR(10),TRUE,_xlfn._xlws.FILTER(#REF!&": "&#REF!,#REF!=$A49,"")),"")} | F49: Large | G49: High | H49: P1 - Critical | I49: 46392 | J49: 46395 | K49: 46397 | L49: IT-TEST-01 | M49: IT-UAT-01 | N49: Draft | P49: Critical for Q3 financial close | V49: USR-063 | W49: Draft | X49: REL-0042 | Y49: Not Started | Z49: 0.17 | AA49: USR-077,USR-089,USR-097 | AB49: Weekend | AC49: =AND( IF($B$2="All",TRUE,$C49=$B$2), IF($D$2="All",TRUE,$D49=$D$2), IF($H$2="All",TRUE,$N49=$H$2), IF($J$2="All",TRUE,IF($J$2="Has Conflict",$O49<>"",IF($J$2="No Conflict",$O49="",TRUE))), IF($F$2="All Time",TRUE,IF($F$2="Today",$J49=TODAY(),IF($F$2="This Week",AND($J49>=TODAY(),$J49<=TODAY()+7),IF($F$2="This Month",AND($J49>=TODAY(),$J49<=TODAY()+30),AND($J49>=DATE(YEAR(TODAY()),1,1),$J49<=DATE(YEAR(TODAY()),12,31)))))) ) -> TRUE
A50: REL-0046 | B50: SAP UI Tweak v5.2 | C50: HR | D50: SAP SuccessFactors | E50: NA | F50: Small | G50: Low | H50: P4 - Low | I50: 46397 | J50: 46399 | K50: 46399 | L50: HR-TEST-03 | M50: HR-UAT-02 | N50: Draft | P50: Executive sponsor: CFO | V50: USR-064 | W50: Draft | Y50: Not Started | Z50: 0.14 | AA50: USR-078,USR-090,USR-098 | AB50: Off-Peak | AC50: =AND( IF($B$2="All",TRUE,$C50=$B$2), IF($D$2="All",TRUE,$D50=$D$2), IF($H$2="All",TRUE,$N50=$H$2), IF($J$2="All",TRUE,IF($J$2="Has Conflict",$O50<>"",IF($J$2="No Conflict",$O50="",TRUE))), IF($F$2="All Time",TRUE,IF($F$2="Today",$J50=TODAY(),IF($F$2="This Week",AND($J50>=TODAY(),$J50<=TODAY()+7),IF($F$2="This Month",AND($J50>=TODAY(),$J50<=TODAY()+30),AND($J50>=DATE(YEAR(TODAY()),1,1),$J50<=DATE(YEAR(TODAY()),12,31)))))) ) -> TRUE
A51: REL-0047 | B51: DocuSign Integration Enhancement v1.4 | C51: Legal | D51: DocuSign CLM | E51: NA | F51: Medium | G51: Medium | H51: P3 - Medium | I51: 46401 | J51: 46403 | K51: 46404 | L51: LEG-TEST-02 | M51: LEG-UAT-02 | N51: Draft | P51: Customer-facing impact - coordinate with support | V51: USR-065 | W51: Draft | Y51: Not Started | Z51: 0.1 | AA51: USR-079,USR-091,USR-097 | AB51: Weekend | AC51: =AND( IF($B$2="All",TRUE,$C51=$B$2), IF($D$2="All",TRUE,$D51=$D$2), IF($H$2="All",TRUE,$N51=$H$2), IF($J$2="All",TRUE,IF($J$2="Has Conflict",$O51<>"",IF($J$2="No Conflict",$O51="",TRUE))), IF($F$2="All Time",TRUE,IF($F$2="Today",$J51=TODAY(),IF($F$2="This Week",AND($J51>=TODAY(),$J51<=TODAY()+7),IF($F$2="This Month",AND($J51>=TODAY(),$J51<=TODAY()+30),AND($J51>=DATE(YEAR(TODAY()),1,1),$J51<=DATE(YEAR(TODAY()),12,31)))))) ) -> TRUE
A52: REL-0048 | B52: Okta Report Fix v4.1 | C52: Security | D52: Okta Identity Cloud | E52: NA | F52: Small | G52: Low | H52: P4 - Low | I52: 46405 | J52: 46407 | K52: 46407 | L52: SEC-TEST-03 | M52: SEC-UAT-01 | N52: Draft | P52: External vendor coordination needed | V52: USR-066 | W52: Draft | Y52: Not Started | Z52: 0.17 | AA52: USR-080,USR-092,USR-098 | AB52: Business Hours | AC52: =AND( IF($B$2="All",TRUE,$C52=$B$2), IF($D$2="All",TRUE,$D52=$D$2), IF($H$2="All",TRUE,$N52=$H$2), IF($J$2="All",TRUE,IF($J$2="Has Conflict",$O52<>"",IF($J$2="No Conflict",$O52="",TRUE))), IF($F$2="All Time",TRUE,IF($F$2="Today",$J52=TODAY(),IF($F$2="This Week",AND($J52>=TODAY(),$J52<=TODAY()+7),IF($F$2="This Month",AND($J52>=TODAY(),$J52<=TODAY()+30),AND($J52>=DATE(YEAR(TODAY()),1,1),$J52<=DATE(YEAR(TODAY()),12,31)))))) ) -> TRUE
A53: REL-0049 | B53: Anaplan Minor Update v3.3 | C53: Finance | D53: Anaplan | E53: {=IFERROR(_xlfn.TEXTJOIN(CHAR(10),TRUE,_xlfn._xlws.FILTER(#REF!&": "&#REF!,#REF!=$A53,"")),"")} | F53: Small | G53: Low | H53: P4 - Low | I53: 46409 | J53: 46411 | K53: 46411 | L53: FIN-TEST-02 | M53: FIN-UAT-02 | N53: Draft | P53: DR sync required post-deployment | U53: SOX Compliance | V53: USR-067 | W53: Draft | X53: REL-0046,REL-0044 | Y53: Not Started | Z53: 0.18 | AA53: USR-073,USR-085,USR-097 | AB53: Business Hours | AC53: =AND( IF($B$2="All",TRUE,$C53=$B$2), IF($D$2="All",TRUE,$D53=$D$2), IF($H$2="All",TRUE,$N53=$H$2), IF($J$2="All",TRUE,IF($J$2="Has Conflict",$O53<>"",IF($J$2="No Conflict",$O53="",TRUE))), IF($F$2="All Time",TRUE,IF($F$2="Today",$J53=TODAY(),IF($F$2="This Week",AND($J53>=TODAY(),$J53<=TODAY()+7),IF($F$2="This Month",AND($J53>=TODAY(),$J53<=TODAY()+30),AND($J53>=DATE(YEAR(TODAY()),1,1),$J53<=DATE(YEAR(TODAY()),12,31)))))) ) -> TRUE
A54: REL-0050 | B54: Blue Configuration Change v5.9 | C54: Logistics | D54: Blue Yonder WMS | E54: NA | F54: Small | G54: Low | H54: P4 - Low | I54: 46416 | J54: 46418 | K54: 46418 | L54: LOG-TEST-01 | M54: LOG-UAT-02 | N54: Draft | P54: Executive sponsor: CIO | V54: USR-068 | W54: Draft | Y54: Not Started | Z54: 0 | AA54: USR-074,USR-086,USR-098 | AB54: Off-Peak | AC54: =AND( IF($B$2="All",TRUE,$C54=$B$2), IF($D$2="All",TRUE,$D54=$D$2), IF($H$2="All",TRUE,$N54=$H$2), IF($J$2="All",TRUE,IF($J$2="Has Conflict",$O54<>"",IF($J$2="No Conflict",$O54="",TRUE))), IF($F$2="All Time",TRUE,IF($F$2="Today",$J54=TODAY(),IF($F$2="This Week",AND($J54>=TODAY(),$J54<=TODAY()+7),IF($F$2="This Month",AND($J54>=TODAY(),$J54<=TODAY()+30),AND($J54>=DATE(YEAR(TODAY()),1,1),$J54<=DATE(YEAR(TODAY()),12,31)))))) ) -> TRUE
A55: REL-0051 | B55: HubSpot Module Update v4.7 | C55: CRM | D55: HubSpot CRM | E55: NA | F55: Medium | G55: Medium | H55: P2 - High | I55: 46420 | J55: 46422 | K55: 46423 | L55: CRM-TEST-03 | M55: CRM-UAT-02 | N55: Draft | P55: Requires weekend deployment window | V55: USR-001 | W55: Draft | Y55: Not Started | Z55: 0.03 | AA55: USR-075,USR-087,USR-097 | AB55: Off-Peak | AC55: =AND( IF($B$2="All",TRUE,$C55=$B$2), IF($D$2="All",TRUE,$D55=$D$2), IF($H$2="All",TRUE,$N55=$H$2), IF($J$2="All",TRUE,IF($J$2="Has Conflict",$O55<>"",IF($J$2="No Conflict",$O55="",TRUE))), IF($F$2="All Time",TRUE,IF($F$2="Today",$J55=TODAY(),IF($F$2="This Week",AND($J55>=TODAY(),$J55<=TODAY()+7),IF($F$2="This Month",AND($J55>=TODAY(),$J55<=TODAY()+30),AND($J55>=DATE(YEAR(TODAY()),1,1),$J55<=DATE(YEAR(TODAY()),12,31)))))) ) -> TRUE
A56: REL-0052 | B56: SAP Configuration Change v1.3 | C56: Manufacturing | D56: SAP S/4HANA Manufacturing | E56: NA | F56: Small | G56: Low | H56: P4 - Low | I56: 46424 | J56: 46426 | K56: 46426 | L56: MAN-TEST-01 | M56: MAN-UAT-01 | N56: Draft | P56: DR sync required post-deployment | V56: USR-002 | W56: Draft | Y56: Not Started | Z56: 0.12 | AA56: USR-076,USR-088,USR-098 | AB56: Business Hours | AC56: =AND( IF($B$2="All",TRUE,$C56=$B$2), IF($D$2="All",TRUE,$D56=$D$2), IF($H$2="All",TRUE,$N56=$H$2), IF($J$2="All",TRUE,IF($J$2="Has Conflict",$O56<>"",IF($J$2="No Conflict",$O56="",TRUE))), IF($F$2="All Time",TRUE,IF($F$2="Today",$J56=TODAY(),IF($F$2="This Week",AND($J56>=TODAY(),$J56<=TODAY()+7),IF($F$2="This Month",AND($J56>=TODAY(),$J56<=TODAY()+30),AND($J56>=DATE(YEAR(TODAY()),1,1),$J56<=DATE(YEAR(TODAY()),12,31)))))) ) -> TRUE
A57: REL-0053 | B57: Splunk Global Rollout v5.8 | C57: IT | D57: Splunk Enterprise | E57: {=IFERROR(_xlfn.TEXTJOIN(CHAR(10),TRUE,_xlfn._xlws.FILTER(#REF!&": "&#REF!,#REF!=$A57,"")),"")} | F57: Large | G57: High | H57: P1 - Critical | I57: 46427 | J57: 46430 | K57: 46432 | L57: IT-TEST-03 | M57: IT-UAT-02 | N57: Draft | P57: Dependent on vendor patch delivery | V57: USR-003 | W57: Draft | X57: REL-0051 | Y57: Not Started | Z57: 0.06 | AA57: USR-077,USR-089,USR-097 | AB57: Weekend | AC57: =AND( IF($B$2="All",TRUE,$C57=$B$2), IF($D$2="All",TRUE,$D57=$D$2), IF($H$2="All",TRUE,$N57=$H$2), IF($J$2="All",TRUE,IF($J$2="Has Conflict",$O57<>"",IF($J$2="No Conflict",$O57="",TRUE))), IF($F$2="All Time",TRUE,IF($F$2="Today",$J57=TODAY(),IF($F$2="This Week",AND($J57>=TODAY(),$J57<=TODAY()+7),IF($F$2="This Month",AND($J57>=TODAY(),$J57<=TODAY()+30),AND($J57>=DATE(YEAR(TODAY()),1,1),$J57<=DATE(YEAR(TODAY()),12,31)))))) ) -> TRUE
A58: REL-0054 | B58: Workday Core Transformation v2.7 | C58: HR | D58: Workday HCM | E58: NA | F58: Large | G58: High | H58: P2 - High | I58: 46431 | J58: 46434 | K58: 46436 | L58: HR-TEST-01 | M58: HR-UAT-01 | N58: Draft | P58: Training materials to be updated | V58: USR-004 | W58: Draft | Y58: Not Started | Z58: 0.02 | AA58: USR-078,USR-090,USR-098 | AB58: Weekend | AC58: =AND( IF($B$2="All",TRUE,$C58=$B$2), IF($D$2="All",TRUE,$D58=$D$2), IF($H$2="All",TRUE,$N58=$H$2), IF($J$2="All",TRUE,IF($J$2="Has Conflict",$O58<>"",IF($J$2="No Conflict",$O58="",TRUE))), IF($F$2="All Time",TRUE,IF($F$2="Today",$J58=TODAY(),IF($F$2="This Week",AND($J58>=TODAY(),$J58<=TODAY()+7),IF($F$2="This Month",AND($J58>=TODAY(),$J58<=TODAY()+30),AND($J58>=DATE(YEAR(TODAY()),1,1),$J58<=DATE(YEAR(TODAY()),12,31)))))) ) -> TRUE
A59: REL-0055 | B59: DocuSign Major Enhancement v5.2 | C59: Legal | D59: DocuSign CLM | E59: NA | F59: Large | G59: High | H59: P1 - Critical | I59: 46435 | J59: 46438 | K59: 46440 | L59: LEG-TEST-03 | M59: LEG-UAT-01 | N59: Draft | P59: Rollback plan required | U59: GDPR Compliance | V59: USR-005 | W59: Draft | Y59: Not Started | Z59: 0 | AA59: USR-079,USR-091,USR-097 | AB59: Weekend | AC59: =AND( IF($B$2="All",TRUE,$C59=$B$2), IF($D$2="All",TRUE,$D59=$D$2), IF($H$2="All",TRUE,$N59=$H$2), IF($J$2="All",TRUE,IF($J$2="Has Conflict",$O59<>"",IF($J$2="No Conflict",$O59="",TRUE))), IF($F$2="All Time",TRUE,IF($F$2="Today",$J59=TODAY(),IF($F$2="This Week",AND($J59>=TODAY(),$J59<=TODAY()+7),IF($F$2="This Month",AND($J59>=TODAY(),$J59<=TODAY()+30),AND($J59>=DATE(YEAR(TODAY()),1,1),$J59<=DATE(YEAR(TODAY()),12,31)))))) ) -> TRUE
A60: REL-0056 | B60: Okta Performance Optimization v5.0 | C60: Security | D60: Okta Identity Cloud | E60: NA | F60: Medium | G60: Medium | H60: P2 - High | I60: 46440 | J60: 46442 | K60: 46443 | L60: SEC-TEST-01 | M60: SEC-UAT-02 | N60: Draft | O60: ⚠️ CONFLICT | P60: Resource conflict with REL-0058 - Overlapping Test/UAT window | V60: USR-006 | W60: Draft | Y60: Not Started | Z60: 0.17 | AA60: USR-080,USR-092,USR-098 | AB60: Weekend | AC60: =AND( IF($B$2="All",TRUE,$C60=$B$2), IF($D$2="All",TRUE,$D60=$D$2), IF($H$2="All",TRUE,$N60=$H$2), IF($J$2="All",TRUE,IF($J$2="Has Conflict",$O60<>"",IF($J$2="No Conflict",$O60="",TRUE))), IF($F$2="All Time",TRUE,IF($F$2="Today",$J60=TODAY(),IF($F$2="This Week",AND($J60>=TODAY(),$J60<=TODAY()+7),IF($F$2="This Month",AND($J60>=TODAY(),$J60<=TODAY()+30),AND($J60>=DATE(YEAR(TODAY()),1,1),$J60<=DATE(YEAR(TODAY()),12,31)))))) ) -> TRUE
A61: REL-0057 | B61: Coupa Security Patch Bundle v3.3 | C61: Finance | D61: Coupa | E61: {=IFERROR(_xlfn.TEXTJOIN(CHAR(10),TRUE,_xlfn._xlws.FILTER(#REF!&": "&#REF!,#REF!=$A61,"")),"")} | F61: Medium | G61: Medium | H61: P3 - Medium | I61: 46444 | J61: 46446 | K61: 46447 | L61: FIN-TEST-02 | M61: FIN-UAT-01 | N61: Draft | P61: External vendor coordination needed | V61: USR-061 | W61: Draft | X61: REL-0054,REL-0052 | Y61: Not Started | Z61: 0.05 | AA61: USR-073,USR-085,USR-097 | AB61: Off-Peak | AC61: =AND( IF($B$2="All",TRUE,$C61=$B$2), IF($D$2="All",TRUE,$D61=$D$2), IF($H$2="All",TRUE,$N61=$H$2), IF($J$2="All",TRUE,IF($J$2="Has Conflict",$O61<>"",IF($J$2="No Conflict",$O61="",TRUE))), IF($F$2="All Time",TRUE,IF($F$2="Today",$J61=TODAY(),IF($F$2="This Week",AND($J61>=TODAY(),$J61<=TODAY()+7),IF($F$2="This Month",AND($J61>=TODAY(),$J61<=TODAY()+30),AND($J61>=DATE(YEAR(TODAY()),1,1),$J61<=DATE(YEAR(TODAY()),12,31)))))) ) -> TRUE
A62: REL-0058 | B62: Manhattan API Enhancement v2.0 | C62: Logistics | D62: Manhattan Associates WMS | E62: NA | F62: Medium | G62: Low | H62: P4 - Low | I62: 46443 | J62: 46445 | K62: 46446 | L62: SEC-TEST-01 | M62: SEC-UAT-02 | N62: Draft | O62: ⚠️ CONFLICT | P62: Resource conflict with REL-0056 - Overlapping Test/UAT window | V62: USR-062 | W62: Draft | Y62: Not Started | Z62: 0.07 | AA62: USR-074,USR-086,USR-098 | AB62: Weekend | AC62: =AND( IF($B$2="All",TRUE,$C62=$B$2), IF($D$2="All",TRUE,$D62=$D$2), IF($H$2="All",TRUE,$N62=$H$2), IF($J$2="All",TRUE,IF($J$2="Has Conflict",$O62<>"",IF($J$2="No Conflict",$O62="",TRUE))), IF($F$2="All Time",TRUE,IF($F$2="Today",$J62=TODAY(),IF($F$2="This Week",AND($J62>=TODAY(),$J62<=TODAY()+7),IF($F$2="This Month",AND($J62>=TODAY(),$J62<=TODAY()+30),AND($J62>=DATE(YEAR(TODAY()),1,1),$J62<=DATE(YEAR(TODAY()),12,31)))))) ) -> TRUE
A63: REL-0059 | B63: Salesforce Workflow Automation v5.8 | C63: CRM | D63: Salesforce Service Cloud | E63: NA | F63: Medium | G63: Medium | H63: P3 - Medium | I63: 46452 | J63: 46454 | K63: 46455 | L63: CRM-TEST-03 | M63: CRM-UAT-02 | N63: Draft | P63: Holiday freeze exception requested | V63: USR-063 | W63: Draft | Y63: Not Started | Z63: 0 | AA63: USR-075,USR-087,USR-097 | AB63: Weekend | AC63: =AND( IF($B$2="All",TRUE,$C63=$B$2), IF($D$2="All",TRUE,$D63=$D$2), IF($H$2="All",TRUE,$N63=$H$2), IF($J$2="All",TRUE,IF($J$2="Has Conflict",$O63<>"",IF($J$2="No Conflict",$O63="",TRUE))), IF($F$2="All Time",TRUE,IF($F$2="Today",$J63=TODAY(),IF($F$2="This Week",AND($J63>=TODAY(),$J63<=TODAY()+7),IF($F$2="This Month",AND($J63>=TODAY(),$J63<=TODAY()+30),AND($J63>=DATE(YEAR(TODAY()),1,1),$J63<=DATE(YEAR(TODAY()),12,31)))))) ) -> TRUE
A64: REL-0060 | B64: Plex UI Tweak v4.0 | C64: Manufacturing | D64: Plex Smart Manufacturing | E64: NA | F64: Small | G64: Low | H64: P4 - Low | I64: 46456 | J64: 46458 | K64: 46458 | L64: MAN-TEST-02 | M64: MAN-UAT-02 | N64: Draft | P64: Performance testing mandatory | V64: USR-064 | W64: Draft | Y64: Not Started | Z64: 0.18 | AA64: USR-076,USR-088,USR-098 | AB64: Business Hours | AC64: =AND( IF($B$2="All",TRUE,$C64=$B$2), IF($D$2="All",TRUE,$D64=$D$2), IF($H$2="All",TRUE,$N64=$H$2), IF($J$2="All",TRUE,IF($J$2="Has Conflict",$O64<>"",IF($J$2="No Conflict",$O64="",TRUE))), IF($F$2="All Time",TRUE,IF($F$2="Today",$J64=TODAY(),IF($F$2="This Week",AND($J64>=TODAY(),$J64<=TODAY()+7),IF($F$2="This Month",AND($J64>=TODAY(),$J64<=TODAY()+30),AND($J64>=DATE(YEAR(TODAY()),1,1),$J64<=DATE(YEAR(TODAY()),12,31)))))) ) -> TRUE
A65: REL-0061 | B65: Datadog API Enhancement v5.6 | C65: IT | D65: Datadog | E65: {=IFERROR(_xlfn.TEXTJOIN(CHAR(10),TRUE,_xlfn._xlws.FILTER(#REF!&": "&#REF!,#REF!=$A65,"")),"")} | F65: Medium | G65: Low | H65: P4 - Low | I65: 46460 | J65: 46462 | K65: 46463 | L65: IT-TEST-02 | M65: IT-UAT-01 | N65: Draft | P65: Holiday freeze exception requested | V65: USR-065 | W65: Draft | X65: REL-0059 | Y65: Not Started | Z65: 0.12 | AA65: USR-077,USR-089,USR-097 | AB65: Off-Peak | AC65: =AND( IF($B$2="All",TRUE,$C65=$B$2), IF($D$2="All",TRUE,$D65=$D$2), IF($H$2="All",TRUE,$N65=$H$2), IF($J$2="All",TRUE,IF($J$2="Has Conflict",$O65<>"",IF($J$2="No Conflict",$O65="",TRUE))), IF($F$2="All Time",TRUE,IF($F$2="Today",$J65=TODAY(),IF($F$2="This Week",AND($J65>=TODAY(),$J65<=TODAY()+7),IF($F$2="This Month",AND($J65>=TODAY(),$J65<=TODAY()+30),AND($J65>=DATE(YEAR(TODAY()),1,1),$J65<=DATE(YEAR(TODAY()),12,31)))))) ) -> TRUE
A66: REL-0062 | B66: SAP Report Fix v2.8 | C66: HR | D66: SAP SuccessFactors | E66: NA | F66: Small | G66: Medium | H66: P3 - Medium | I66: 46464 | J66: 46466 | K66: 46466 | L66: HR-TEST-03 | M66: HR-UAT-02 | N66: Draft | P66: Dependent on vendor patch delivery | V66: USR-066 | W66: Draft | Y66: Not Started | Z66: 0.11 | AA66: USR-078,USR-090,USR-098 | AB66: Off-Peak | AC66: =AND( IF($B$2="All",TRUE,$C66=$B$2), IF($D$2="All",TRUE,$D66=$D$2), IF($H$2="All",TRUE,$N66=$H$2), IF($J$2="All",TRUE,IF($J$2="Has Conflict",$O66<>"",IF($J$2="No Conflict",$O66="",TRUE))), IF($F$2="All Time",TRUE,IF($F$2="Today",$J66=TODAY(),IF($F$2="This Week",AND($J66>=TODAY(),$J66<=TODAY()+7),IF($F$2="This Month",AND($J66>=TODAY(),$J66<=TODAY()+30),AND($J66>=DATE(YEAR(TODAY()),1,1),$J66<=DATE(YEAR(TODAY()),12,31)))))) ) -> TRUE
A67: REL-0063 | B67: Mitratech Workflow Automation v2.3 | C67: Legal | D67: Mitratech TeamConnect | E67: NA | F67: Medium | G67: Low | H67: P4 - Low | I67: 46468 | J67: 46470 | K67: 46471 | L67: LEG-TEST-01 | M67: LEG-UAT-02 | N67: Draft | P67: Business continuity testing required | V67: USR-067 | W67: Draft | Y67: Not Started | Z67: 0.15 | AA67: USR-079,USR-091,USR-097 | AB67: Off-Peak | AC67: =AND( IF($B$2="All",TRUE,$C67=$B$2), IF($D$2="All",TRUE,$D67=$D$2), IF($H$2="All",TRUE,$N67=$H$2), IF($J$2="All",TRUE,IF($J$2="Has Conflict",$O67<>"",IF($J$2="No Conflict",$O67="",TRUE))), IF($F$2="All Time",TRUE,IF($F$2="Today",$J67=TODAY(),IF($F$2="This Week",AND($J67>=TODAY(),$J67<=TODAY()+7),IF($F$2="This Month",AND($J67>=TODAY(),$J67<=TODAY()+30),AND($J67>=DATE(YEAR(TODAY()),1,1),$J67<=DATE(YEAR(TODAY()),12,31)))))) ) -> TRUE
A68: REL-0064 | B68: Microsoft Integration Enhancement v4.1 | C68: Security | D68: Microsoft Sentinel | E68: NA | F68: Medium | G68: Low | H68: P4 - Low | I68: 46475 | J68: 46477 | K68: 46478 | L68: SEC-TEST-03 | M68: SEC-UAT-02 | N68: Draft | P68: Customer-facing impact - coordinate with support | T68: Quarter-End Freeze | U68: SOC2 Requirement | V68: USR-068 | W68: Draft | Y68: Not Started | Z68: 0.05 | AA68: USR-080,USR-092,USR-098 | AB68: Off-Peak | AC68: =AND( IF($B$2="All",TRUE,$C68=$B$2), IF($D$2="All",TRUE,$D68=$D$2), IF($H$2="All",TRUE,$N68=$H$2), IF($J$2="All",TRUE,IF($J$2="Has Conflict",$O68<>"",IF($J$2="No Conflict",$O68="",TRUE))), IF($F$2="All Time",TRUE,IF($F$2="Today",$J68=TODAY(),IF($F$2="This Week",AND($J68>=TODAY(),$J68<=TODAY()+7),IF($F$2="This Month",AND($J68>=TODAY(),$J68<=TODAY()+30),AND($J68>=DATE(YEAR(TODAY()),1,1),$J68<=DATE(YEAR(TODAY()),12,31)))))) ) -> TRUE
A69: REL-0065 | B69: Oracle System Migration v1.9 | C69: Finance | D69: Oracle Hyperion HFM | E69: {=IFERROR(_xlfn.TEXTJOIN(CHAR(10),TRUE,_xlfn._xlws.FILTER(#REF!&": "&#REF!,#REF!=$A69,"")),"")} | F69: Large | G69: High | H69: P2 - High | I69: 46478 | J69: 46481 | K69: 46483 | L69: FIN-TEST-03 | M69: FIN-UAT-02 | N69: Draft | P69: Dependencies on infrastructure team | V69: USR-001 | W69: Draft | X69: REL-0062,REL-0060 | Y69: Not Started | Z69: 0.09 | AA69: USR-073,USR-085,USR-097 | AB69: Weekend | AC69: =AND( IF($B$2="All",TRUE,$C69=$B$2), IF($D$2="All",TRUE,$D69=$D$2), IF($H$2="All",TRUE,$N69=$H$2), IF($J$2="All",TRUE,IF($J$2="Has Conflict",$O69<>"",IF($J$2="No Conflict",$O69="",TRUE))), IF($F$2="All Time",TRUE,IF($F$2="Today",$J69=TODAY(),IF($F$2="This Week",AND($J69>=TODAY(),$J69<=TODAY()+7),IF($F$2="This Month",AND($J69>=TODAY(),$J69<=TODAY()+30),AND($J69>=DATE(YEAR(TODAY()),1,1),$J69<=DATE(YEAR(TODAY()),12,31)))))) ) -> TRUE
A70: REL-0066 | B70: Oracle Module Update v5.6 | C70: Logistics | D70: Oracle Transportation Management | E70: NA | F70: Medium | G70: Medium | H70: P3 - Medium | I70: 46483 | J70: 46485 | K70: 46486 | L70: LOG-TEST-02 | M70: LOG-UAT-01 | N70: Draft | O70: ⚠️ CONFLICT | P70: Resource conflict with REL-0068 - Overlapping Test/UAT window | V70: USR-002 | W70: Draft | Y70: Not Started | Z70: 0.1 | AA70: USR-074,USR-086,USR-098 | AB70: Off-Peak | AC70: =AND( IF($B$2="All",TRUE,$C70=$B$2), IF($D$2="All",TRUE,$D70=$D$2), IF($H$2="All",TRUE,$N70=$H$2), IF($J$2="All",TRUE,IF($J$2="Has Conflict",$O70<>"",IF($J$2="No Conflict",$O70="",TRUE))), IF($F$2="All Time",TRUE,IF($F$2="Today",$J70=TODAY(),IF($F$2="This Week",AND($J70>=TODAY(),$J70<=TODAY()+7),IF($F$2="This Month",AND($J70>=TODAY(),$J70<=TODAY()+30),AND($J70>=DATE(YEAR(TODAY()),1,1),$J70<=DATE(YEAR(TODAY()),12,31)))))) ) -> TRUE
A71: REL-0067 | B71: Salesforce Complete Redesign v1.9 | C71: CRM | D71: Salesforce Sales Cloud | E71: NA | F71: Large | G71: High | H71: P1 - Critical | I71: 46486 | J71: 46489 | K71: 46491 | L71: CRM-TEST-03 | M71: CRM-UAT-02 | N71: Draft | P71: Blackout period consideration | V71: USR-003 | W71: Draft | Y71: Not Started | Z71: 0.19 | AA71: USR-075,USR-087,USR-097 | AB71: Weekend | AC71: =AND( IF($B$2="All",TRUE,$C71=$B$2), IF($D$2="All",TRUE,$D71=$D$2), IF($H$2="All",TRUE,$N71=$H$2), IF($J$2="All",TRUE,IF($J$2="Has Conflict",$O71<>"",IF($J$2="No Conflict",$O71="",TRUE))), IF($F$2="All Time",TRUE,IF($F$2="Today",$J71=TODAY(),IF($F$2="This Week",AND($J71>=TODAY(),$J71<=TODAY()+7),IF($F$2="This Month",AND($J71>=TODAY(),$J71<=TODAY()+30),AND($J71>=DATE(YEAR(TODAY()),1,1),$J71<=DATE(YEAR(TODAY()),12,31)))))) ) -> TRUE
A72: REL-0068 | B72: Rockwell Minor Update v1.1 | C72: Manufacturing | D72: Rockwell FactoryTalk | E72: NA | F72: Small | G72: Low | H72: P4 - Low | I72: 46486 | J72: 46488 | K72: 46488 | L72: LOG-TEST-02 | M72: LOG-UAT-01 | N72: Draft | O72: ⚠️ CONFLICT | P72: Resource conflict with REL-0066 - Overlapping Test/UAT window | V72: USR-004 | W72: Draft | Y72: Not Started | Z72: 0.18 | AA72: USR-076,USR-088,USR-098 | AB72: Business Hours | AC72: =AND( IF($B$2="All",TRUE,$C72=$B$2), IF($D$2="All",TRUE,$D72=$D$2), IF($H$2="All",TRUE,$N72=$H$2), IF($J$2="All",TRUE,IF($J$2="Has Conflict",$O72<>"",IF($J$2="No Conflict",$O72="",TRUE))), IF($F$2="All Time",TRUE,IF($F$2="Today",$J72=TODAY(),IF($F$2="This Week",AND($J72>=TODAY(),$J72<=TODAY()+7),IF($F$2="This Month",AND($J72>=TODAY(),$J72<=TODAY()+30),AND($J72>=DATE(YEAR(TODAY()),1,1),$J72<=DATE(YEAR(TODAY()),12,31)))))) ) -> TRUE
A73: REL-0069 | B73: BMC UI Tweak v5.1 | C73: IT | D73: BMC Remedy | E73: {=IFERROR(_xlfn.TEXTJOIN(CHAR(10),TRUE,_xlfn._xlws.FILTER(#REF!&": "&#REF!,#REF!=$A73,"")),"")} | F73: Small | G73: Medium | H73: P3 - Medium | I73: 46495 | J73: 46497 | K73: 46497 | L73: IT-TEST-01 | M73: IT-UAT-01 | N73: Draft | P73: Rollback plan required | V73: USR-005 | W73: Draft | X73: REL-0067 | Y73: Not Started | Z73: 0.02 | AA73: USR-077,USR-089,USR-097 | AB73: Off-Peak | AC73: =AND( IF($B$2="All",TRUE,$C73=$B$2), IF($D$2="All",TRUE,$D73=$D$2), IF($H$2="All",TRUE,$N73=$H$2), IF($J$2="All",TRUE,IF($J$2="Has Conflict",$O73<>"",IF($J$2="No Conflict",$O73="",TRUE))), IF($F$2="All Time",TRUE,IF($F$2="Today",$J73=TODAY(),IF($F$2="This Week",AND($J73>=TODAY(),$J73<=TODAY()+7),IF($F$2="This Month",AND($J73>=TODAY(),$J73<=TODAY()+30),AND($J73>=DATE(YEAR(TODAY()),1,1),$J73<=DATE(YEAR(TODAY()),12,31)))))) ) -> TRUE
A74: REL-0070 | B74: Oracle Workflow Automation v3.6 | C74: HR | D74: Oracle HCM Cloud | E74: NA | F74: Medium | G74: Medium | H74: P3 - Medium | I74: 46499 | J74: 46501 | K74: 46502 | L74: HR-TEST-02 | M74: HR-UAT-02 | N74: Draft | P74: Requires weekend deployment window | S74: Oracle Patch Window | V74: USR-006 | W74: Draft | Y74: Not Started | Z74: 0 | AA74: USR-078,USR-090,USR-098 | AB74: Weekend | AC74: =AND( IF($B$2="All",TRUE,$C74=$B$2), IF($D$2="All",TRUE,$D74=$D$2), IF($H$2="All",TRUE,$N74=$H$2), IF($J$2="All",TRUE,IF($J$2="Has Conflict",$O74<>"",IF($J$2="No Conflict",$O74="",TRUE))), IF($F$2="All Time",TRUE,IF($F$2="Today",$J74=TODAY(),IF($F$2="This Week",AND($J74>=TODAY(),$J74<=TODAY()+7),IF($F$2="This Month",AND($J74>=TODAY(),$J74<=TODAY()+30),AND($J74>=DATE(YEAR(TODAY()),1,1),$J74<=DATE(YEAR(TODAY()),12,31)))))) ) -> TRUE
A75: REL-0071 | B75: Agiloft Minor Update v4.1 | C75: Legal | D75: Agiloft CLM | E75: NA | F75: Small | G75: Low | H75: P3 - Medium | I75: 46505 | J75: 46507 | K75: 46507 | L75: LEG-TEST-03 | M75: LEG-UAT-01 | N75: Draft | O75: ⚠️ CONFLICT | P75: Resource conflict with REL-0073 - Overlapping Test/UAT window | V75: USR-061 | W75: Draft | Y75: Not Started | Z75: 0.11 | AA75: USR-079,USR-091,USR-097 | AB75: Business Hours | AC75: =AND( IF($B$2="All",TRUE,$C75=$B$2), IF($D$2="All",TRUE,$D75=$D$2), IF($H$2="All",TRUE,$N75=$H$2), IF($J$2="All",TRUE,IF($J$2="Has Conflict",$O75<>"",IF($J$2="No Conflict",$O75="",TRUE))), IF($F$2="All Time",TRUE,IF($F$2="Today",$J75=TODAY(),IF($F$2="This Week",AND($J75>=TODAY(),$J75<=TODAY()+7),IF($F$2="This Month",AND($J75>=TODAY(),$J75<=TODAY()+30),AND($J75>=DATE(YEAR(TODAY()),1,1),$J75<=DATE(YEAR(TODAY()),12,31)))))) ) -> TRUE
A76: REL-0072 | B76: Palo Hotfix v5.8 | C76: Security | D76: Palo Alto Cortex XDR | E76: NA | F76: Small | G76: Low | H76: P3 - Medium | I76: 46509 | J76: 46511 | K76: 46511 | L76: SEC-TEST-01 | M76: SEC-UAT-01 | N76: Draft | P76: Dependent on vendor patch delivery | V76: USR-062 | W76: Draft | Y76: Not Started | Z76: 0.18 | AA76: USR-080,USR-092,USR-098 | AB76: Business Hours | AC76: =AND( IF($B$2="All",TRUE,$C76=$B$2), IF($D$2="All",TRUE,$D76=$D$2), IF($H$2="All",TRUE,$N76=$H$2), IF($J$2="All",TRUE,IF($J$2="Has Conflict",$O76<>"",IF($J$2="No Conflict",$O76="",TRUE))), IF($F$2="All Time",TRUE,IF($F$2="Today",$J76=TODAY(),IF($F$2="This Week",AND($J76>=TODAY(),$J76<=TODAY()+7),IF($F$2="This Month",AND($J76>=TODAY(),$J76<=TODAY()+30),AND($J76>=DATE(YEAR(TODAY()),1,1),$J76<=DATE(YEAR(TODAY()),12,31)))))) ) -> TRUE
A77: REL-0073 | B77: Kyriba Security Patch Bundle v3.6 | C77: Finance | D77: Kyriba | E77: {=IFERROR(_xlfn.TEXTJOIN(CHAR(10),TRUE,_xlfn._xlws.FILTER(#REF!&": "&#REF!,#REF!=$A77,"")),"")} | F77: Medium | G77: Medium | H77: P2 - High | I77: 46508 | J77: 46510 | K77: 46511 | L77: LEG-TEST-03 | M77: LEG-UAT-01 | N77: Draft | O77: ⚠️ CONFLICT | P77: Resource conflict with REL-0071 - Overlapping Test/UAT window | V77: USR-063 | W77: Draft | X77: REL-0070,REL-0068 | Y77: Not Started | Z77: 0.14 | AA77: USR-073,USR-085,USR-097 | AB77: Off-Peak | AC77: =AND( IF($B$2="All",TRUE,$C77=$B$2), IF($D$2="All",TRUE,$D77=$D$2), IF($H$2="All",TRUE,$N77=$H$2), IF($J$2="All",TRUE,IF($J$2="Has Conflict",$O77<>"",IF($J$2="No Conflict",$O77="",TRUE))), IF($F$2="All Time",TRUE,IF($F$2="Today",$J77=TODAY(),IF($F$2="This Week",AND($J77>=TODAY(),$J77<=TODAY()+7),IF($F$2="This Month",AND($J77>=TODAY(),$J77<=TODAY()+30),AND($J77>=DATE(YEAR(TODAY()),1,1),$J77<=DATE(YEAR(TODAY()),12,31)))))) ) -> TRUE
A78: REL-0074 | B78: Oracle Hotfix v4.3 | C78: Logistics | D78: Oracle Transportation Management | E78: NA | F78: Small | G78: Low | H78: P3 - Medium | I78: 46517 | J78: 46519 | K78: 46519 | L78: LOG-TEST-03 | M78: LOG-UAT-02 | N78: Draft | P78: Dependent on vendor patch delivery | V78: USR-064 | W78: Draft | Y78: Not Started | Z78: 0.16 | AA78: USR-074,USR-086,USR-098 | AB78: Business Hours | AC78: =AND( IF($B$2="All",TRUE,$C78=$B$2), IF($D$2="All",TRUE,$D78=$D$2), IF($H$2="All",TRUE,$N78=$H$2), IF($J$2="All",TRUE,IF($J$2="Has Conflict",$O78<>"",IF($J$2="No Conflict",$O78="",TRUE))), IF($F$2="All Time",TRUE,IF($F$2="Today",$J78=TODAY(),IF($F$2="This Week",AND($J78>=TODAY(),$J78<=TODAY()+7),IF($F$2="This Month",AND($J78>=TODAY(),$J78<=TODAY()+30),AND($J78>=DATE(YEAR(TODAY()),1,1),$J78<=DATE(YEAR(TODAY()),12,31)))))) ) -> TRUE
A79: REL-0075 | B79: HubSpot Performance Optimization v3.0 | C79: CRM | D79: HubSpot CRM | E79: NA | F79: Medium | G79: Medium | H79: P3 - Medium | I79: 46521 | J79: 46523 | K79: 46524 | L79: CRM-TEST-02 | M79: CRM-UAT-02 | N79: Draft | P79: Dependencies on infrastructure team | V79: USR-065 | W79: Draft | Y79: Not Started | Z79: 0.04 | AA79: USR-075,USR-087,USR-097 | AB79: Weekend | AC79: =AND( IF($B$2="All",TRUE,$C79=$B$2), IF($D$2="All",TRUE,$D79=$D$2), IF($H$2="All",TRUE,$N79=$H$2), IF($J$2="All",TRUE,IF($J$2="Has Conflict",$O79<>"",IF($J$2="No Conflict",$O79="",TRUE))), IF($F$2="All Time",TRUE,IF($F$2="Today",$J79=TODAY(),IF($F$2="This Week",AND($J79>=TODAY(),$J79<=TODAY()+7),IF($F$2="This Month",AND($J79>=TODAY(),$J79<=TODAY()+30),AND($J79>=DATE(YEAR(TODAY()),1,1),$J79<=DATE(YEAR(TODAY()),12,31)))))) ) -> TRUE
A80: REL-0076 | B80: SAP Hotfix v4.1 | C80: Manufacturing | D80: SAP S/4HANA Manufacturing | E80: NA | F80: Small | G80: Low | H80: P4 - Low | I80: 46525 | J80: 46527 | K80: 46527 | L80: MAN-TEST-01 | M80: MAN-UAT-01 | N80: Draft | P80: Security review pending | V80: USR-066 | W80: Draft | Y80: Not Started | Z80: 0.02 | AA80: USR-076,USR-088,USR-098 | AB80: Business Hours | AC80: =AND( IF($B$2="All",TRUE,$C80=$B$2), IF($D$2="All",TRUE,$D80=$D$2), IF($H$2="All",TRUE,$N80=$H$2), IF($J$2="All",TRUE,IF($J$2="Has Conflict",$O80<>"",IF($J$2="No Conflict",$O80="",TRUE))), IF($F$2="All Time",TRUE,IF($F$2="Today",$J80=TODAY(),IF($F$2="This Week",AND($J80>=TODAY(),$J80<=TODAY()+7),IF($F$2="This Month",AND($J80>=TODAY(),$J80<=TODAY()+30),AND($J80>=DATE(YEAR(TODAY()),1,1),$J80<=DATE(YEAR(TODAY()),12,31)))))) ) -> TRUE
A81: REL-0077 | B81: Jira Core Transformation v1.8 | C81: IT | D81: Jira Service Management | E81: {=IFERROR(_xlfn.TEXTJOIN(CHAR(10),TRUE,_xlfn._xlws.FILTER(#REF!&": "&#REF!,#REF!=$A81,"")),"")} | F81: Large | G81: High | H81: P2 - High | I81: 46528 | J81: 46531 | K81: 46533 | L81: IT-TEST-02 | M81: IT-UAT-01 | N81: Draft | P81: Rollback plan required | V81: USR-067 | W81: Draft | X81: REL-0076 | Y81: Not Started | Z81: 0.02 | AA81: USR-077,USR-089,USR-097 | AB81: Weekend | AC81: =AND( IF($B$2="All",TRUE,$C81=$B$2), IF($D$2="All",TRUE,$D81=$D$2), IF($H$2="All",TRUE,$N81=$H$2), IF($J$2="All",TRUE,IF($J$2="Has Conflict",$O81<>"",IF($J$2="No Conflict",$O81="",TRUE))), IF($F$2="All Time",TRUE,IF($F$2="Today",$J81=TODAY(),IF($F$2="This Week",AND($J81>=TODAY(),$J81<=TODAY()+7),IF($F$2="This Month",AND($J81>=TODAY(),$J81<=TODAY()+30),AND($J81>=DATE(YEAR(TODAY()),1,1),$J81<=DATE(YEAR(TODAY()),12,31)))))) ) -> TRUE
A82: REL-0078 | B82: ADP Workflow Automation v2.7 | C82: HR | D82: ADP Workforce Now | E82: NA | F82: Medium | G82: High | H82: P1 - Critical | I82: 46536 | J82: 46538 | K82: 46539 | L82: HR-TEST-03 | M82: HR-UAT-02 | N82: Draft | P82: Regulatory deadline driven | V82: USR-068 | W82: Draft | Y82: Not Started | Z82: 0.06 | AA82: USR-078,USR-090,USR-098 | AB82: Weekend | AC82: =AND( IF($B$2="All",TRUE,$C82=$B$2), IF($D$2="All",TRUE,$D82=$D$2), IF($H$2="All",TRUE,$N82=$H$2), IF($J$2="All",TRUE,IF($J$2="Has Conflict",$O82<>"",IF($J$2="No Conflict",$O82="",TRUE))), IF($F$2="All Time",TRUE,IF($F$2="Today",$J82=TODAY(),IF($F$2="This Week",AND($J82>=TODAY(),$J82<=TODAY()+7),IF($F$2="This Month",AND($J82>=TODAY(),$J82<=TODAY()+30),AND($J82>=DATE(YEAR(TODAY()),1,1),$J82<=DATE(YEAR(TODAY()),12,31)))))) ) -> TRUE
A83: REL-0079 | B83: Ironclad Module Update v4.7 | C83: Legal | D83: Ironclad | E83: NA | F83: Medium | G83: High | H83: P2 - High | I83: 46540 | J83: 46542 | K83: 46543 | L83: LEG-TEST-01 | M83: LEG-UAT-01 | N83: Draft | P83: Dependencies on infrastructure team | U83: GDPR Compliance | V83: USR-001 | W83: Draft | Y83: Not Started | Z83: 0.08 | AA83: USR-079,USR-091,USR-097 | AB83: Off-Peak | AC83: =AND( IF($B$2="All",TRUE,$C83=$B$2), IF($D$2="All",TRUE,$D83=$D$2), IF($H$2="All",TRUE,$N83=$H$2), IF($J$2="All",TRUE,IF($J$2="Has Conflict",$O83<>"",IF($J$2="No Conflict",$O83="",TRUE))), IF($F$2="All Time",TRUE,IF($F$2="Today",$J83=TODAY(),IF($F$2="This Week",AND($J83>=TODAY(),$J83<=TODAY()+7),IF($F$2="This Month",AND($J83>=TODAY(),$J83<=TODAY()+30),AND($J83>=DATE(YEAR(TODAY()),1,1),$J83<=DATE(YEAR(TODAY()),12,31)))))) ) -> TRUE
A84: REL-0080 | B84: CrowdStrike Performance Optimization v5.9 | C84: Security | D84: CrowdStrike Falcon | E84: NA | F84: Medium | G84: High | H84: P1 - Critical | I84: 46544 | J84: 46546 | K84: 46547 | L84: SEC-TEST-03 | M84: SEC-UAT-01 | N84: Draft | P84: Audit finding remediation | V84: USR-002 | W84: Draft | Y84: Not Started | Z84: 0.08 | AA84: USR-080,USR-092,USR-098 | AB84: Weekend | AC84: =AND( IF($B$2="All",TRUE,$C84=$B$2), IF($D$2="All",TRUE,$D84=$D$2), IF($H$2="All",TRUE,$N84=$H$2), IF($J$2="All",TRUE,IF($J$2="Has Conflict",$O84<>"",IF($J$2="No Conflict",$O84="",TRUE))), IF($F$2="All Time",TRUE,IF($F$2="Today",$J84=TODAY(),IF($F$2="This Week",AND($J84>=TODAY(),$J84<=TODAY()+7),IF($F$2="This Month",AND($J84>=TODAY(),$J84<=TODAY()+30),AND($J84>=DATE(YEAR(TODAY()),1,1),$J84<=DATE(YEAR(TODAY()),12,31)))))) ) -> TRUE

Sheet Calendar
A1: 🔍 FILTERS | C1: Time Period: | D1: All Time | E1: Department: | F1: All | G1: Event Type: | H1: All
A2: Showing: | B2: {=SUMPRODUCT((H15:H180<>"")*IF(F1="All",1,H15:H180=F1)*IF(H1="All",1,E15:E180=H1)*IF(D1="All Time",1,IF(D1="Today",C15:C180=TODAY(),IF(D1="This Week",(C15:C180>=TODAY())*(C15:C180<=TODAY()+7),IF(D1="This Month",(C15:C180>=TODAY())*(C15:C180<=TODAY()+30),(C15:C180>=DATE(YEAR(TODAY()),1,1))*(C15:C180<=DATE(YEAR(TODAY()),12,31)))))))&" of "&COUNTA(E15:E180)&" events"} -> 166 of 166 events
A4: RELEASE CALENDAR - FY2026-2027
A6: Legend:
A7: ■ Change Freeze | B7: Deployment restrictions in effect
A8: ■ Large Release | B8: High impact, extended testing
A9: ■ Medium Release | B9: Standard release cycle
A10: ■ Small Release | B10: Quick deployment
A11: ■ Regulatory | B11: Compliance-driven release
A12: ■ Vendor Maint. | B12: Vendor maintenance window
A14: Month | B14: Week | C14: Date | D14: Day | E14: Event Type | F14: Release ID | G14: Release Name | H14: Department | I14: Size/Impact | J14: Notes
A15: =TEXT(C15,"mmm yyyy") -> Jun 2026 | B15: 4 | C15: 46201 | D15: Sun | E15: CAB MEETING | F15: REL-0001 | G15: CAB: Kyriba UI Tweak v4.5... | H15: Finance | I15: Small | J15: Approval meeting for REL-0001
A16: =TEXT(C16,"mmm yyyy") -> Jun 2026 | B16: 5 | C16: 46203 | D16: Tue | E16: RELEASE | F16: REL-0001 | G16: Kyriba UI Tweak v4.5 | H16: Finance | I16: Small / Low | J16: Impact: Low - Quarter-End Freeze AFFECTED
A17: =TEXT(C17,"mmm yyyy") -> Jun 2026 | B17: 5 | C17: 46203 | D17: Tue | E17: CAB MEETING | F17: REL-0003 | G17: CAB: Zendesk Minor Update v4.3... | H17: CRM | I17: Small | J17: Approval meeting for REL-0003
A18: =TEXT(C18,"mmm yyyy") -> Jul 2026 | B18: 1 | C18: 46205 | D18: Thu | E18: CAB MEETING | F18: REL-0002 | G18: CAB: Blue Workflow Automation v2.1... | H18: Logistics | I18: Medium | J18: Approval meeting for REL-0002
A19: =TEXT(C19,"mmm yyyy") -> Jul 2026 | B19: 1 | C19: 46205 | D19: Thu | E19: RELEASE | F19: REL-0003 | G19: Zendesk Minor Update v4.3 | H19: CRM | I19: Small / Low | J19: Impact: Low
A20: =TEXT(C20,"mmm yyyy") -> Jul 2026 | B20: 1 | C20: 46205 | D20: Thu | E20: CAB MEETING | F20: REL-0007 | G20: CAB: Mitratech Integration Enhancem... | H20: Legal | I20: Medium | J20: Approval meeting for REL-0007
A21: =TEXT(C21,"mmm yyyy") -> Jul 2026 | B21: 1 | C21: 46207 | D21: Sat | E21: RELEASE | F21: REL-0002 | G21: Blue Workflow Automation v2.1 | H21: Logistics | I21: Medium / High | J21: Impact: High
A22: =TEXT(C22,"mmm yyyy") -> Jul 2026 | B22: 1 | C22: 46207 | D22: Sat | E22: RELEASE | F22: REL-0007 | G22: Mitratech Integration Enhancement v5.2 | H22: Legal | I22: Medium / High | J22: Impact: High
A23: =TEXT(C23,"mmm yyyy") -> Jul 2026 | B23: 1 | C23: 46207 | D23: Sat | E23: CAB MEETING | F23: REL-0012 | G23: CAB: Plex Report Fix v2.5... | H23: Manufacturing | I23: Small | J23: Approval meeting for REL-0012
A24: =TEXT(C24,"mmm yyyy") -> Jul 2026 | B24: 1 | C24: 46209 | D24: Mon | E24: RELEASE | F24: REL-0012 | G24: Plex Report Fix v2.5 | H24: Manufacturing | I24: Small / Medium | J24: Impact: Medium
A25: =TEXT(C25,"mmm yyyy") -> Jul 2026 | B25: 2 | C25: 46213 | D25: Fri | E25: CAB MEETING | F25: REL-0004 | G25: CAB: AVEVA Dashboard Upgrade v5.5... | H25: Manufacturing | I25: Medium | J25: Approval meeting for REL-0004
A26: =TEXT(C26,"mmm yyyy") -> Jul 2026 | B26: 2 | C26: 46215 | D26: Sun | E26: RELEASE | F26: REL-0004 | G26: AVEVA Dashboard Upgrade v5.5 | H26: Manufacturing | I26: Medium / High | J26: Impact: High
... A180: =TEXT(C180,"mmm yyyy") -> Jun 2027 | B180: 4 | C180: 46565 | D180: Sun | E180: CHANGE FREEZE | F180: - | G180: Q2 Quarter-End Freeze END | H180: ALL | I180: Critical | J180: No deployments allowed

Sheet Env booking
A1: 🔍 FILTERS | C1: Time Period: | D1: All Time | E1: Department: | F1: All | G1: Application: | H1: All | I1: Conflict: | J1: All | L1: 💡 Select filters above to highlight matching bookings
A2: Showing: | B2: {=SUMPRODUCT((A5:A115<>"")*IF(F1="All",1,D5:D115=F1)*IF(H1="All",1,C5:C115=H1)*IF(J1="All",1,IF(J1="Conflict Only",U5:U115<>"",U5:U115=""))*IF(D1="All Time",1,IF(D1="Today",G5:G115=TODAY(),IF(D1="This Week",(G5:G115>=TODAY())*(G5:G115<=TODAY()+7),IF(D1="This Month",(G5:G115>=TODAY())*(G5:G115<=TODAY()+30),(G5:G115>=DATE(YEAR(TODAY()),1,1))*(G5:G115<=DATE(YEAR(TODAY()),12,31)))))))&" of "&COUNTA(A5:A115)&" bookings"} -> 101 of 101 bookings
A4: Booking ID | B4: Release ID | C4: Application | D4: Department | E4: Dependencies | F4: Release Size | G4: Prod Release Date | H4: CAB Date | I4: Test Env | J4: Test Start | K4: Test End | L4: Test Days | M4: UAT Env | N4: UAT Start | O4: UAT End | P4: UAT Days | Q4: Pre-Prod Env | R4: Pre-Prod Start | S4: Pre-Prod End | T4: Pre-Prod Days | U4: Conflict Flag | V4: Notes
A5: ENV-0001 | B5: REL-0001 | C5: Kyriba | D5: Finance | E5: NA | F5: Small | G5: 46203 | H5: 46201 | I5: FIN-TEST-01 | J5: 46196 | K5: 46198 | L5: 3 | M5: FIN-UAT-01 | N5: 46199 | O5: 46200 | P5: 2 | Q5: FIN-PREPROD-01 | R5: 46201 | S5: 46201 | T5: 1 | U5: ⚠️ CONFLICT | V5: Resource conflict with REL-0003 - Same Test/UAT env required
A6: ENV-0002 | B6: REL-0002 | C6: Blue Yonder WMS | D6: Logistics | E6: NA | F6: Medium | G6: 46207 | H6: 46205 | I6: LOG-TEST-01 | J6: 46194 | K6: 46198 | L6: 5 | M6: LOG-UAT-01 | N6: 46199 | O6: 46201 | P6: 3 | Q6: LOG-PREPROD-01 | R6: 46202 | S6: 46203 | T6: 2 | V6: Executive sponsor: CFO
A7: ENV-0003 | B7: REL-0003 | C7: Zendesk | D7: CRM | E7: NA | F7: Small | G7: 46205 | H7: 46203 | I7: FIN-TEST-01 | J7: 46198 | K7: 46200 | L7: 3 | M7: FIN-UAT-01 | N7: 46201 | O7: 46202 | P7: 2 | Q7: CRM-PREPROD-01 | R7: 46203 | S7: 46203 | T7: 1 | U7: ⚠️ CONFLICT | V7: Resource conflict with REL-0007 - Same Test/UAT env required
A8: ENV-0004 | B8: REL-0004 | C8: AVEVA MES | D8: Manufacturing | E8: NA | F8: Medium | G8: 46215 | H8: 46213 | I8: MAN-TEST-03 | J8: 46202 | K8: 46206 | L8: 5 | M8: MAN-UAT-01 | N8: 46207 | O8: 46209 | P8: 3 | Q8: MFG-PREPROD-01 | R8: 46210 | S8: 46211 | T8: 2 | V8: Blackout period consideration
A9: ENV-0005 | B9: REL-0005 | C9: Datadog | D9: IT | E9: NA | F9: Medium | G9: 46219 | H9: 46217 | I9: IT-TEST-01 | J9: 46206 | K9: 46210 | L9: 5 | M9: IT-UAT-01 | N9: 46211 | O9: 46213 | P9: 3 | Q9: IT-PREPROD-01 | R9: 46214 | S9: 46215 | T9: 2 | U9: ⚠️ CONFLICT | V9: Resource conflict with REL-0010 - Same Test/UAT env required
A10: ENV-0006 | B10: REL-0006 | C10: SAP SuccessFactors | D10: HR | E10: NA | F10: Small | G10: 46223 | H10: 46221 | I10: HR-TEST-01 | J10: 46216 | K10: 46218 | L10: 3 | M10: HR-UAT-01 | N10: 46219 | O10: 46220 | P10: 2 | Q10: HR-PREPROD-01 | R10: 46221 | S10: 46221 | T10: 1 | V10: Integration testing with downstream systems
A11: ENV-0007 | B11: REL-0007 | C11: Mitratech TeamConnect | D11: Legal | E11: NA | F11: Medium | G11: 46207 | H11: 46205 | I11: FIN-TEST-01 | J11: 46194 | K11: 46198 | L11: 5 | M11: FIN-UAT-01 | N11: 46199 | O11: 46201 | P11: 3 | Q11: LEG-PREPROD-01 | R11: 46202 | S11: 46203 | T11: 2 | U11: ⚠️ CONFLICT | V11: Resource conflict with REL-0012 - Same Test/UAT env required
A12: ENV-0008 | B12: REL-0008 | C12: CrowdStrike Falcon | D12: Security | E12: NA | F12: Small | G12: 46234 | H12: 46232 | I12: SEC-TEST-01 | J12: 46227 | K12: 46229 | L12: 3 | M12: SEC-UAT-02 | N12: 46230 | O12: 46231 | P12: 2 | Q12: SEC-PREPROD-01 | R12: 46232 | S12: 46232 | T12: 1 | V12: Data migration included
A13: ENV-0009 | B13: REL-0009 | C13: Oracle Hyperion HFM | D13: Finance | E13: {=IFERROR(_xlfn.TEXTJOIN(CHAR(10),TRUE,_xlfn._xlws.FILTER(#REF!&": "&#REF!,#REF!=$A13,"")),"")} | F13: Small | G13: 46238 | H13: 46236 | I13: FIN-TEST-03 | J13: 46231 | K13: 46233 | L13: 3 | M13: FIN-UAT-01 | N13: 46234 | O13: 46235 | P13: 2 | Q13: FIN-PREPROD-01 | R13: 46236 | S13: 46236 | T13: 1 | U13: ⚠️ CONFLICT | V13: Resource conflict with REL-0014 - Same Test/UAT env required
A14: ENV-0010 | B14: REL-0010 | C14: Manhattan Associates WMS | D14: Logistics | E14: NA | F14: Large | G14: 46221 | H14: 46218 | I14: IT-TEST-01 | J14: 46195 | K14: 46204 | L14: 10 | M14: IT-UAT-01 | N14: 46205 | O14: 46209 | P14: 5 | Q14: LOG-PREPROD-01 | R14: 46211 | S14: 46214 | T14: 4 | U14: ⚠️ CONFLICT | V14: Resource conflict with REL-0005 - Same Test/UAT env required
A15: ENV-0011 | B15: REL-0011 | C15: HubSpot CRM | D15: CRM | E15: NA | F15: Small | G15: 46246 | H15: 46244 | I15: CRM-TEST-02 | J15: 46239 | K15: 46241 | L15: 3 | M15: CRM-UAT-01 | N15: 46242 | O15: 46243 | P15: 2 | Q15: CRM-PREPROD-01 | R15: 46244 | S15: 46244 | T15: 1 | U15: ⚠️ CONFLICT | V15: Resource conflict with REL-0014 - Same Test/UAT env required
A16: ENV-0012 | B16: REL-0012 | C16: Plex Smart Manufacturing | D16: Manufacturing | E16: NA | F16: Small | G16: 46209 | H16: 46207 | I16: FIN-TEST-01 | J16: 46202 | K16: 46204 | L16: 3 | M16: FIN-UAT-01 | N16: 46205 | O16: 46206 | P16: 2 | Q16: MFG-PREPROD-01 | R16: 46207 | S16: 46207 | T16: 1 | U16: ⚠️ CONFLICT | V16: Resource conflict with REL-0007 - Same Test/UAT env required
A17: ENV-0013 | B17: REL-0013 | C17: Dynatrace | D17: IT | E17: {=IFERROR(_xlfn.TEXTJOIN(CHAR(10),TRUE,_xlfn._xlws.FILTER(#REF!&": "&#REF!,#REF!=$A17,"")),"")} | F17: Small | G17: 46254 | H17: 46252 | I17: IT-TEST-03 | J17: 46247 | K17: 46249 | L17: 3 | M17: IT-UAT-01 | N17: 46250 | O17: 46251 | P17: 2 | Q17: IT-PREPROD-01 | R17: 46252 | S17: 46252 | T17: 1 | U17: ⚠️ CONFLICT | V17: Resource conflict with REL-0015 - Same Test/UAT env required
A18: ENV-0014 | B18: REL-0014 | C18: Oracle HCM Cloud | D18: HR | E18: NA | F18: Large | G18: 46248 | H18: 46245 | I18: CRM-TEST-02 | J18: 46222 | K18: 46231 | L18: 10 | M18: CRM-UAT-01 | N18: 46232 | O18: 46236 | P18: 5 | Q18: HR-PREPROD-01 | R18: 46238 | S18: 46241 | T18: 4 | U18: ⚠️ CONFLICT | V18: Resource conflict with REL-0011 - Same Test/UAT env required
A19: ENV-0015 | B19: REL-0015 | C19: DocuSign CLM | D19: Legal | E19: NA | F19: Large | G19: 46256 | H19: 46253 | I19: IT-TEST-03 | J19: 46230 | K19: 46239 | L19: 10 | M19: IT-UAT-01 | N19: 46240 | O19: 46244 | P19: 5 | Q19: LEG-PREPROD-01 | R19: 46246 | S19: 46249 | T19: 4 | U19: ⚠️ CONFLICT | V19: Resource conflict with REL-0017 - Same Test/UAT env required
A20: ENV-0016 | B20: REL-0016 | C20: CyberArk PAM | D20: Security | E20: NA | F20: Large | G20: 46269 | H20: 46266 | I20: SEC-TEST-01 | J20: 46243 | K20: 46252 | L20: 10 | M20: SEC-UAT-02 | N20: 46253 | O20: 46257 | P20: 5 | Q20: SEC-PREPROD-01 | R20: 46259 | S20: 46262 | T20: 4 | V20: Change Advisory Board approval needed
A21: ENV-0017 | B21: REL-0017 | C21: HighRadius | D21: Finance | E21: {=IFERROR(_xlfn.TEXTJOIN(CHAR(10),TRUE,_xlfn._xlws.FILTER(#REF!&": "&#REF!,#REF!=$A21,"")),"")} | F21: Small | G21: 46258 | H21: 46256 | I21: IT-TEST-03 | J21: 46251 | K21: 46253 | L21: 3 | M21: IT-UAT-01 | N21: 46254 | O21: 46255 | P21: 2 | Q21: FIN-PREPROD-01 | R21: 46256 | S21: 46256 | T21: 1 | U21: ⚠️ CONFLICT | V21: Resource conflict with REL-0022 - Same Test/UAT env required
A22: ENV-0018 | B22: REL-0018 | C22: Oracle Transportation Management | D22: Logistics | E22: NA | F22: Small | G22: 46277 | H22: 46275 | I22: LOG-TEST-03 | J22: 46270 | K22: 46272 | L22: 3 | M22: LOG-UAT-02 | N22: 46273 | O22: 46274 | P22: 2 | Q22: LOG-PREPROD-01 | R22: 46275 | S22: 46275 | T22: 1 | V22: Audit finding remediation
A23: ENV-0019 | B23: REL-0019 | C23: Salesforce Service Cloud | D23: CRM | E23: NA | F23: Small | G23: 46281 | H23: 46279 | I23: CRM-TEST-01 | J23: 46274 | K23: 46276 | L23: 3 | M23: CRM-UAT-02 | N23: 46277 | O23: 46278 | P23: 2 | Q23: CRM-PREPROD-01 | R23: 46279 | S23: 46279 | T23: 1 | U23: ⚠️ CONFLICT | V23: Resource conflict with REL-0021 - Same Test/UAT env required
A24: ENV-0020 | B24: REL-0020 | C24: Rockwell FactoryTalk | D24: Manufacturing | E24: NA | F24: Small | G24: 46285 | H24: 46283 | I24: MAN-TEST-03 | J24: 46278 | K24: 46280 | L24: 3 | M24: MAN-UAT-01 | N24: 46281 | O24: 46282 | P24: 2 | Q24: MFG-PREPROD-01 | R24: 46283 | S24: 46283 | T24: 1 | V24: Holiday freeze exception requested
A25: ENV-0021 | B25: REL-0021 | C25: Splunk Enterprise | D25: IT | E25: {=IFERROR(_xlfn.TEXTJOIN(CHAR(10),TRUE,_xlfn._xlws.FILTER(#REF!&": "&#REF!,#REF!=$A25,"")),"")} | F25: Small | G25: 46283 | H25: 46281 | I25: CRM-TEST-01 | J25: 46276 | K25: 46278 | L25: 3 | M25: CRM-UAT-02 | N25: 46279 | O25: 46280 | P25: 2 | Q25: IT-PREPROD-01 | R25: 46281 | S25: 46281 | T25: 1 | U25: ⚠️ CONFLICT | V25: Resource conflict with REL-0026 - Same Test/UAT env required
A26: ENV-0022 | B26: REL-0022 | C26: Oracle HCM Cloud | D26: HR | E26: NA | F26: Medium | G26: 46260 | H26: 46258 | I26: IT-TEST-03 | J26: 46247 | K26: 46251 | L26: 5 | M26: IT-UAT-01 | N26: 46252 | O26: 46254 | P26: 3 | Q26: HR-PREPROD-01 | R26: 46255 | S26: 46256 | T26: 2 | U26: ⚠️ CONFLICT | V26: Resource conflict with REL-0017 - Same Test/UAT env required
A27: ENV-0023 | B27: REL-0023 | C27: DocuSign CLM | D27: Legal | E27: NA | F27: Medium | G27: 46299 | H27: 46297 | I27: LEG-TEST-02 | J27: 46286 | K27: 46290 | L27: 5 | M27: LEG-UAT-02 | N27: 46291 | O27: 46293 | P27: 3 | Q27: LEG-PREPROD-01 | R27: 46294 | S27: 46295 | T27: 2 | U27: ⚠️ CONFLICT | V27: Resource conflict with REL-0027 - Same Test/UAT env required
A28: ENV-0024 | B28: REL-0024 | C28: Okta Identity Cloud | D28: Security | E28: NA | F28: Small | G28: 46303 | H28: 46301 | I28: SEC-TEST-01 | J28: 46296 | K28: 46298 | L28: 3 | M28: SEC-UAT-02 | N28: 46299 | O28: 46300 | P28: 2 | Q28: SEC-PREPROD-01 | R28: 46301 | S28: 46301 | T28: 1 | V28: Security review pending
A29: ENV-0025 | B29: REL-0025 | C29: Coupa | D29: Finance | E29: {=IFERROR(_xlfn.TEXTJOIN(CHAR(10),TRUE,_xlfn._xlws.FILTER(#REF!&": "&#REF!,#REF!=$A29,"")),"")} | F29: Medium | G29: 46307 | H29: 46305 | I29: FIN-TEST-03 | J29: 46294 | K29: 46298 | L29: 5 | M29: FIN-UAT-02 | N29: 46299 | O29: 46301 | P29: 3 | Q29: FIN-PREPROD-01 | R29: 46302 | S29: 46303 | T29: 2 | V29: DR sync required post-deployment
A30: ENV-0026 | B30: REL-0026 | C30: Kinaxis RapidResponse | D30: Logistics | E30: NA | F30: Medium | G30: 46285 | H30: 46283 | I30: CRM-TEST-01 | J30: 46272 | K30: 46276 | L30: 5 | M30: CRM-UAT-02 | N30: 46277 | O30: 46279 | P30: 3 | Q30: LOG-PREPROD-01 | R30: 46280 | S30: 46281 | T30: 2 | U30: ⚠️ CONFLICT | V30: Resource conflict with REL-0021 - Same Test/UAT env required
A31: ENV-0027 | B31: REL-0027 | C31: Salesforce Sales Cloud | D31: CRM | E31: NA | F31: Small | G31: 46301 | H31: 46299 | I31: LEG-TEST-02 | J31: 46294 | K31: 46296 | L31: 3 | M31: LEG-UAT-02 | N31: 46297 | O31: 46298 | P31: 2 | Q31: CRM-PREPROD-01 | R31: 46299 | S31: 46299 | T31: 1 | U31: ⚠️ CONFLICT | V31: Resource conflict with REL-0023 - Same Test/UAT env required
A32: ENV-0028 | B32: REL-0028 | C32: SAP S/4HANA Manufacturing | D32: Manufacturing | E32: NA | F32: Large | G32: 46319 | H32: 46316 | I32: MAN-TEST-03 | J32: 46293 | K32: 46302 | L32: 10 | M32: MAN-UAT-01 | N32: 46303 | O32: 46307 | P32: 5 | Q32: MFG-PREPROD-01 | R32: 46309 | S32: 46312 | T32: 4 | V32: Critical for Q3 financial close
A33: ENV-0029 | B33: REL-0029 | C33: Datadog | D33: IT | E33: {=IFERROR(_xlfn.TEXTJOIN(CHAR(10),TRUE,_xlfn._xlws.FILTER(#REF!&": "&#REF!,#REF!=$A33,"")),"")} | F33: Medium | G33: 46326 | H33: 46324 | I33: IT-TEST-03 | J33: 46313 | K33: 46317 | L33: 5 | M33: IT-UAT-01 | N33: 46318 | O33: 46320 | P33: 3 | Q33: IT-PREPROD-01 | R33: 46321 | S33: 46322 | T33: 2 | V33: Dependencies on infrastructure team
A34: ENV-0030 | B34: REL-0030 | C34: Cornerstone OnDemand | D34: HR | E34: NA | F34: Medium | G34: 46330 | H34: 46328 | I34: HR-TEST-02 | J34: 46317 | K34: 46321 | L34: 5 | M34: HR-UAT-01 | N34: 46322 | O34: 46324 | P34: 3 | Q34: HR-PREPROD-01 | R34: 46325 | S34: 46326 | T34: 2 | V34: Dependent on vendor patch delivery
A35: ENV-0031 | B35: REL-0031 | C35: Mitratech TeamConnect | D35: Legal | E35: NA | F35: Small | G35: 46334 | H35: 46332 | I35: LEG-TEST-02 | J35: 46327 | K35: 46329 | L35: 3 | M35: LEG-UAT-02 | N35: 46330 | O35: 46331 | P35: 2 | Q35: LEG-PREPROD-01 | R35: 46332 | S35: 46332 | T35: 1 | V35: Executive sponsor: CIO
A36: ENV-0032 | B36: REL-0032 | C36: CrowdStrike Falcon | D36: Security | E36: NA | F36: Small | G36: 46338 | H36: 46336 | I36: SEC-TEST-01 | J36: 46331 | K36: 46333 | L36: 3 | M36: SEC-UAT-02 | N36: 46334 | O36: 46335 | P36: 2 | Q36: SEC-PREPROD-01 | R36: 46336 | S36: 46336 | T36: 1 | V36: Integration testing with downstream systems
A37: ENV-0033 | B37: REL-0033 | C37: Oracle Hyperion HFM | D37: Finance | E37: {=IFERROR(_xlfn.TEXTJOIN(CHAR(10),TRUE,_xlfn._xlws.FILTER(#REF!&": "&#REF!,#REF!=$A37,"")),"")} | F37: Large | G37: 46342 | H37: 46339 | I37: FIN-TEST-01 | J37: 46316 | K37: 46325 | L37: 10 | M37: FIN-UAT-01 | N37: 46326 | O37: 46330 | P37: 5 | Q37: FIN-PREPROD-01 | R37: 46332 | S37: 46335 | T37: 4 | V37: Dependencies on infrastructure team
A38: ENV-0034 | B38: REL-0034 | C38: Manhattan Associates WMS | D38: Logistics | E38: NA | F38: Medium | G38: 46346 | H38: 46344 | I38: LOG-TEST-01 | J38: 46333 | K38: 46337 | L38: 5 | M38: LOG-UAT-01 | N38: 46338 | O38: 46340 | P38: 3 | Q38: LOG-PREPROD-01 | R38: 46341 | S38: 46342 | T38: 2 | V38: Executive sponsor: CFO
A39: ENV-0035 | B39: REL-0035 | C39: Salesforce Service Cloud | D39: CRM | E39: NA | F39: Small | G39: 46350 | H39: 46348 | I39: CRM-TEST-01 | J39: 46343 | K39: 46345 | L39: 3 | M39: CRM-UAT-02 | N39: 46346 | O39: 46347 | P39: 2 | Q39: CRM-PREPROD-01 | R39: 46348 | S39: 46348 | T39: 1 | V39: Change Advisory Board approval needed
A40: ENV-0036 | B40: REL-0036 | C40: Plex Smart Manufacturing | D40: Manufacturing | E40: NA | F40: Small | G40: 46356 | H40: 46354 | I40: MAN-TEST-03 | J40: 46349 | K40: 46351 | L40: 3 | M40: MAN-UAT-01 | N40: 46352 | O40: 46353 | P40: 2 | Q40: MFG-PREPROD-01 | R40: 46354 | S40: 46354 | T40: 1 | V40: Data migration included
A41: ENV-0037 | B41: REL-0037 | C41: Dynatrace | D41: IT | E41: {=IFERROR(_xlfn.TEXTJOIN(CHAR(10),TRUE,_xlfn._xlws.FILTER(#REF!&": "&#REF!,#REF!=$A41,"")),"")} | F41: Large | G41: 46360 | H41: 46357 | I41: IT-TEST-03 | J41: 46334 | K41: 46343 | L41: 10 | M41: IT-UAT-02 | N41: 46344 | O41: 46348 | P41: 5 | Q41: IT-PREPROD-01 | R41: 46350 | S41: 46353 | T41: 4 | V41: Customer-facing impact - coordinate with support
A42: ENV-0038 | B42: REL-0038 | C42: SAP SuccessFactors | D42: HR | E42: NA | F42: Small | G42: 46364 | H42: 46362 | I42: HR-TEST-02 | J42: 46357 | K42: 46359 | L42: 3 | M42: HR-UAT-02 | N42: 46360 | O42: 46361 | P42: 2 | Q42: HR-PREPROD-01 | R42: 46362 | S42: 46362 | T42: 1 | V42: Dependent on vendor patch delivery
A43: ENV-0039 | B43: REL-0039 | C43: Agiloft CLM | D43: Legal | E43: NA | F43: Large | G43: 46368 | H43: 46365 | I43: LEG-TEST-03 | J43: 46342 | K43: 46351 | L43: 10 | M43: LEG-UAT-01 | N43: 46352 | O43: 46356 | P43: 5 | Q43: LEG-PREPROD-01 | R43: 46358 | S43: 46361 | T43: 4 | V43: Holiday freeze exception requested
A44: ENV-0040 | B44: REL-0040 | C44: Palo Alto Cortex XDR | D44: Security | E44: NA | F44: Small | G44: 46372 | H44: 46370 | I44: SEC-TEST-03 | J44: 46365 | K44: 46367 | L44: 3 | M44: SEC-UAT-02 | N44: 46368 | O44: 46369 | P44: 2 | Q44: SEC-PREPROD-01 | R44: 46370 | S44: 46370 | T44: 1 | V44: Critical for Q3 financial close
A45: ENV-0041 | B45: REL-0041 | C45: Anaplan | D45: Finance | E45: {=IFERROR(_xlfn.TEXTJOIN(CHAR(10),TRUE,_xlfn._xlws.FILTER(#REF!&": "&#REF!,#REF!=$A45,"")),"")} | F45: Small | G45: 46376 | H45: 46374 | I45: FIN-TEST-01 | J45: 46369 | K45: 46371 | L45: 3 | M45: FIN-UAT-01 | N45: 46372 | O45: 46373 | P45: 2 | Q45: FIN-PREPROD-01 | R45: 46374 | S45: 46374 | T45: 1 | U45: ⚠️ CONFLICT | V45: Resource conflict with REL-0043 - Overlapping Test/UAT window
A46: ENV-0042 | B46: REL-0042 | C46: Oracle Transportation Management | D46: Logistics | E46: NA | F46: Medium | G46: 46380 | H46: 46378 | I46: LOG-TEST-01 | J46: 46367 | K46: 46371 | L46: 5 | M46: LOG-UAT-01 | N46: 46372 | O46: 46374 | P46: 3 | Q46: LOG-PREPROD-01 | R46: 46375 | S46: 46376 | T46: 2 | V46: Executive sponsor: CFO
A47: ENV-0043 | B47: REL-0043 | C47: Microsoft Dynamics 365 CRM | D47: CRM | E47: NA | F47: Medium | G47: 46379 | H47: 46377 | I47: FIN-TEST-01 | J47: 46366 | K47: 46370 | L47: 5 | M47: FIN-UAT-01 | N47: 46371 | O47: 46373 | P47: 3 | Q47: CRM-PREPROD-01 | R47: 46374 | S47: 46375 | T47: 2 | U47: ⚠️ CONFLICT | V47: Resource conflict with REL-0041 - Overlapping Test/UAT window
A48: ENV-0044 | B48: REL-0044 | C48: Siemens Opcenter | D48: Manufacturing | E48: NA | F48: Medium | G48: 46391 | H48: 46389 | I48: MAN-TEST-01 | J48: 46378 | K48: 46382 | L48: 5 | M48: MAN-UAT-01 | N48: 46383 | O48: 46385 | P48: 3 | Q48: MFG-PREPROD-01 | R48: 46386 | S48: 46387 | T48: 2 | V48: License renewal dependency
A49: ENV-0045 | B49: REL-0045 | C49: Splunk Enterprise | D49: IT | E49: {=IFERROR(_xlfn.TEXTJOIN(CHAR(10),TRUE,_xlfn._xlws.FILTER(#REF!&": "&#REF!,#REF!=$A49,"")),"")} | F49: Large | G49: 46395 | H49: 46392 | I49: IT-TEST-01 | J49: 46369 | K49: 46378 | L49: 10 | M49: IT-UAT-01 | N49: 46379 | O49: 46383 | P49: 5 | Q49: IT-PREPROD-01 | R49: 46385 | S49: 46388 | T49: 4 | V49: Critical for Q3 financial close
A50: ENV-0046 | B50: REL-0046 | C50: SAP SuccessFactors | D50: HR | E50: NA | F50: Small | G50: 46399 | H50: 46397 | I50: HR-TEST-03 | J50: 46392 | K50: 46394 | L50: 3 | M50: HR-UAT-02 | N50: 46395 | O50: 46396 | P50: 2 | Q50: HR-PREPROD-01 | R50: 46397 | S50: 46397 | T50: 1 | V50: Executive sponsor: CFO
A51: ENV-0047 | B51: REL-0047 | C51: DocuSign CLM | D51: Legal | E51: NA | F51: Medium | G51: 46403 | H51: 46401 | I51: LEG-TEST-02 | J51: 46390 | K51: 46394 | L51: 5 | M51: LEG-UAT-02 | N51: 46395 | O51: 46397 | P51: 3 | Q51: LEG-PREPROD-01 | R51: 46398 | S51: 46399 | T51: 2 | V51: Customer-facing impact - coordinate with support
A52: ENV-0048 | B52: REL-0048 | C52: Okta Identity Cloud | D52: Security | E52: NA | F52: Small | G52: 46407 | H52: 46405 | I52: SEC-TEST-03 | J52: 46400 | K52: 46402 | L52: 3 | M52: SEC-UAT-01 | N52: 46403 | O52: 46404 | P52: 2 | Q52: SEC-PREPROD-01 | R52: 46405 | S52: 46405 | T52: 1 | V52: External vendor coordination needed
A53: ENV-0049 | B53: REL-0049 | C53: Anaplan | D53: Finance | E53: {=IFERROR(_xlfn.TEXTJOIN(CHAR(10),TRUE,_xlfn._xlws.FILTER(#REF!&": "&#REF!,#REF!=$A53,"")),"")} | F53: Small | G53: 46411 | H53: 46409 | I53: FIN-TEST-02 | J53: 46404 | K53: 46406 | L53: 3 | M53: FIN-UAT-02 | N53: 46407 | O53: 46408 | P53: 2 | Q53: FIN-PREPROD-01 | R53: 46409 | S53: 46409 | T53: 1 | V53: DR sync required post-deployment
A54: ENV-0050 | B54: REL-0050 | C54: Blue Yonder WMS | D54: Logistics | E54: NA | F54: Small | G54: 46418 | H54: 46416 | I54: LOG-TEST-01 | J54: 46411 | K54: 46413 | L54: 3 | M54: LOG-UAT-02 | N54: 46414 | O54: 46415 | P54: 2 | Q54: LOG-PREPROD-01 | R54: 46416 | S54: 46416 | T54: 1 | V54: Executive sponsor: CIO
A55: ENV-0051 | B55: REL-0051 | C55: HubSpot CRM | D55: CRM | E55: NA | F55: Medium | G55: 46422 | H55: 46420 | I55: CRM-TEST-03 | J55: 46409 | K55: 46413 | L55: 5 | M55: CRM-UAT-02 | N55: 46414 | O55: 46416 | P55: 3 | Q55: CRM-PREPROD-01 | R55: 46417 | S55: 46418 | T55: 2 | V55: Requires weekend deployment window
A56: ENV-0052 | B56: REL-0052 | C56: SAP S/4HANA Manufacturing | D56: Manufacturing | E56: NA | F56: Small | G56: 46426 | H56: 46424 | I56: MAN-TEST-01 | J56: 46419 | K56: 46421 | L56: 3 | M56: MAN-UAT-01 | N56: 46422 | O56: 46423 | P56: 2 | Q56: MFG-PREPROD-01 | R56: 46424 | S56: 46424 | T56: 1 | V56: DR sync required post-deployment
A57: ENV-0053 | B57: REL-0053 | C57: Splunk Enterprise | D57: IT | E57: {=IFERROR(_xlfn.TEXTJOIN(CHAR(10),TRUE,_xlfn._xlws.FILTER(#REF!&": "&#REF!,#REF!=$A57,"")),"")} | F57: Large | G57: 46430 | H57: 46427 | I57: IT-TEST-03 | J57: 46404 | K57: 46413 | L57: 10 | M57: IT-UAT-02 | N57: 46414 | O57: 46418 | P57: 5 | Q57: IT-PREPROD-01 | R57: 46420 | S57: 46423 | T57: 4 | V57: Dependent on vendor patch delivery
A58: ENV-0054 | B58: REL-0054 | C58: Workday HCM | D58: HR | E58: NA | F58: Large | G58: 46434 | H58: 46431 | I58: HR-TEST-01 | J58: 46408 | K58: 46417 | L58: 10 | M58: HR-UAT-01 | N58: 46418 | O58: 46422 | P58: 5 | Q58: HR-PREPROD-01 | R58: 46424 | S58: 46427 | T58: 4 | V58: Training materials to be updated
A59: ENV-0055 | B59: REL-0055 | C59: DocuSign CLM | D59: Legal | E59: NA | F59: Large | G59: 46438 | H59: 46435 | I59: LEG-TEST-03 | J59: 46412 | K59: 46421 | L59: 10 | M59: LEG-UAT-01 | N59: 46422 | O59: 46426 | P59: 5 | Q59: LEG-PREPROD-01 | R59: 46428 | S59: 46431 | T59: 4 | V59: Rollback plan required
A60: ENV-0056 | B60: REL-0056 | C60: Okta Identity Cloud | D60: Security | E60: NA | F60: Medium | G60: 46442 | H60: 46440 | I60: SEC-TEST-01 | J60: 46429 | K60: 46433 | L60: 5 | M60: SEC-UAT-02 | N60: 46434 | O60: 46436 | P60: 3 | Q60: SEC-PREPROD-01 | R60: 46437 | S60: 46438 | T60: 2 | U60: ⚠️ CONFLICT | V60: Resource conflict with REL-0058 - Overlapping Test/UAT window
A61: ENV-0057 | B61: REL-0057 | C61: Coupa | D61: Finance | E61: {=IFERROR(_xlfn.TEXTJOIN(CHAR(10),TRUE,_xlfn._xlws.FILTER(#REF!&": "&#REF!,#REF!=$A61,"")),"")} | F61: Medium | G61: 46446 | H61: 46444 | I61: FIN-TEST-02 | J61: 46433 | K61: 46437 | L61: 5 | M61: FIN-UAT-01 | N61: 46438 | O61: 46440 | P61: 3 | Q61: FIN-PREPROD-01 | R61: 46441 | S61: 46442 | T61: 2 | V61: External vendor coordination needed
A62: ENV-0058 | B62: REL-0058 | C62: Manhattan Associates WMS | D62: Logistics | E62: NA | F62: Medium | G62: 46445 | H62: 46443 | I62: SEC-TEST-01 | J62: 46432 | K62: 46436 | L62: 5 | M62: SEC-UAT-02 | N62: 46437 | O62: 46439 | P62: 3 | Q62: LOG-PREPROD-01 | R62: 46440 | S62: 46441 | T62: 2 | U62: ⚠️ CONFLICT | V62: Resource conflict with REL-0056 - Overlapping Test/UAT window
A63: ENV-0059 | B63: REL-0059 | C63: Salesforce Service Cloud | D63: CRM | E63: NA | F63: Medium | G63: 46454 | H63: 46452 | I63: CRM-TEST-03 | J63: 46441 | K63: 46445 | L63: 5 | M63: CRM-UAT-02 | N63: 46446 | O63: 46448 | P63: 3 | Q63: CRM-PREPROD-01 | R63: 46449 | S63: 46450 | T63: 2 | V63: Holiday freeze exception requested
A64: ENV-0060 | B64: REL-0060 | C64: Plex Smart Manufacturing | D64: Manufacturing | E64: NA | F64: Small | G64: 46458 | H64: 46456 | I64: MAN-TEST-02 | J64: 46451 | K64: 46453 | L64: 3 | M64: MAN-UAT-02 | N64: 46454 | O64: 46455 | P64: 2 | Q64: MFG-PREPROD-01 | R64: 46456 | S64: 46456 | T64: 1 | V64: Performance testing mandatory
A65: ENV-0061 | B65: REL-0061 | C65: Datadog | D65: IT | E65: {=IFERROR(_xlfn.TEXTJOIN(CHAR(10),TRUE,_xlfn._xlws.FILTER(#REF!&": "&#REF!,#REF!=$A65,"")),"")} | F65: Medium | G65: 46462 | H65: 46460 | I65: IT-TEST-02 | J65: 46449 | K65: 46453 | L65: 5 | M65: IT-UAT-01 | N65: 46454 | O65: 46456 | P65: 3 | Q65: IT-PREPROD-01 | R65: 46457 | S65: 46458 | T65: 2 | V65: Holiday freeze exception requested
A66: ENV-0062 | B66: REL-0062 | C66: SAP SuccessFactors | D66: HR | E66: NA | F66: Small | G66: 46466 | H66: 46464 | I66: HR-TEST-03 | J66: 46459 | K66: 46461 | L66: 3 | M66: HR-UAT-02 | N66: 46462 | O66: 46463 | P66: 2 | Q66: HR-PREPROD-01 | R66: 46464 | S66: 46464 | T66: 1 | V66: Dependent on vendor patch delivery
A67: ENV-0063 | B67: REL-0063 | C67: Mitratech TeamConnect | D67: Legal | E67: NA | F67: Medium | G67: 46470 | H67: 46468 | I67: LEG-TEST-01 | J67: 46457 | K67: 46461 | L67: 5 | M67: LEG-UAT-02 | N67: 46462 | O67: 46464 | P67: 3 | Q67: LEG-PREPROD-01 | R67: 46465 | S67: 46466 | T67: 2 | V67: Business continuity testing required
A68: ENV-0064 | B68: REL-0064 | C68: Microsoft Sentinel | D68: Security | E68: NA | F68: Medium | G68: 46477 | H68: 46475 | I68: SEC-TEST-03 | J68: 46464 | K68: 46468 | L68: 5 | M68: SEC-UAT-02 | N68: 46469 | O68: 46471 | P68: 3 | Q68: SEC-PREPROD-01 | R68: 46472 | S68: 46473 | T68: 2 | V68: Customer-facing impact - coordinate with support
A69: ENV-0065 | B69: REL-0065 | C69: Oracle Hyperion HFM | D69: Finance | E69: {=IFERROR(_xlfn.TEXTJOIN(CHAR(10),TRUE,_xlfn._xlws.FILTER(#REF!&": "&#REF!,#REF!=$A69,"")),"")} | F69: Large | G69: 46481 | H69: 46478 | I69: FIN-TEST-03 | J69: 46455 | K69: 46464 | L69: 10 | M69: FIN-UAT-02 | N69: 46465 | O69: 46469 | P69: 5 | Q69: FIN-PREPROD-01 | R69: 46471 | S69: 46474 | T69: 4 | V69: Dependencies on infrastructure team
A70: ENV-0066 | B70: REL-0066 | C70: Oracle Transportation Management | D70: Logistics | E70: NA | F70: Medium | G70: 46485 | H70: 46483 | I70: LOG-TEST-02 | J70: 46472 | K70: 46476 | L70: 5 | M70: LOG-UAT-01 | N70: 46477 | O70: 46479 | P70: 3 | Q70: LOG-PREPROD-01 | R70: 46480 | S70: 46481 | T70: 2 | U70: ⚠️ CONFLICT | V70: Resource conflict with REL-0068 - Overlapping Test/UAT window
A71: ENV-0067 | B71: REL-0067 | C71: Salesforce Sales Cloud | D71: CRM | E71: NA | F71: Large | G71: 46489 | H71: 46486 | I71: CRM-TEST-03 | J71: 46463 | K71: 46472 | L71: 10 | M71: CRM-UAT-02 | N71: 46473 | O71: 46477 | P71: 5 | Q71: CRM-PREPROD-01 | R71: 46479 | S71: 46482 | T71: 4 | V71: Blackout period consideration
A72: ENV-0068 | B72: REL-0068 | C72: Rockwell FactoryTalk | D72: Manufacturing | E72: NA | F72: Small | G72: 46488 | H72: 46486 | I72: LOG-TEST-02 | J72: 46481 | K72: 46483 | L72: 3 | M72: LOG-UAT-01 | N72: 46484 | O72: 46485 | P72: 2 | Q72: MFG-PREPROD-01 | R72: 46486 | S72: 46486 | T72: 1 | U72: ⚠️ CONFLICT | V72: Resource conflict with REL-0066 - Overlapping Test/UAT window
A73: ENV-0069 | B73: REL-0069 | C73: BMC Remedy | D73: IT | E73: {=IFERROR(_xlfn.TEXTJOIN(CHAR(10),TRUE,_xlfn._xlws.FILTER(#REF!&": "&#REF!,#REF!=$A73,"")),"")} | F73: Small | G73: 46497 | H73: 46495 | I73: IT-TEST-01 | J73: 46490 | K73: 46492 | L73: 3 | M73: IT-UAT-01 | N73: 46493 | O73: 46494 | P73: 2 | Q73: IT-PREPROD-01 | R73: 46495 | S73: 46495 | T73: 1 | V73: Rollback plan required
A74: ENV-0070 | B74: REL-0070 | C74: Oracle HCM Cloud | D74: HR | E74: NA | F74: Medium | G74: 46501 | H74: 46499 | I74: HR-TEST-02 | J74: 46488 | K74: 46492 | L74: 5 | M74: HR-UAT-02 | N74: 46493 | O74: 46495 | P74: 3 | Q74: HR-PREPROD-01 | R74: 46496 | S74: 46497 | T74: 2 | V74: Requires weekend deployment window
A75: ENV-0071 | B75: REL-0071 | C75: Agiloft CLM | D75: Legal | E75: NA | F75: Small | G75: 46507 | H75: 46505 | I75: LEG-TEST-03 | J75: 46500 | K75: 46502 | L75: 3 | M75: LEG-UAT-01 | N75: 46503 | O75: 46504 | P75: 2 | Q75: LEG-PREPROD-01 | R75: 46505 | S75: 46505 | T75: 1 | U75: ⚠️ CONFLICT | V75: Resource conflict with REL-0073 - Overlapping Test/UAT window
A76: ENV-0072 | B76: REL-0072 | C76: Palo Alto Cortex XDR | D76: Security | E76: NA | F76: Small | G76: 46511 | H76: 46509 | I76: SEC-TEST-01 | J76: 46504 | K76: 46506 | L76: 3 | M76: SEC-UAT-01 | N76: 46507 | O76: 46508 | P76: 2 | Q76: SEC-PREPROD-01 | R76: 46509 | S76: 46509 | T76: 1 | V76: Dependent on vendor patch delivery
A77: ENV-0073 | B77: REL-0073 | C77: Kyriba | D77: Finance | E77: {=IFERROR(_xlfn.TEXTJOIN(CHAR(10),TRUE,_xlfn._xlws.FILTER(#REF!&": "&#REF!,#REF!=$A77,"")),"")} | F77: Medium | G77: 46510 | H77: 46508 | I77: LEG-TEST-03 | J77: 46497 | K77: 46501 | L77: 5 | M77: LEG-UAT-01 | N77: 46502 | O77: 46504 | P77: 3 | Q77: FIN-PREPROD-01 | R77: 46505 | S77: 46506 | T77: 2 | U77: ⚠️ CONFLICT | V77: Resource conflict with REL-0071 - Overlapping Test/UAT window
A78: ENV-0074 | B78: REL-0074 | C78: Oracle Transportation Management | D78: Logistics | E78: NA | F78: Small | G78: 46519 | H78: 46517 | I78: LOG-TEST-03 | J78: 46512 | K78: 46514 | L78: 3 | M78: LOG-UAT-02 | N78: 46515 | O78: 46516 | P78: 2 | Q78: LOG-PREPROD-01 | R78: 46517 | S78: 46517 | T78: 1 | V78: Dependent on vendor patch delivery
A79: ENV-0075 | B79: REL-0075 | C79: HubSpot CRM | D79: CRM | E79: NA | F79: Medium | G79: 46523 | H79: 46521 | I79: CRM-TEST-02 | J79: 46510 | K79: 46514 | L79: 5 | M79: CRM-UAT-02 | N79: 46515 | O79: 46517 | P79: 3 | Q79: CRM-PREPROD-01 | R79: 46518 | S79: 46519 | T79: 2 | V79: Dependencies on infrastructure team
A80: ENV-0076 | B80: REL-0076 | C80: SAP S/4HANA Manufacturing | D80: Manufacturing | E80: NA | F80: Small | G80: 46527 | H80: 46525 | I80: MAN-TEST-01 | J80: 46520 | K80: 46522 | L80: 3 | M80: MAN-UAT-01 | N80: 46523 | O80: 46524 | P80: 2 | Q80: MFG-PREPROD-01 | R80: 46525 | S80: 46525 | T80: 1 | V80: Security review pending
A81: ENV-0077 | B81: REL-0077 | C81: Jira Service Management | D81: IT | E81: {=IFERROR(_xlfn.TEXTJOIN(CHAR(10),TRUE,_xlfn._xlws.FILTER(#REF!&": "&#REF!,#REF!=$A81,"")),"")} | F81: Large | G81: 46531 | H81: 46528 | I81: IT-TEST-02 | J81: 46505 | K81: 46514 | L81: 10 | M81: IT-UAT-01 | N81: 46515 | O81: 46519 | P81: 5 | Q81: IT-PREPROD-01 | R81: 46521 | S81: 46524 | T81: 4 | V81: Rollback plan required
A82: ENV-0078 | B82: REL-0078 | C82: ADP Workforce Now | D82: HR | E82: NA | F82: Medium | G82: 46538 | H82: 46536 | I82: HR-TEST-03 | J82: 46525 | K82: 46529 | L82: 5 | M82: HR-UAT-02 | N82: 46530 | O82: 46532 | P82: 3 | Q82: HR-PREPROD-01 | R82: 46533 | S82: 46534 | T82: 2 | V82: Regulatory deadline driven
A83: ENV-0079 | B83: REL-0079 | C83: Ironclad | D83: Legal | E83: NA | F83: Medium | G83: 46542 | H83: 46540 | I83: LEG-TEST-01 | J83: 46529 | K83: 46533 | L83: 5 | M83: LEG-UAT-01 | N83: 46534 | O83: 46536 | P83: 3 | Q83: LEG-PREPROD-01 | R83: 46537 | S83: 46538 | T83: 2 | V83: Dependencies on infrastructure team
A84: ENV-0080 | B84: REL-0080 | C84: CrowdStrike Falcon | D84: Security | E84: NA | F84: Medium | G84: 46546 | H84: 46544 | I84: SEC-TEST-03 | J84: 46533 | K84: 46537 | L84: 5 | M84: SEC-UAT-01 | N84: 46538 | O84: 46540 | P84: 3 | Q84: SEC-PREPROD-01 | R84: 46541 | S84: 46542 | T84: 2 | V84: Audit finding remediation
A87: ENVIRONMENT BOOKING SUMMARY
A89: Testing Phase Durations:
A90: • Large Releases: Test (10 days) → UAT (5 days) → Pre-Prod (4 days) → CAB (-3 days) → Prod (+2 days max)
A91: • Medium Releases: Test (5 days) → UAT (3 days) → Pre-Prod (2 days) → CAB (-2 days) → Prod (+1 day)
A92: • Small Releases: Test (3 days) → UAT (2 days) → Pre-Prod (1 day) → CAB (-2 days) → Prod (same day)
A94: Color Legend:
A95: Blue = Test Phase | Green = UAT Phase | Orange = Pre-Prod Phase | Purple = CAB Date | Peach = Prod Date | Red = Conflict | F95: Test Phase | G95: UAT Phase | I95: Pre-Prod Phase | J95: Conflict
A98: Environment Usage Statistics
A100: Metric | B100: Value | C100: Formula
A101: Total Releases | B101: =COUNTA(A5:A84) -> 80
A102: Releases with Conflicts | B102: =COUNTIF(U5:U84,"*CONFLICT*") -> 26
A103: Large Releases | B103: =COUNTIF(F5:F84,"Large") -> 15
A104: Medium Releases | B104: =COUNTIF(F5:F84,"Medium") -> 30
A105: Small Releases | B105: =COUNTIF(F5:F84,"Small") -> 35
A106: Total Test Days Required | B106: =SUM(L5:L84)+SUM(P5:P84)+SUM(T5:T84) -> 795
A107: CAB Meetings Required | B107: =COUNTA(H5:H84) -> 80
A111: CHANGE FREEZE PERIODS
...

Sheet Risk Factors
A1: COMPREHENSIVE RELEASE RISK SCORING MODEL
A2: Multi-factor weighted risk assessment for Release Desk Go/No-Go decisions
I3: Total Releases Assessed | J3: =COUNTA($A$68:$A$79) -> 12
A4: Category | B4: Factor Name | C4: Weight | D4: Description | E4: Score 1 (Best) | F4: Score 5 (Worst) | G4: Data Source | I4: SEVERE Risk Releases | J4: =COUNTIF($AX$68:$AX$79,"SEVERE") -> 2 | K4: Immediate review required
A5: Technical Complexity | B5: Files Changed | C5: 0.04 | D5: Number of modified files | E5: <10 | F5: ≥100 | G5: Git/SCM | I5: CRITICAL Risk Releases | J5: =COUNTIF($AX$68:$AX$79,"CRITICAL") -> 1 | K5: Executive approval needed
B6: Code Churn (LOC) | C6: 0.03 | D6: Lines of code changed | E6: <200 | F6: ≥3000 | G6: Git/SCM | I6: HIGH Risk Releases | J6: =COUNTIF($AX$68:$AX$79,"HIGH") -> 0 | K6: CAB review required
B7: DB Schema Changes | C7: 0.05 | D7: Database schema modifications | E7: 0 | F7: ≥5 | G7: Migration Scripts | I7: MEDIUM Risk Releases | J7: =COUNTIF($AX$68:$AX$79,"MEDIUM") -> 5 | K7: Enhanced monitoring
B8: API Contract Changes | C8: 0.04 | D8: Breaking API changes | E8: 0 | F8: ≥4 | G8: API Specs | I8: LOW Risk Releases | J8: =COUNTIF($AX$68:$AX$79,"LOW") -> 4 | K8: Standard deployment
B9: New Technology Stack | C9: 0.02 | D9: Unfamiliar tech introduced | E9: Proven stack | F9: Entirely new | G9: Architecture Review
A10: Testing Quality | B10: Test Coverage % | C10: 0.06 | D10: Code coverage percentage | E10: >90% | F10: <60% | G10: SonarQube | I10: Average Risk Score | J10: =ROUND(AVERAGE($AW$68:$AW$79),2) -> 2.28
B11: Test Execution Days | C11: 0.03 | D11: Testing duration | E11: <3 days | F11: ≥10 days | G11: Test Plan | I11: Highest Risk Release | J11: =INDEX($A$68:$A$79,MATCH(MAX($AW$68:$AW$79),$AW$68:$AW$79,0)) -> REL-0010 | K11: =MAX($AW$68:$AW$79) -> 4.52
B12: Bugs Found (Test) | C12: 0.04 | D12: Defects discovered in testing | E12: <3 | F12: ≥15 | G12: Jira
B13: Bug Fix Rate % | C13: 0.02 | D13: Defects fixed vs found | E13: >95% | F13: <60% | G13: Jira
B14: UAT Duration Days | C14: 0.03 | D14: UAT testing period | E14: <3 days | F14: ≥10 days | G14: UAT Plan
B15: UAT Defects | C15: 0.04 | D15: Defects found in UAT | E15: <2 | F15: ≥8 | G15: Jira
B16: UAT Sign-off | C16: 0.02 | D16: Business sign-off status | E16: Full sign-off | F16: No sign-off | G16: UAT Tracker
B17: Test Env Parity | C17: 0.02 | D17: Test env match with Prod | E17: ≥95% match | F17: <60% match | G17: Env Config
A18: Security & Compliance | B18: Critical/High Vulns | C18: 0.03 | D18: Open security vulnerabilities | E18: 0 | F18: ≥5 | G18: SAST/DAST
B19: Pen Test Sign-off | C19: 0.02 | D19: Penetration test status | E19: Passed | F19: Not done | G19: Security Team
B20: Compliance Gate | C20: 0.03 | D20: SOX/GDPR/PCI-DSS status | E20: All passed | F20: Blocked | G20: GRC System
A21: Data Migration | B21: Migration Required | C21: 0.01 | D21: Data migration needed | E21: No | F21: Yes, complex | G21: Release Notes | I21: RISK SCORE THRESHOLDS
B22: Backup Restore Tested | C22: 0.015 | D22: Backup/restore verified | E22: Yes, verified | F22: Not tested | G22: DBA Team | I22: Level | J22: Score Range | K22: Action
B23: Migration Script Tested | C23: 0.015 | D23: Migration scripts validated | E23: Tested in Pre-prod | F23: Not tested | G23: DBA Team | I23: LOW | J23: < 1.5 | K23: Standard deployment
A24: Resource & Schedule | B24: Testers Allocated | C24: 0.02 | D24: QA resource count | E24: >3 | F24: 1 or none | G24: Resource Plan | I24: MEDIUM | J24: 1.5 - 2.5 | K24: Enhanced monitoring
B25: Key Staff Availability | C25: 0.03 | D25: Critical personnel present | E25: All available | F25: Key staff OOO | G25: Leave Calendar | I25: HIGH | J25: 2.5 - 3.5 | K25: CAB review required
B26: Days Until Release | C26: 0.04 | D26: Time to deployment | E26: >30 days | F26: <5 days | G26: Release Schedule | I26: CRITICAL | J26: 3.5 - 4.0 | K26: Executive approval needed
B27: Downstream Releases | C27: 0.03 | D27: Dependent releases count | E27: 0 | F27: ≥4 | G27: Dependencies | I27: SEVERE | J27: ≥ 4.0 | K27: Postpone or major mitigation
B28: Overlapping Releases | C28: 0.02 | D28: Releases in same window | E28: 0 | F28: ≥4 | G28: Release Calendar
A29: Env & Dependencies | B29: Drift Issues | C29: 0.03 | D29: Environment drift count | E29: 0 | F29: ≥4 | G29: Drift Tracker
B30: Dependency Count | C30: 0.02 | D30: External dependencies | E30: 0 | F30: ≥4 | G30: Dependencies
B31: Dependency Health | C31: 0.02 | D31: Upstream system status | E31: All healthy | F31: Critical blocked | G31: Health Dashboard
B32: Feature Flag Cleanup | C32: 0.02 | D32: Stale feature flags | E32: Clean | F32: ≥5 stale flags | G32: Feature Mgmt
A33: Operational Readiness | B33: Rollback Plan | C33: 0.02 | D33: Rollback documented | E33: Full plan tested | F33: No plan | G33: Runbook
B34: Go-Live Checklist % | C34: 0.02 | D34: Checklist completion | E34: >90% | F34: <50% | G34: Checklist
B35: Change Freeze Impact | C35: 0.015 | D35: Freeze window conflict | E35: No conflict | F35: During freeze | G35: Calendar
B36: Vendor Coordination | C36: 0.005 | D36: Vendor readiness | E36: Confirmed | F36: Not coordinated | G36: Vendor Mgmt
B37: Rollback Time RTO | C37: 0.02 | D37: Rollback duration (min) | E37: <15 min | F37: >120 min | G37: Runbook
B38: Deployment Automation % | C38: 0.015 | D38: Automation level | E38: >90% | F38: <50% | G38: CI/CD Pipeline
A39: Performance & Scalability | B39: Load Test Status | C39: 0.02 | D39: Load testing result | E39: Passed | F39: Not done | G39: Perf Team
B40: Perf Regression % | C40: 0.02 | D40: Performance vs baseline | E40: <5% | F40: >25% | G40: APM Tools
A41: Release History | B41: BC Tested | C41: 0.015 | D41: Backward compatibility | E41: Fully tested | F41: Not tested | G41: Test Results
B42: Rollback Flow Tested | C42: 0.015 | D42: Rollback rehearsal done | E42: Tested in Pre-prod | F42: Never tested | G42: Deployment Runbook
B43: Previous Failures | C43: 0.005 | D43: Past failure history | E43: 0 failures (12mo) | F43: ≥3 failures | G43: Incident History
B44: Release Cadence Dev | C44: 0.005 | D44: Deviation from schedule | E44: On schedule | F44: >14 days late | G44: Release Plan
B45: MTBF Days | C45: 0.005 | D45: Mean time between failures | E45: >180 days | F45: <14 days | G45: Incident Metrics
B46: Recent Incidents | C46: 0.005 | D46: Incidents last 30 days | E46: 0 | F46: ≥3 | G46: Incident Mgmt
A47: Business Criticality | B47: Revenue Impact | C47: 0.01 | D47: Revenue risk if failed | E47: Low | F47: High | G47: Business Team
B48: User Blast Radius | C48: 0.01 | D48: Users/customers affected | E48: <100 | F48: >100K or all | G48: Product Team
A50: WEIGHT SUMMARY BY CATEGORY
A51: Category | B51: Weight | C51: Factors
A52: Technical Complexity | B52: 0.18 | C52: 5 factors
A53: Testing Quality | B53: 0.26 | C53: 8 factors
A54: Security & Compliance | B54: 0.08 | C54: 3 factors
A55: Data Migration | B55: 0.04 | C55: 3 factors
A56: Resource & Schedule | B56: 0.14 | C56: 5 factors
A57: Env & Dependencies | B57: 0.09 | C57: 4 factors
A58: Operational Readiness | B58: 0.1 | C58: 6 factors
A59: Performance & Scalability | B59: 0.04 | C59: 2 factors
A60: Release History | B60: 0.05 | C60: 6 factors
A61: Business Criticality | B61: 0.02 | C61: 2 factors
A62: TOTAL | B62: 1 | C62: 44 factors
A63: FORMULA: Weighted Score = Σ (Factor Score × Factor Weight)
A66: RELEASE RISK ASSESSMENT DATA
A67: Release ID | B67: Release Name | C67: Prod Date | D67: Days Out | E67: Files Changed | F67: Code Churn | G67: DB Changes | H67: API Changes | I67: New Tech Stack | J67: Test Coverage % | K67: Test Days | L67: Test Bugs | M67: Bug Fix Rate % | N67: UAT Days | O67: UAT Defects | P67: UAT Sign-off | Q67: Test Env Parity | R67: Crit/High Vulns | S67: Pen Test | T67: Compliance Gate | U67: Migration Req | V67: Backup Tested | W67: Migration Script | X67: Team Size | Y67: Deploy Window | Z67: Freeze Proximity | AA67: Key Staff Avail | AB67: Overlapping Rels | AC67: Dep Count | AD67: Dep Health | AE67: Vendor Involvement | AF67: Feature Flags | AG67: Rollback Plan | AH67: Docs Complete | AI67: Monitoring Ready | AJ67: Runbook Updated | AK67: Rollback RTO | AL67: Deploy Auto % | AM67: Load Test | AN67: Perf Regression % | AO67: Vendor Patch | AP67: Cadence Dev | AQ67: MTBF Days | AR67: Past Failures | AS67: BC Tested | AT67: Rollback Tested | AU67: Revenue Impact | AV67: Blast Radius | AW67: WEIGHTED SCORE | AX67: RISK LEVEL
A68: REL-0001 | B68: Kyriba UI Tweak v4.5 | C68: 46203 | D68: 5 | E68: 12 | F68: 320 | G68: 0 | H68: 0 | I68: 1 | J68: 85 | K68: 3 | L68: 2 | M68: 100 | N68: 2 | O68: 0 | P68: 4 | Q68: 4 | R68: 0 | S68: 4 | T68: 5 | U68: 0 | V68: 5 | W68: 5 | X68: 2 | Y68: 2 | Z68: 30 | AA68: 5 | AB68: 1 | AC68: 2 | AD68: 5 | AE68: 0 | AF68: 5 | AG68: 4 | AH68: 4 | AI68: 4 | AJ68: 4 | AK68: 15 | AL68: 90 | AM68: 5 | AN68: 5 | AO68: 5 | AP68: 0 | AQ68: 90 | AR68: 0 | AS68: 5 | AT68: 4 | AU68: 1 | AV68: 500 | AW68: =ROUND((IF(E68<10,1,IF(E68<30,2,IF(E68<60,3,IF(E68<100,4,5))))*0.04)+(IF(F68<200,1,IF(F68<500,2,IF(F68<1500,3,IF(F68<3000,4,5))))*0.03)+(IF(G68=0,1,IF(G68=1,2,IF(G68=2,3,IF(G68<5,4,5))))*0.05)+(IF(H68=0,1,IF(H68=1,2,IF(H68=2,3,IF(H68=3,4,5))))*0.04)+(I68*0.02)+(IF(J68>90,1,IF(J68>80,2,IF(J68>70,3,IF(J68>60,4,5))))*0.06)+(IF(K68<3,1,IF(K68<5,2,IF(K68<7,3,IF(K68<10,4,5))))*0.03)+(IF(L68<3,1,IF(L68<6,2,IF(L68<10,3,IF(L68<15,4,5))))*0.04)+(IF(M68>95,1,IF(M68>85,2,IF(M68>75,3,IF(M68>60,4,5))))*0.02)+(IF(N68<3,1,IF(N68<5,2,IF(N68<7,3,IF(N68<10,4,5))))*0.03)+(IF(O68<2,1,IF(O68<4,2,IF(O68<7,3,IF(O68<10,4,5))))*0.02)+((6-P68)*0.03)+((6-Q68)*0.02)+(IF(R68=0,1,IF(R68<3,2,IF(R68<5,3,IF(R68<10,4,5))))*0.03)+((6-S68)*0.03)+((6-T68)*0.02)+(IF(U68=0,1,3)*0.015)+((6-V68)*0.01)+((6-W68)*0.015)+(IF(X68<3,1,IF(X68<6,2,IF(X68<10,3,IF(X68<15,4,5))))*0.02)+(IF(Y68<2,1,IF(Y68<4,2,IF(Y68<6,3,IF(Y68<8,4,5))))*0.03)+(IF(Z68>14,1,IF(Z68>7,2,IF(Z68>3,3,IF(Z68>1,4,5))))*0.03)+((6-AA68)*0.03)+(IF(AB68=0,1,IF(AB68=1,2,IF(AB68=2,3,IF(AB68=3,4,5))))*0.03)+(IF(AC68<2,1,IF(AC68<4,2,IF(AC68<6,3,IF(AC68<8,4,5))))*0.03)+((6-AD68)*0.02)+(IF(AE68=0,1,IF(AE68=1,3,5))*0.02)+((6-AF68)*0.02)+((6-AG68)*0.02)+((6-AH68)*0.015)+((6-AI68)*0.015)+((6-AJ68)*0.015)+(IF(AK68<15,1,IF(AK68<30,2,IF(AK68<60,3,IF(AK68<120,4,5))))*0.02)+(IF(AL68>90,1,IF(AL68>75,2,IF(AL68>50,3,IF(AL68>25,4,5))))*0.015)+((6-AM68)*0.02)+(IF(AN68<5,1,IF(AN68<10,2,IF(AN68<15,3,IF(AN68<25,4,5))))*0.02)+((6-AO68)*0.01)+(IF(AP68<2,1,IF(AP68<5,2,IF(AP68<10,3,IF(AP68<20,4,5))))*0.008)+(IF(AQ68>60,1,IF(AQ68>30,2,IF(AQ68>14,3,IF(AQ68>7,4,5))))*0.008)+(IF(AR68=0,1,IF(AR68=1,2,IF(AR68=2,3,IF(AR68=3,4,5))))*0.01)+((6-AS68)*0.008)+((6-AT68)*0.008)+(AU68*0.01)+(IF(AV68<1000,1,IF(AV68<5000,2,IF(AV68<20000,3,IF(AV68<50000,4,5))))*0.01),2) -> 1.45 | AX68: =IF(AW68>=4,"SEVERE",IF(AW68>=3.5,"CRITICAL",IF(AW68>=2.5,"HIGH",IF(AW68>=1.5,"MEDIUM","LOW")))) -> LOW
A69: REL-0002 | B69: Blue Workflow v2.1 | C69: 46207 | D69: 9 | E69: 45 | F69: 1200 | G69: 1 | H69: 1 | I69: 2 | J69: 72 | K69: 5 | L69: 8 | M69: 90 | N69: 4 | O69: 3 | P69: 3 | Q69: 3 | R69: 2 | S69: 3 | T69: 4 | U69: 0 | V69: 4 | W69: 5 | X69: 5 | Y69: 3 | Z69: 20 | AA69: 4 | AB69: 2 | AC69: 3 | AD69: 4 | AE69: 1 | AF69: 4 | AG69: 3 | AH69: 3 | AI69: 3 | AJ69: 4 | AK69: 30 | AL69: 75 | AM69: 4 | AN69: 10 | AO69: 4 | AP69: 3 | AQ69: 60 | AR69: 1 | AS69: 4 | AT69: 3 | AU69: 2 | AV69: 5000 | AW69: =ROUND((IF(E69<10,1,IF(E69<30,2,IF(E69<60,3,IF(E69<100,4,5))))*0.04)+(IF(F69<200,1,IF(F69<500,2,IF(F69<1500,3,IF(F69<3000,4,5))))*0.03)+(IF(G69=0,1,IF(G69=1,2,IF(G69=2,3,IF(G69<5,4,5))))*0.05)+(IF(H69=0,1,IF(H69=1,2,IF(H69=2,3,IF(H69=3,4,5))))*0.04)+(I69*0.02)+(IF(J69>90,1,IF(J69>80,2,IF(J69>70,3,IF(J69>60,4,5))))*0.06)+(IF(K69<3,1,IF(K69<5,2,IF(K69<7,3,IF(K69<10,4,5))))*0.03)+(IF(L69<3,1,IF(L69<6,2,IF(L69<10,3,IF(L69<15,4,5))))*0.04)+(IF(M69>95,1,IF(M69>85,2,IF(M69>75,3,IF(M69>60,4,5))))*0.02)+(IF(N69<3,1,IF(N69<5,2,IF(N69<7,3,IF(N69<10,4,5))))*0.03)+(IF(O69<2,1,IF(O69<4,2,IF(O69<7,3,IF(O69<10,4,5))))*0.02)+((6-P69)*0.03)+((6-Q69)*0.02)+(IF(R69=0,1,IF(R69<3,2,IF(R69<5,3,IF(R69<10,4,5))))*0.03)+((6-S69)*0.03)+((6-T69)*0.02)+(IF(U69=0,1,3)*0.015)+((6-V69)*0.01)+((6-W69)*0.015)+(IF(X69<3,1,IF(X69<6,2,IF(X69<10,3,IF(X69<15,4,5))))*0.02)+(IF(Y69<2,1,IF(Y69<4,2,IF(Y69<6,3,IF(Y69<8,4,5))))*0.03)+(IF(Z69>14,1,IF(Z69>7,2,IF(Z69>3,3,IF(Z69>1,4,5))))*0.03)+((6-AA69)*0.03)+(IF(AB69=0,1,IF(AB69=1,2,IF(AB69=2,3,IF(AB69=3,4,5))))*0.03)+(IF(AC69<2,1,IF(AC69<4,2,IF(AC69<6,3,IF(AC69<8,4,5))))*0.03)+((6-AD69)*0.02)+(IF(AE69=0,1,IF(AE69=1,3,5))*0.02)+((6-AF69)*0.02)+((6-AG69)*0.02)+((6-AH69)*0.015)+((6-AI69)*0.015)+((6-AJ69)*0.015)+(IF(AK69<15,1,IF(AK69<30,2,IF(AK69<60,3,IF(AK69<120,4,5))))*0.02)+(IF(AL69>90,1,IF(AL69>75,2,IF(AL69>50,3,IF(AL69>25,4,5))))*0.015)+((6-AM69)*0.02)+(IF(AN69<5,1,IF(AN69<10,2,IF(AN69<15,3,IF(AN69<25,4,5))))*0.02)+((6-AO69)*0.01)+(IF(AP69<2,1,IF(AP69<5,2,IF(AP69<10,3,IF(AP69<20,4,5))))*0.008)+(IF(AQ69>60,1,IF(AQ69>30,2,IF(AQ69>14,3,IF(AQ69>7,4,5))))*0.008)+(IF(AR69=0,1,IF(AR69=1,2,IF(AR69=2,3,IF(AR69=3,4,5))))*0.01)+((6-AS69)*0.008)+((6-AT69)*0.008)+(AU69*0.01)+(IF(AV69<1000,1,IF(AV69<5000,2,IF(AV69<20000,3,IF(AV69<50000,4,5))))*0.01),2) -> 2.38 | AX69: =IF(AW69>=4,"SEVERE",IF(AW69>=3.5,"CRITICAL",IF(AW69>=2.5,"HIGH",IF(AW69>=1.5,"MEDIUM","LOW")))) -> MEDIUM
A70: REL-0003 | B70: Zendesk Minor v4.3 | C70: 46205 | D70: 7 | E70: 5 | F70: 80 | G70: 0 | H70: 0 | I70: 1 | J70: 92 | K70: 2 | L70: 1 | M70: 100 | N70: 1 | O70: 0 | P70: 5 | Q70: 5 | R70: 0 | S70: 5 | T70: 5 | U70: 0 | V70: 5 | W70: 5 | X70: 2 | Y70: 1 | Z70: 45 | AA70: 5 | AB70: 0 | AC70: 1 | AD70: 5 | AE70: 0 | AF70: 5 | AG70: 5 | AH70: 5 | AI70: 5 | AJ70: 5 | AK70: 10 | AL70: 95 | AM70: 5 | AN70: 2 | AO70: 5 | AP70: 5 | AQ70: 120 | AR70: 0 | AS70: 5 | AT70: 5 | AU70: 1 | AV70: 200 | AW70: =ROUND((IF(E70<10,1,IF(E70<30,2,IF(E70<60,3,IF(E70<100,4,5))))*0.04)+(IF(F70<200,1,IF(F70<500,2,IF(F70<1500,3,IF(F70<3000,4,5))))*0.03)+(IF(G70=0,1,IF(G70=1,2,IF(G70=2,3,IF(G70<5,4,5))))*0.05)+(IF(H70=0,1,IF(H70=1,2,IF(H70=2,3,IF(H70=3,4,5))))*0.04)+(I70*0.02)+(IF(J70>90,1,IF(J70>80,2,IF(J70>70,3,IF(J70>60,4,5))))*0.06)+(IF(K70<3,1,IF(K70<5,2,IF(K70<7,3,IF(K70<10,4,5))))*0.03)+(IF(L70<3,1,IF(L70<6,2,IF(L70<10,3,IF(L70<15,4,5))))*0.04)+(IF(M70>95,1,IF(M70>85,2,IF(M70>75,3,IF(M70>60,4,5))))*0.02)+(IF(N70<3,1,IF(N70<5,2,IF(N70<7,3,IF(N70<10,4,5))))*0.03)+(IF(O70<2,1,IF(O70<4,2,IF(O70<7,3,IF(O70<10,4,5))))*0.02)+((6-P70)*0.03)+((6-Q70)*0.02)+(IF(R70=0,1,IF(R70<3,2,IF(R70<5,3,IF(R70<10,4,5))))*0.03)+((6-S70)*0.03)+((6-T70)*0.02)+(IF(U70=0,1,3)*0.015)+((6-V70)*0.01)+((6-W70)*0.015)+(IF(X70<3,1,IF(X70<6,2,IF(X70<10,3,IF(X70<15,4,5))))*0.02)+(IF(Y70<2,1,IF(Y70<4,2,IF(Y70<6,3,IF(Y70<8,4,5))))*0.03)+(IF(Z70>14,1,IF(Z70>7,2,IF(Z70>3,3,IF(Z70>1,4,5))))*0.03)+((6-AA70)*0.03)+(IF(AB70=0,1,IF(AB70=1,2,IF(AB70=2,3,IF(AB70=3,4,5))))*0.03)+(IF(AC70<2,1,IF(AC70<4,2,IF(AC70<6,3,IF(AC70<8,4,5))))*0.03)+((6-AD70)*0.02)+(IF(AE70=0,1,IF(AE70=1,3,5))*0.02)+((6-AF70)*0.02)+((6-AG70)*0.02)+((6-AH70)*0.015)+((6-AI70)*0.015)+((6-AJ70)*0.015)+(IF(AK70<15,1,IF(AK70<30,2,IF(AK70<60,3,IF(AK70<120,4,5))))*0.02)+(IF(AL70>90,1,IF(AL70>75,2,IF(AL70>50,3,IF(AL70>25,4,5))))*0.015)+((6-AM70)*0.02)+(IF(AN70<5,1,IF(AN70<10,2,IF(AN70<15,3,IF(AN70<25,4,5))))*0.02)+((6-AO70)*0.01)+(IF(AP70<2,1,IF(AP70<5,2,IF(AP70<10,3,IF(AP70<20,4,5))))*0.008)+(IF(AQ70>60,1,IF(AQ70>30,2,IF(AQ70>14,3,IF(AQ70>7,4,5))))*0.008)+(IF(AR70=0,1,IF(AR70=1,2,IF(AR70=2,3,IF(AR70=3,4,5))))*0.01)+((6-AS70)*0.008)+((6-AT70)*0.008)+(AU70*0.01)+(IF(AV70<1000,1,IF(AV70<5000,2,IF(AV70<20000,3,IF(AV70<50000,4,5))))*0.01),2) -> 1.01 | AX70: =IF(AW70>=4,"SEVERE",IF(AW70>=3.5,"CRITICAL",IF(AW70>=2.5,"HIGH",IF(AW70>=1.5,"MEDIUM","LOW")))) -> LOW
A71: REL-0004 | B71: Oracle HFM Upgrade v12 | C71: 46210 | D71: 12 | E71: 85 | F71: 3200 | G71: 4 | H71: 2 | I71: 3 | J71: 65 | K71: 8 | L71: 15 | M71: 80 | N71: 7 | O71: 8 | P71: 2 | Q71: 2 | R71: 5 | S71: 2 | T71: 3 | U71: 1 | V71: 3 | W71: 3 | X71: 8 | Y71: 4 | Z71: 10 | AA71: 3 | AB71: 3 | AC71: 5 | AD71: 3 | AE71: 2 | AF71: 3 | AG71: 2 | AH71: 2 | AI71: 2 | AJ71: 3 | AK71: 60 | AL71: 60 | AM71: 3 | AN71: 18 | AO71: 3 | AP71: 2 | AQ71: 45 | AR71: 2 | AS71: 3 | AT71: 2 | AU71: 3 | AV71: 25000 | AW71: =ROUND((IF(E71<10,1,IF(E71<30,2,IF(E71<60,3,IF(E71<100,4,5))))*0.04)+(IF(F71<200,1,IF(F71<500,2,IF(F71<1500,3,IF(F71<3000,4,5))))*0.03)+(IF(G71=0,1,IF(G71=1,2,IF(G71=2,3,IF(G71<5,4,5))))*0.05)+(IF(H71=0,1,IF(H71=1,2,IF(H71=2,3,IF(H71=3,4,5))))*0.04)+(I71*0.02)+(IF(J71>90,1,IF(J71>80,2,IF(J71>70,3,IF(J71>60,4,5))))*0.06)+(IF(K71<3,1,IF(K71<5,2,IF(K71<7,3,IF(K71<10,4,5))))*0.03)+(IF(L71<3,1,IF(L71<6,2,IF(L71<10,3,IF(L71<15,4,5))))*0.04)+(IF(M71>95,1,IF(M71>85,2,IF(M71>75,3,IF(M71>60,4,5))))*0.02)+(IF(N71<3,1,IF(N71<5,2,IF(N71<7,3,IF(N71<10,4,5))))*0.03)+(IF(O71<2,1,IF(O71<4,2,IF(O71<7,3,IF(O71<10,4,5))))*0.02)+((6-P71)*0.03)+((6-Q71)*0.02)+(IF(R71=0,1,IF(R71<3,2,IF(R71<5,3,IF(R71<10,4,5))))*0.03)+((6-S71)*0.03)+((6-T71)*0.02)+(IF(U71=0,1,3)*0.015)+((6-V71)*0.01)+((6-W71)*0.015)+(IF(X71<3,1,IF(X71<6,2,IF(X71<10,3,IF(X71<15,4,5))))*0.02)+(IF(Y71<2,1,IF(Y71<4,2,IF(Y71<6,3,IF(Y71<8,4,5))))*0.03)+(IF(Z71>14,1,IF(Z71>7,2,IF(Z71>3,3,IF(Z71>1,4,5))))*0.03)+((6-AA71)*0.03)+(IF(AB71=0,1,IF(AB71=1,2,IF(AB71=2,3,IF(AB71=3,4,5))))*0.03)+(IF(AC71<2,1,IF(AC71<4,2,IF(AC71<6,3,IF(AC71<8,4,5))))*0.03)+((6-AD71)*0.02)+(IF(AE71=0,1,IF(AE71=1,3,5))*0.02)+((6-AF71)*0.02)+((6-AG71)*0.02)+((6-AH71)*0.015)+((6-AI71)*0.015)+((6-AJ71)*0.015)+(IF(AK71<15,1,IF(AK71<30,2,IF(AK71<60,3,IF(AK71<120,4,5))))*0.02)+(IF(AL71>90,1,IF(AL71>75,2,IF(AL71>50,3,IF(AL71>25,4,5))))*0.015)+((6-AM71)*0.02)+(IF(AN71<5,1,IF(AN71<10,2,IF(AN71<15,3,IF(AN71<25,4,5))))*0.02)+((6-AO71)*0.01)+(IF(AP71<2,1,IF(AP71<5,2,IF(AP71<10,3,IF(AP71<20,4,5))))*0.008)+(IF(AQ71>60,1,IF(AQ71>30,2,IF(AQ71>14,3,IF(AQ71>7,4,5))))*0.008)+(IF(AR71=0,1,IF(AR71=1,2,IF(AR71=2,3,IF(AR71=3,4,5))))*0.01)+((6-AS71)*0.008)+((6-AT71)*0.008)+(AU71*0.01)+(IF(AV71<1000,1,IF(AV71<5000,2,IF(AV71<20000,3,IF(AV71<50000,4,5))))*0.01),2) -> 3.59 | AX71: =IF(AW71>=4,"SEVERE",IF(AW71>=3.5,"CRITICAL",IF(AW71>=2.5,"HIGH",IF(AW71>=1.5,"MEDIUM","LOW")))) -> CRITICAL
A72: REL-0005 | B72: Coupa Integration v3.0 | C72: 46215 | D72: 17 | E72: 35 | F72: 950 | G72: 1 | H72: 2 | I72: 2 | J72: 78 | K72: 4 | L72: 5 | M72: 95 | N72: 3 | O72: 2 | P72: 4 | Q72: 4 | R72: 1 | S72: 4 | T72: 4 | U72: 0 | V72: 4 | W72: 5 | X72: 4 | Y72: 3 | Z72: 25 | AA72: 4 | AB72: 1 | AC72: 3 | AD72: 4 | AE72: 1 | AF72: 4 | AG72: 4 | AH72: 4 | AI72: 4 | AJ72: 4 | AK72: 25 | AL72: 80 | AM72: 4 | AN72: 8 | AO72: 4 | AP72: 4 | AQ72: 75 | AR72: 0 | AS72: 4 | AT72: 4 | AU72: 2 | AV72: 8000 | AW72: =ROUND((IF(E72<10,1,IF(E72<30,2,IF(E72<60,3,IF(E72<100,4,5))))*0.04)+(IF(F72<200,1,IF(F72<500,2,IF(F72<1500,3,IF(F72<3000,4,5))))*0.03)+(IF(G72=0,1,IF(G72=1,2,IF(G72=2,3,IF(G72<5,4,5))))*0.05)+(IF(H72=0,1,IF(H72=1,2,IF(H72=2,3,IF(H72=3,4,5))))*0.04)+(I72*0.02)+(IF(J72>90,1,IF(J72>80,2,IF(J72>70,3,IF(J72>60,4,5))))*0.06)+(IF(K72<3,1,IF(K72<5,2,IF(K72<7,3,IF(K72<10,4,5))))*0.03)+(IF(L72<3,1,IF(L72<6,2,IF(L72<10,3,IF(L72<15,4,5))))*0.04)+(IF(M72>95,1,IF(M72>85,2,IF(M72>75,3,IF(M72>60,4,5))))*0.02)+(IF(N72<3,1,IF(N72<5,2,IF(N72<7,3,IF(N72<10,4,5))))*0.03)+(IF(O72<2,1,IF(O72<4,2,IF(O72<7,3,IF(O72<10,4,5))))*0.02)+((6-P72)*0.03)+((6-Q72)*0.02)+(IF(R72=0,1,IF(R72<3,2,IF(R72<5,3,IF(R72<10,4,5))))*0.03)+((6-S72)*0.03)+((6-T72)*0.02)+(IF(U72=0,1,3)*0.015)+((6-V72)*0.01)+((6-W72)*0.015)+(IF(X72<3,1,IF(X72<6,2,IF(X72<10,3,IF(X72<15,4,5))))*0.02)+(IF(Y72<2,1,IF(Y72<4,2,IF(Y72<6,3,IF(Y72<8,4,5))))*0.03)+(IF(Z72>14,1,IF(Z72>7,2,IF(Z72>3,3,IF(Z72>1,4,5))))*0.03)+((6-AA72)*0.03)+(IF(AB72=0,1,IF(AB72=1,2,IF(AB72=2,3,IF(AB72=3,4,5))))*0.03)+(IF(AC72<2,1,IF(AC72<4,2,IF(AC72<6,3,IF(AC72<8,4,5))))*0.03)+((6-AD72)*0.02)+(IF(AE72=0,1,IF(AE72=1,3,5))*0.02)+((6-AF72)*0.02)+((6-AG72)*0.02)+((6-AH72)*0.015)+((6-AI72)*0.015)+((6-AJ72)*0.015)+(IF(AK72<15,1,IF(AK72<30,2,IF(AK72<60,3,IF(AK72<120,4,5))))*0.02)+(IF(AL72>90,1,IF(AL72>75,2,IF(AL72>50,3,IF(AL72>25,4,5))))*0.015)+((6-AM72)*0.02)+(IF(AN72<5,1,IF(AN72<10,2,IF(AN72<15,3,IF(AN72<25,4,5))))*0.02)+((6-AO72)*0.01)+(IF(AP72<2,1,IF(AP72<5,2,IF(AP72<10,3,IF(AP72<20,4,5))))*0.008)+(IF(AQ72>60,1,IF(AQ72>30,2,IF(AQ72>14,3,IF(AQ72>7,4,5))))*0.008)+(IF(AR72=0,1,IF(AR72=1,2,IF(AR72=2,3,IF(AR72=3,4,5))))*0.01)+((6-AS72)*0.008)+((6-AT72)*0.008)+(AU72*0.01)+(IF(AV72<1000,1,IF(AV72<5000,2,IF(AV72<20000,3,IF(AV72<50000,4,5))))*0.01),2) -> 2.11 | AX72: =IF(AW72>=4,"SEVERE",IF(AW72>=3.5,"CRITICAL",IF(AW72>=2.5,"HIGH",IF(AW72>=1.5,"MEDIUM","LOW")))) -> MEDIUM
A73: REL-0006 | B73: Salesforce Patch v8.2 | C73: 46220 | D73: 22 | E73: 18 | F73: 420 | G73: 0 | H73: 1 | I73: 1 | J73: 88 | K73: 3 | L73: 3 | M73: 100 | N73: 2 | O73: 1 | P73: 4 | Q73: 4 | R73: 0 | S73: 4 | T73: 5 | U73: 0 | V73: 5 | W73: 5 | X73: 3 | Y73: 2 | Z73: 35 | AA73: 5 | AB73: 0 | AC73: 2 | AD73: 5 | AE73: 0 | AF73: 5 | AG73: 4 | AH73: 4 | AI73: 4 | AJ73: 5 | AK73: 20 | AL73: 85 | AM73: 5 | AN73: 4 | AO73: 5 | AP73: 5 | AQ73: 90 | AR73: 0 | AS73: 5 | AT73: 5 | AU73: 1 | AV73: 1500 | AW73: =ROUND((IF(E73<10,1,IF(E73<30,2,IF(E73<60,3,IF(E73<100,4,5))))*0.04)+(IF(F73<200,1,IF(F73<500,2,IF(F73<1500,3,IF(F73<3000,4,5))))*0.03)+(IF(G73=0,1,IF(G73=1,2,IF(G73=2,3,IF(G73<5,4,5))))*0.05)+(IF(H73=0,1,IF(H73=1,2,IF(H73=2,3,IF(H73=3,4,5))))*0.04)+(I73*0.02)+(IF(J73>90,1,IF(J73>80,2,IF(J73>70,3,IF(J73>60,4,5))))*0.06)+(IF(K73<3,1,IF(K73<5,2,IF(K73<7,3,IF(K73<10,4,5))))*0.03)+(IF(L73<3,1,IF(L73<6,2,IF(L73<10,3,IF(L73<15,4,5))))*0.04)+(IF(M73>95,1,IF(M73>85,2,IF(M73>75,3,IF(M73>60,4,5))))*0.02)+(IF(N73<3,1,IF(N73<5,2,IF(N73<7,3,IF(N73<10,4,5))))*0.03)+(IF(O73<2,1,IF(O73<4,2,IF(O73<7,3,IF(O73<10,4,5))))*0.02)+((6-P73)*0.03)+((6-Q73)*0.02)+(IF(R73=0,1,IF(R73<3,2,IF(R73<5,3,IF(R73<10,4,5))))*0.03)+((6-S73)*0.03)+((6-T73)*0.02)+(IF(U73=0,1,3)*0.015)+((6-V73)*0.01)+((6-W73)*0.015)+(IF(X73<3,1,IF(X73<6,2,IF(X73<10,3,IF(X73<15,4,5))))*0.02)+(IF(Y73<2,1,IF(Y73<4,2,IF(Y73<6,3,IF(Y73<8,4,5))))*0.03)+(IF(Z73>14,1,IF(Z73>7,2,IF(Z73>3,3,IF(Z73>1,4,5))))*0.03)+((6-AA73)*0.03)+(IF(AB73=0,1,IF(AB73=1,2,IF(AB73=2,3,IF(AB73=3,4,5))))*0.03)+(IF(AC73<2,1,IF(AC73<4,2,IF(AC73<6,3,IF(AC73<8,4,5))))*0.03)+((6-AD73)*0.02)+(IF(AE73=0,1,IF(AE73=1,3,5))*0.02)+((6-AF73)*0.02)+((6-AG73)*0.02)+((6-AH73)*0.015)+((6-AI73)*0.015)+((6-AJ73)*0.015)+(IF(AK73<15,1,IF(AK73<30,2,IF(AK73<60,3,IF(AK73<120,4,5))))*0.02)+(IF(AL73>90,1,IF(AL73>75,2,IF(AL73>50,3,IF(AL73>25,4,5))))*0.015)+((6-AM73)*0.02)+(IF(AN73<5,1,IF(AN73<10,2,IF(AN73<15,3,IF(AN73<25,4,5))))*0.02)+((6-AO73)*0.01)+(IF(AP73<2,1,IF(AP73<5,2,IF(AP73<10,3,IF(AP73<20,4,5))))*0.008)+(IF(AQ73>60,1,IF(AQ73>30,2,IF(AQ73>14,3,IF(AQ73>7,4,5))))*0.008)+(IF(AR73=0,1,IF(AR73=1,2,IF(AR73=2,3,IF(AR73=3,4,5))))*0.01)+((6-AS73)*0.008)+((6-AT73)*0.008)+(AU73*0.01)+(IF(AV73<1000,1,IF(AV73<5000,2,IF(AV73<20000,3,IF(AV73<50000,4,5))))*0.01),2) -> 1.5 | AX73: =IF(AW73>=4,"SEVERE",IF(AW73>=3.5,"CRITICAL",IF(AW73>=2.5,"HIGH",IF(AW73>=1.5,"MEDIUM","LOW")))) -> MEDIUM
A74: REL-0007 | B74: SAP S4 Finance v2.0 | C74: 46225 | D74: 27 | E74: 150 | F74: 8500 | G74: 5 | H74: 4 | I74: 4 | J74: 58 | K74: 12 | L74: 25 | M74: 75 | N74: 10 | O74: 12 | P74: 2 | Q74: 2 | R74: 8 | S74: 2 | T74: 2 | U74: 1 | V74: 2 | W74: 2 | X74: 12 | Y74: 5 | Z74: 7 | AA74: 2 | AB74: 4 | AC74: 6 | AD74: 2 | AE74: 3 | AF74: 4 | AG74: 2 | AH74: 2 | AI74: 2 | AJ74: 2 | AK74: 90 | AL74: 50 | AM74: 2 | AN74: 22 | AO74: 2 | AP74: 2 | AQ74: 30 | AR74: 3 | AS74: 2 | AT74: 2 | AU74: 5 | AV74: 50000 | AW74: =ROUND((IF(E74<10,1,IF(E74<30,2,IF(E74<60,3,IF(E74<100,4,5))))*0.04)+(IF(F74<200,1,IF(F74<500,2,IF(F74<1500,3,IF(F74<3000,4,5))))*0.03)+(IF(G74=0,1,IF(G74=1,2,IF(G74=2,3,IF(G74<5,4,5))))*0.05)+(IF(H74=0,1,IF(H74=1,2,IF(H74=2,3,IF(H74=3,4,5))))*0.04)+(I74*0.02)+(IF(J74>90,1,IF(J74>80,2,IF(J74>70,3,IF(J74>60,4,5))))*0.06)+(IF(K74<3,1,IF(K74<5,2,IF(K74<7,3,IF(K74<10,4,5))))*0.03)+(IF(L74<3,1,IF(L74<6,2,IF(L74<10,3,IF(L74<15,4,5))))*0.04)+(IF(M74>95,1,IF(M74>85,2,IF(M74>75,3,IF(M74>60,4,5))))*0.02)+(IF(N74<3,1,IF(N74<5,2,IF(N74<7,3,IF(N74<10,4,5))))*0.03)+(IF(O74<2,1,IF(O74<4,2,IF(O74<7,3,IF(O74<10,4,5))))*0.02)+((6-P74)*0.03)+((6-Q74)*0.02)+(IF(R74=0,1,IF(R74<3,2,IF(R74<5,3,IF(R74<10,4,5))))*0.03)+((6-S74)*0.03)+((6-T74)*0.02)+(IF(U74=0,1,3)*0.015)+((6-V74)*0.01)+((6-W74)*0.015)+(IF(X74<3,1,IF(X74<6,2,IF(X74<10,3,IF(X74<15,4,5))))*0.02)+(IF(Y74<2,1,IF(Y74<4,2,IF(Y74<6,3,IF(Y74<8,4,5))))*0.03)+(IF(Z74>14,1,IF(Z74>7,2,IF(Z74>3,3,IF(Z74>1,4,5))))*0.03)+((6-AA74)*0.03)+(IF(AB74=0,1,IF(AB74=1,2,IF(AB74=2,3,IF(AB74=3,4,5))))*0.03)+(IF(AC74<2,1,IF(AC74<4,2,IF(AC74<6,3,IF(AC74<8,4,5))))*0.03)+((6-AD74)*0.02)+(IF(AE74=0,1,IF(AE74=1,3,5))*0.02)+((6-AF74)*0.02)+((6-AG74)*0.02)+((6-AH74)*0.015)+((6-AI74)*0.015)+((6-AJ74)*0.015)+(IF(AK74<15,1,IF(AK74<30,2,IF(AK74<60,3,IF(AK74<120,4,5))))*0.02)+(IF(AL74>90,1,IF(AL74>75,2,IF(AL74>50,3,IF(AL74>25,4,5))))*0.015)+((6-AM74)*0.02)+(IF(AN74<5,1,IF(AN74<10,2,IF(AN74<15,3,IF(AN74<25,4,5))))*0.02)+((6-AO74)*0.01)+(IF(AP74<2,1,IF(AP74<5,2,IF(AP74<10,3,IF(AP74<20,4,5))))*0.008)+(IF(AQ74>60,1,IF(AQ74>30,2,IF(AQ74>14,3,IF(AQ74>7,4,5))))*0.008)+(IF(AR74=0,1,IF(AR74=1,2,IF(AR74=2,3,IF(AR74=3,4,5))))*0.01)+((6-AS74)*0.008)+((6-AT74)*0.008)+(AU74*0.01)+(IF(AV74<1000,1,IF(AV74<5000,2,IF(AV74<20000,3,IF(AV74<50000,4,5))))*0.01),2) -> 4.24 | AX74: =IF(AW74>=4,"SEVERE",IF(AW74>=3.5,"CRITICAL",IF(AW74>=2.5,"HIGH",IF(AW74>=1.5,"MEDIUM","LOW")))) -> SEVERE
A75: REL-0008 | B75: Workday HR Update v5.1 | C75: 46230 | D75: 32 | E75: 42 | F75: 1100 | G75: 2 | H75: 1 | I75: 2 | J75: 75 | K75: 5 | L75: 6 | M75: 92 | N75: 4 | O75: 3 | P75: 3 | Q75: 3 | R75: 1 | S75: 3 | T75: 4 | U75: 0 | V75: 4 | W75: 5 | X75: 5 | Y75: 3 | Z75: 28 | AA75: 4 | AB75: 2 | AC75: 3 | AD75: 4 | AE75: 1 | AF75: 4 | AG75: 3 | AH75: 3 | AI75: 4 | AJ75: 4 | AK75: 35 | AL75: 70 | AM75: 4 | AN75: 12 | AO75: 4 | AP75: 3 | AQ75: 55 | AR75: 1 | AS75: 4 | AT75: 3 | AU75: 2 | AV75: 12000 | AW75: =ROUND((IF(E75<10,1,IF(E75<30,2,IF(E75<60,3,IF(E75<100,4,5))))*0.04)+(IF(F75<200,1,IF(F75<500,2,IF(F75<1500,3,IF(F75<3000,4,5))))*0.03)+(IF(G75=0,1,IF(G75=1,2,IF(G75=2,3,IF(G75<5,4,5))))*0.05)+(IF(H75=0,1,IF(H75=1,2,IF(H75=2,3,IF(H75=3,4,5))))*0.04)+(I75*0.02)+(IF(J75>90,1,IF(J75>80,2,IF(J75>70,3,IF(J75>60,4,5))))*0.06)+(IF(K75<3,1,IF(K75<5,2,IF(K75<7,3,IF(K75<10,4,5))))*0.03)+(IF(L75<3,1,IF(L75<6,2,IF(L75<10,3,IF(L75<15,4,5))))*0.04)+(IF(M75>95,1,IF(M75>85,2,IF(M75>75,3,IF(M75>60,4,5))))*0.02)+(IF(N75<3,1,IF(N75<5,2,IF(N75<7,3,IF(N75<10,4,5))))*0.03)+(IF(O75<2,1,IF(O75<4,2,IF(O75<7,3,IF(O75<10,4,5))))*0.02)+((6-P75)*0.03)+((6-Q75)*0.02)+(IF(R75=0,1,IF(R75<3,2,IF(R75<5,3,IF(R75<10,4,5))))*0.03)+((6-S75)*0.03)+((6-T75)*0.02)+(IF(U75=0,1,3)*0.015)+((6-V75)*0.01)+((6-W75)*0.015)+(IF(X75<3,1,IF(X75<6,2,IF(X75<10,3,IF(X75<15,4,5))))*0.02)+(IF(Y75<2,1,IF(Y75<4,2,IF(Y75<6,3,IF(Y75<8,4,5))))*0.03)+(IF(Z75>14,1,IF(Z75>7,2,IF(Z75>3,3,IF(Z75>1,4,5))))*0.03)+((6-AA75)*0.03)+(IF(AB75=0,1,IF(AB75=1,2,IF(AB75=2,3,IF(AB75=3,4,5))))*0.03)+(IF(AC75<2,1,IF(AC75<4,2,IF(AC75<6,3,IF(AC75<8,4,5))))*0.03)+((6-AD75)*0.02)+(IF(AE75=0,1,IF(AE75=1,3,5))*0.02)+((6-AF75)*0.02)+((6-AG75)*0.02)+((6-AH75)*0.015)+((6-AI75)*0.015)+((6-AJ75)*0.015)+(IF(AK75<15,1,IF(AK75<30,2,IF(AK75<60,3,IF(AK75<120,4,5))))*0.02)+(IF(AL75>90,1,IF(AL75>75,2,IF(AL75>50,3,IF(AL75>25,4,5))))*0.015)+((6-AM75)*0.02)+(IF(AN75<5,1,IF(AN75<10,2,IF(AN75<15,3,IF(AN75<25,4,5))))*0.02)+((6-AO75)*0.01)+(IF(AP75<2,1,IF(AP75<5,2,IF(AP75<10,3,IF(AP75<20,4,5))))*0.008)+(IF(AQ75>60,1,IF(AQ75>30,2,IF(AQ75>14,3,IF(AQ75>7,4,5))))*0.008)+(IF(AR75=0,1,IF(AR75=1,2,IF(AR75=2,3,IF(AR75=3,4,5))))*0.01)+((6-AS75)*0.008)+((6-AT75)*0.008)+(AU75*0.01)+(IF(AV75<1000,1,IF(AV75<5000,2,IF(AV75<20000,3,IF(AV75<50000,4,5))))*0.01),2) -> 2.41 | AX75: =IF(AW75>=4,"SEVERE",IF(AW75>=3.5,"CRITICAL",IF(AW75>=2.5,"HIGH",IF(AW75>=1.5,"MEDIUM","LOW")))) -> MEDIUM
